Workbook

Sheet Resumen
A1: Rootflow — Cierre de septiembre 2026
A2: Todo sin IVA. Ingresos por fecha de entrega; gastos prorrateados por el periodo de cada factura. Sin sueldos de socios ni amortización del equipo. Datos del ERP a 05/10/2026.
A4: 1 · LO QUE DICE EL ERP
A5: Ingresos de septiembre (entregas de septiembre) | B5: =Ingresos!$F$24 -> 899.76 | C5: Hoja Ingresos
A6: (–) Gastos de estructura | B6: =-Gastos!$J$21 -> -665.62226 | C6: Alquiler, luz, agua, basura, software, teléfono, autónomos
A7: (–) Material comprado (sustrato) | B7: =-Gastos!$J$22 -> -61.16
A8: (–) Inversión puntual (bomba y estantería) | B8: =-Gastos!$J$23 -> -130.81
A9: RESULTADO CON LO REGISTRADO | B9: =SUM(B5:B8) -> 42.167742
A11: 2 · RESULTADO OPERATIVO REAL DEL MES (para ver el break-even)
A12: Ingresos de septiembre | B12: =B5 -> 899.76
A13: (–) Gastos de estructura | B13: =B6 -> -665.62226
A14: (–) Material realmente consumido (estimado) | B14: =-Material!$G$27 -> -225.63047 | C14: Semilla y sustrato de las 201 bandejas sembradas para septiembre + envases de lo entregado (hoja Material)
A15: RESULTADO OPERATIVO | B15: =SUM(B12:B14) -> 8.5072758 | C15: Sin la bomba ni la estantería (son inversión, no gasto del mes)
A17: 3 · GASTOS QUE PROBABLEMENTE FALTAN EN EL ERP (confirmar; celdas amarillas)
A18: Gestoría: no hay ninguna cuota registrada desde junio | B18: -99 | C18: Último importe registrado: 119,79 € con IVA (junio). Si ya no hay gestoría, poner 0.
A19: Finetwork: cuota de septiembre (solo consta un recargo por impago) | B19: -21.48 | C19: 25,99 € con IVA, como en julio y agosto. El asiento contable sí recogía 30,99 €.
A20: Autónomos Nico: diferencia hasta la cuota habitual (88,56 − 2,95) | B20: -85.61 | C20: Si la cuota de septiembre fue realmente 2,95 €, poner 0.
A21: RESULTADO OPERATIVO con estos gastos | B21: =B15+SUM(B18:B20) -> -197.58272
A22: … y además facturando a El abuelo Pedro (entregado el 7/09) | B22: =B21+Ingresos!$F$25 -> -73.382724 | C22: Albarán A-2026-0011: 124,20 € sin IVA, entregado y sin factura
A24: 4 · ¿CUÁNTO HAY QUE VENDER AL MES PARA CUBRIR GASTOS?
A25: Material consumido sobre ventas | B25: =IFERROR(Material!$G$27/B5,0) -> 0.25076739
A26: Ventas de equilibrio — con los gastos registrados | B26: =IFERROR(-B6/(1-B25),0) -> 888.40535 | C26: Gastos de estructura ÷ (1 − % de material)
A27: Ventas de equilibrio — si se confirman los gastos que faltan | B27: =IFERROR(-(B6+SUM(B18:B20))/(1-B25),0) -> 1163.4735
A28: Ventas de septiembre | B28: =B5 -> 899.76
A30: 5 · OTRAS FORMAS DE CONTARLO (informativo)
A31: Facturado con fecha de septiembre (por fecha de factura, sin TPV) | B31: =Ingresos!$F$36 -> 745.35 | C31: Incluye la factura de Tequendama del 29/09 (entrega en octubre) y no incluye la F-0014 de Frutas Félix (1/10)
A32: Total gastos registrados imputados a septiembre | B32: =Gastos!$J$24 -> 857.59226

Sheet Ingresos
A1: Ingresos de septiembre 2026 — por fecha de entrega
A2: Base imponible sin IVA. Una venta cuenta en septiembre si se entregó en septiembre, aunque la factura sea de otro mes. Fuente: albaranes, facturas y recibos TPV del ERP.
A4: Entrega | B4: Cliente | C4: Albarán / ticket | D4: Factura | E4: Fecha factura | F4: Base (€) | G4: IVA (€) | H4: Total (€) | I4: ¿Ingreso de septiembre? | J4: Nota
A5: 46266 | B5: La Huerta Hermanos Nieto | C5: A-2026-0009 | D5: F-2026-0010 | E5: 46293 | F5: 116.8 | G5: 4.67 | H5: =F5+G5 -> 121.47 | I5: Sí | J5: 40 cilantro + 20 albahaca 30 g, 20 % dto.
A6: 46273 | B6: La Huerta Hermanos Nieto | C6: A-2026-0013 | D6: F-2026-0010 | E6: 46293 | F6: 116.8 | G6: 4.67 | H6: =F6+G6 -> 121.47 | I6: Sí | J6: Igual, 20 % dto.
A7: 46280 | B7: La Huerta Hermanos Nieto | C7: A-2026-0016 | D7: F-2026-0010 | E7: 46293 | F7: 138.6 | G7: 5.54 | H7: =F7+G7 -> 144.14 | I7: Sí | J7: SIN el 20 % dto. que llevan los demás. El pedido 28 decía 114,00 €. Revisar precio pactado.
A8: 46286 | B8: La Huerta Hermanos Nieto | C8: A-2026-0018 | D8: F-2026-0010 | E8: 46293 | F8: 147.5 | G8: 5.9 | H8: =F8+G8 -> 153.4 | I8: Sí | J8: SIN el 20 % dto.
A9: 46293 | B9: La Huerta Hermanos Nieto | C9: A-2026-0021 | D9: F-2026-0010 | E9: 46293 | F9: 120 | G9: 4.8 | H9: =F9+G9 -> 124.8 | I9: Sí | J9: 20 % dto.
A10: 46268 | B10: Albahaca Ecotienda | C10: A-2026-0010 | D10: F-2026-0003 | E10: 46255 | F10: 48.45 | G10: 1.94 | H10: =F10+G10 -> 50.39 | I10: Sí | J10: La factura figura con fecha 21/08, pero el pedido y la entrega son del 3/09. Cobrada el 21/09.
A11: 46270 | B11: Frutas Félix Vázquez | C11: A-2026-0015 | D11: F-2026-0009 | E11: 46279 | F11: 33 | G11: 1.32 | H11: =F11+G11 -> 34.32 | I11: Sí | J11: Primer pedido.
A12: 46275 | B12: Frutas Félix Vázquez | C12: A-2026-0014 | D12: F-2026-0009 | E12: 46279 | F12: 41.25 | G12: 1.65 | H12: =F12+G12 -> 42.9 | I12: Sí
A13: 46281 | B13: Frutas Félix Vázquez | C13: A-2026-0017 | D13: F-2026-0014 | E13: 46296 | F13: 65.8 | G13: 2.63 | H13: =F13+G13 -> 68.43 | I13: Sí | J13: Entregado en septiembre, facturado el 1/10.
A14: 46289 | B14: Frutas Félix Vázquez | C14: A-2026-0020 | D14: F-2026-0014 | E14: 46296 | F14: 49.45 | G14: 1.98 | H14: =F14+G14 -> 51.43 | I14: Sí | J14: Entregado en septiembre, facturado el 1/10.
A15: 46280 | B15: Venta directa (TPV) | C15: Ticket 5 | D15: — | F15: 4.81 | G15: 0.19 | H15: =F15+G15 -> 5 | I15: Sí
A16: 46281 | B16: Venta directa (TPV) | C16: Ticket 4 | D16: — | F16: 8.65 | G16: 0.35 | H16: =F16+G16 -> 9 | I16: Sí
A17: 46289 | B17: Venta directa (TPV) | C17: Ticket 3 | D17: — | F17: 8.65 | G17: 0.35 | H17: =F17+G17 -> 9 | I17: Sí
A18: 46272 | B18: El abuelo Pedro | C18: A-2026-0011 | D18: SIN FACTURA | F18: 124.2 | G18: 4.97 | H18: =F18+G18 -> 129.17 | I18: Pendiente | J18: Entregado y sin facturar. Se emitieron F-0006 y F-0007 (67,55 € cada una) y luego se borraron del ERP.
A19: 46301 | B19: Tequendama | C19: Pedido 34 | D19: F-2026-0011 | E19: 46294 | F19: 31.4 | G19: 1.26 | H19: =F19+G19 -> 32.66 | I19: No (octubre) | J19: Facturada el 29/09 para un evento que se entrega el 6/10: ingreso de octubre.
A20: 46286 | B20: Tequendama | C20: A-2026-0019 | D20: — | F20: 22.05 | G20: 0.88 | H20: =F20+G20 -> 22.93 | I20: No (cancelado) | J20: El pedido 30 está cancelado, pero el albarán sigue como «entregado».
A21: 46296 | B21: Café El Padrino | C21: A-2026-0022 | D21: F-2026-0015 | E21: 46297 | F21: 10.1 | G21: 0.4 | H21: =F21+G21 -> 10.5 | I21: No (octubre)
A22: 46296 | B22: Venta directa (TPV) | C22: Ticket 2 | D22: — | F22: 8.65 | G22: 0.35 | H22: =F22+G22 -> 9 | I22: No (octubre)
A24: INGRESOS DE SEPTIEMBRE (entregados en septiembre) | F24: =SUMIFS(F5:F22,$I$5:$I$22,"Sí") -> 899.76 | G24: =SUMIFS(G5:G22,$I$5:$I$22,"Sí") -> 35.99 | H24: =SUMIFS(H5:H22,$I$5:$I$22,"Sí") -> 935.75
A25: Pendiente de facturar (El abuelo Pedro) | F25: =SUMIFS(F5:F22,$I$5:$I$22,"Pendiente") -> 124.2
A28: FACTURAS DEL ERP POR FECHA DE FACTURA (informativo)
A29: Fecha factura | B29: Cliente | C29: Factura | D29: Estado cobro | F29: Base (€) | G29: IVA (€) | H29: Total (€) | I29: ¿Fecha en septiembre? | J29: Nota
A30: 46255 | B30: Albahaca Ecotienda | C30: F-2026-0003 | D30: Cobrada 21/09 | F30: 48.45 | G30: 1.94 | H30: =F30+G30 -> 50.39 | I30: No | J30: Fecha probablemente errónea (pedido del 3/09).
A31: 46279 | B31: Frutas Félix Vázquez | C31: F-2026-0009 | D31: Cobrada 21/09 | F31: 74.25 | G31: 2.97 | H31: =F31+G31 -> 77.22 | I31: Sí | J31: En el ERP: estado «pagada» pero cobro «pendiente».
A32: 46293 | B32: La Huerta Hermanos Nieto | C32: F-2026-0010 | D32: Cobrada 02/10 | F32: 639.7 | G32: 25.59 | H32: =F32+G32 -> 665.29 | I32: Sí
A33: 46294 | B33: Tequendama | C33: F-2026-0011 | D33: Pendiente | F33: 31.4 | G33: 1.26 | H33: =F33+G33 -> 32.66 | I33: Sí | J33: Entrega el 6/10.
A34: 46296 | B34: Frutas Félix Vázquez | C34: F-2026-0014 | D34: Pendiente | F34: 115.25 | G34: 4.61 | H34: =F34+G34 -> 119.86 | I34: No | J34: Entregas del 16 y 24/09.
A35: 46297 | B35: Café El Padrino | C35: F-2026-0015 | D35: Pendiente | F35: 10.1 | G35: 0.4 | H35: =F35+G35 -> 10.5 | I35: No
A36: Facturado con fecha de septiembre | F36: =SUMIFS(F30:F35,$I$30:$I$35,"Sí") -> 745.35 | G36: =SUMIFS(G30:G35,$I$30:$I$35,"Sí") -> 29.82 | H36: =SUMIFS(H30:H35,$I$30:$I$35,"Sí") -> 775.17

Sheet Gastos
A1: Gastos imputados a septiembre 2026 — prorrateo por periodo
A2: Base sin IVA (el IVA soportado se recupera). Si una factura cubre varios meses, solo se imputa la parte de septiembre: Imputado = Base × Parte de septiembre ÷ Periodo. Fuente: tabla gastos del ERP y PDF de cada factura.
A4: Nº ERP | B4: Fecha | C4: Proveedor | D4: Concepto (periodo de la factura) | E4: Total pagado (€) | F4: Base sin IVA (€) | G4: Periodo (días o meses) | H4: Parte de septiembre | I4: % imputado | J4: Imputado a sept. (€) | K4: Tipo | L4: Nota
A5: 157 | B5: 46261 | C5: Anthropic | D5: Claude Pro (27/08–27/09) | E5: 18 | F5: 18 | G5: 31 | H5: 26 | I5: =IF(G5>0,H5/G5,0) -> 0.83870968 | J5: =F5*I5 -> 15.096774 | K5: Estructura | L5: 26 de sus 31 días caen en septiembre.
A6: 144 | B6: 46265 | C6: Bellbro Renting | D6: Alquiler del local, septiembre (fra. 000020) | E6: 535.5 | F6: 525 | G6: 1 | H6: 1 | I6: =IF(G6>0,H6/G6,0) -> 1 | J6: =F6*I6 -> 525 | K6: Estructura | L6: 525 € + 110,25 € IVA − 99,75 € retención IRPF = 535,50 €. La retención se ingresa en Hacienda (modelo 115): el coste es 525 €.
A7: 140 | B7: 46268 | C7: Leroy Merlin | D7: Bomba y tubos | E7: 93.29 | F7: 77.1 | G7: 1 | H7: 1 | I7: =IF(G7>0,H7/G7,0) -> 1 | J7: =F7*I7 -> 77.1 | K7: Inversión | L7: Equipo puntual, no gasto recurrente.
A8: 136 | B8: 46269 | C8: Seguridad Social | D8: Cuota de autónomos (Nico) | E8: 2.95 | F8: 2.95 | G8: 1 | H8: 1 | I8: =IF(G8>0,H8/G8,0) -> 1 | J8: =F8*I8 -> 2.95 | K8: Estructura | L8: De mayo a agosto la cuota fue de 88,56 €. Confirmar si la de septiembre es realmente 2,95 €.
A9: 141 | B9: 46279 | C9: Leroy Merlin | D9: Estantería | E9: 64.99 | F9: 53.71 | G9: 1 | H9: 1 | I9: =IF(G9>0,H9/G9,0) -> 1 | J9: =F9*I9 -> 53.71 | K9: Inversión | L9: Equipo puntual.
A10: 158 | B10: 46281 | C10: Anthropic | D10: Claude, uso extra prepago | E10: 20 | F10: 20 | G10: 1 | H10: 1 | I10: =IF(G10>0,H10/G10,0) -> 1 | J10: =F10*I10 -> 20 | K10: Estructura
A11: 146 | B11: 46286 | C11: Finetwork | D11: Recargo por impago de una factura anterior | E11: 5 | F11: 4.13 | G11: 1 | H11: 1 | I11: =IF(G11>0,H11/G11,0) -> 1 | J11: =F11*I11 -> 4.13 | K11: Estructura | L11: No es la cuota mensual: es un recargo por una factura devuelta. La cuota de septiembre no está en el ERP.
A12: 151 | B12: 46288 | C12: Organik Green Zone | D12: Sustrato: 4 sacos de coco de 100 L | E12: 74 | F12: 61.16 | G12: 1 | H12: 1 | I12: =IF(G12>0,H12/G12,0) -> 1 | J12: =F12*I12 -> 61.16 | K12: Material | L12: Compra del mes. En la hoja Material se compara con lo realmente consumido.
A13: 156 | B13: 46292 | C13: Anthropic | D13: Claude Pro (27/09–27/10) | E13: 18 | F13: 18 | G13: 30 | H13: 4 | I13: =IF(G13>0,H13/G13,0) -> 0.13333333 | J13: =F13*I13 -> 2.4 | K13: Estructura | L13: 4 de sus 30 días caen en septiembre.
A14: 159 | B14: 46292 | C14: Anthropic | D14: Claude Pro (27/09–27/10) — DUPLICADO | E14: 18 | F14: 18 | G14: 30 | H14: 0 | I14: =IF(G14>0,H14/G14,0) -> 0 | J14: =F14*I14 -> 0 | K14: Duplicado | L14: Es el mismo PDF que el gasto 156 (factura 8OGMHWLR-0031). Borrar uno de los dos en el ERP.
A15: 153 | B15: 46295 | C15: Bellbro Renting | D15: Alquiler del local, octubre | E15: 535.5 | F15: 525 | G15: 1 | H15: 0 | I15: =IF(G15>0,H15/G15,0) -> 0 | J15: =F15*I15 -> 0 | K15: Otro mes | L15: Es de octubre.
A16: 154 | B16: 46295 | C16: Bellbro Renting | D16: Agua (10/07–08/09) | E16: 30.71 | F16: 27.92 | G16: 60 | H16: 30 | I16: =IF(G16>0,H16/G16,0) -> 0.5 | J16: =F16*I16 -> 13.96 | K16: Estructura | L16: Tarifa diaria de la última factura × 30 días (8 días ya facturados + 22 estimados hasta la próxima).
A17: 155 | B17: 46295 | C17: Bellbro Renting | D17: Luz repercutida (15/07–15/09) | E17: 137.51 | F17: 134.82 | G17: 62 | H17: 30 | I17: =IF(G17>0,H17/G17,0) -> 0.48387097 | J17: =F17*I17 -> 65.235484 | K17: Estructura | L17: Tarifa diaria × 30 días (15 días facturados + 15 estimados). 134,82 € + 28,31 € IVA − 25,62 € IRPF.
A18: 124 | B18: 46199 | C18: Bellbro Renting | D18: Tasa de basura 2026, parte proporcional («6 de 12») | E18: 101.1 | F18: 101.1 | G18: 6 | H18: 1 | I18: =IF(G18>0,H18/G18,0) -> 0.16666667 | J18: =F18*I18 -> 16.85 | K18: Estructura | L18: Cubre 6 meses: se imputa 1/6 a septiembre. Exenta de IVA.
A19: 152 | B19: 46296 | C19: Proveedor (Polonia) | D19: Semillas | E19: 354.52 | F19: 292.99 | G19: 1 | H19: 0 | I19: =IF(G19>0,H19/G19,0) -> 0 | J19: =F19*I19 -> 0 | K19: Otro mes | L19: Compra de octubre para stock. En septiembre se sembró con semilla de junio: ver hoja Material.
D21: Gastos de estructura | J21: =SUMIFS($J$5:$J$19,$K$5:$K$19,"Estructura") -> 665.62226
D22: Material comprado en septiembre | J22: =SUMIFS($J$5:$J$19,$K$5:$K$19,"Material") -> 61.16
D23: Inversión puntual (equipo) | J23: =SUMIFS($J$5:$J$19,$K$5:$K$19,"Inversión") -> 130.81
D24: TOTAL GASTOS REGISTRADOS IMPUTADOS A SEPTIEMBRE | J24: =SUM(J21:J23) -> 857.59226

Sheet Material
A1: Material consumido en septiembre (estimado)
A2: En septiembre no se compró semilla (la última compra es de junio y la siguiente del 1/10) y los envases se compraron en agosto. Para medir el mes de verdad, se estima lo consumido a partir de las bandejas sembradas y las tarrinas entregadas.
A4: 1 · SEMILLA — bandejas sembradas para septiembre (tabla lotes del ERP)
A5: Variedad | B5: Bandejas con fecha de AGOSTO en el ERP | C5: Bandejas con fecha de SEPTIEMBRE | D5: Total bandejas | E5: g de semilla por bandeja | F5: €/kg de semilla (sin IVA) | G5: Coste (€) | H5: Fuente
A6: Cilantro | B6: 45 | C6: 53 | D6: =B6+C6 -> 98 | E6: 34 | F6: 7.5 | G6: =D6*E6/1000*F6 -> 24.99 | H6: g/bandeja: ERP · €/kg: COSTES_ROOTFLOW
A7: Albahaca | B7: 30 | C7: 49 | D7: =B7+C7 -> 79 | E7: 14 | F7: 37 | G7: =D7*E7/1000*F7 -> 40.922 | H7: g/bandeja: ERP · €/kg: COSTES_ROOTFLOW
A8: Mostaza | B8: 1 | C8: 5 | D8: =B8+C8 -> 6 | E8: 25 | F8: 22 | G8: =D8*E8/1000*F8 -> 3.3 | H8: g/bandeja: ERP · €/kg: COSTES_ROOTFLOW
A9: Amaranto | B9: 1 | C9: 4 | D9: =B9+C9 -> 5 | E9: 9 | F9: 50 | G9: =D9*E9/1000*F9 -> 2.25 | H9: COSTES_ROOTFLOW (el ERP no tiene la dosis)
A10: Rúcula | B10: 1 | C10: 3 | D10: =B10+C10 -> 4 | E10: 15 | F10: 11 | G10: =D10*E10/1000*F10 -> 0.66 | H10: COSTES_ROOTFLOW (el ERP no tiene la dosis)
A11: Rábano verde / daikon | B11: 1 | C11: 3 | D11: =B11+C11 -> 4 | E11: 34 | F11: 10 | G11: =D11*E11/1000*F11 -> 1.36 | H11: COSTES_ROOTFLOW (el ERP no tiene la dosis)
A12: Rábano red | B12: 1 | C12: 3 | D12: =B12+C12 -> 4 | E12: 34 | F12: 9.9 | G12: =D12*E12/1000*F12 -> 1.3464 | H12: COSTES_ROOTFLOW (rábano rose)
A13: Remolacha roja | B13: 1 | C13: 0 | D13: =B13+C13 -> 1 | G13: =D13*0.6 -> 0.6 | H13: Sin dosis en el ERP ni en COSTES: 0,60 € por bandeja del modelo V16 (provisional)
A14: Total semilla | B14: =SUM(B6:B13) -> 81 | C14: =SUM(C6:C13) -> 120 | D14: =SUM(D6:D13) -> 201 | G14: =SUM(G6:G13) -> 75.4284
A15: En agosto no se sembró (producción parada): los 12 lotes con fecha 17-28/08 tienen la fecha mal y son los que se cosecharon y vendieron en septiembre, así que su semilla y sustrato son consumo de septiembre. Cuadra con las ventas: lo entregado en septiembre (~14 kg) pide unas 110 bandejas.
A17: 2 · SUSTRATO
A18: Concepto | D18: Bandejas | E18: Litros por bandeja | F18: €/litro (sin IVA) | G18: Coste (€) | H18: Fuente
A19: Sustrato de coco | D19: =D14 -> 201 | E19: 2.5 | F19: =18/1.21/100 -> 0.14876033 | G19: =D19*E19*F19 -> 74.752066 | H19: COSTES_ROOTFLOW: saco de 100 L a 18 € con IVA, 2,5 L por bandeja
A21: 3 · ENVASES — tarrinas entregadas en septiembre (albaranes)
A22: Formato | D22: Tarrinas | F22: € por tarrina (sin IVA) | G22: Coste (€) | H22: Fuente
A23: Tarrina grande (28-100 g) | D23: 385 | F23: 0.17 | G23: =D23*F23 -> 65.45 | H23: COSTES_ROOTFLOW · incluye las 55 de El abuelo Pedro
A24: Tarrina pequeña (5-15 g) | D24: 100 | F24: 0.1 | G24: =D24*F24 -> 10 | H24: COSTES_ROOTFLOW
A25: Total envases | G25: =SUM(G23:G24) -> 75.45
A27: MATERIAL CONSUMIDO EN SEPTIEMBRE (semilla + sustrato + envases) | G27: =G14+G19+G25 -> 225.63047
A28: Compra de sustrato registrada en septiembre (hoja Gastos), para comparar | G28: =Gastos!$J$22 -> 61.16

Sheet Incidencias ERP
A1: Incidencias del ERP encontradas al hacer el cierre
A2: No se ha modificado nada en el ERP: solo se ha leído. Conviene revisarlas con la gestoría.
A4: # | B4: Dónde | C4: Qué pasa | D4: Qué hacer
A5: 1 | B5: Contabilidad (asientos) | C5: El diario conserva asientos de 7 facturas que ya no existen (F-0004 a F-0008, F-0012 y F-0013). La F-0010 aparece dos veces: una de Tequendama (26,50 €) y otra de La Huerta por 788,10 € (la factura real es de 639,70 €). El alquiler de septiembre está contabilizado dos veces (GAS-144 y GAS-145). | D5: Regenerar o depurar los asientos. Hoy la contabilidad del ERP infla las ventas y los gastos de septiembre.
A6: 2 | B6: Numeración de facturas | C6: Faltan los números F-0004 a F-0008, F-0012 y F-0013 porque se borraron. | D6: La numeración debe ser correlativa: una factura emitida se anula con una rectificativa, no se borra. Consultar a la gestoría.
A7: 3 | B7: Cobros | C7: Hay un cobro de 87,36 € (14/09) asignado a la F-0005, que ya no existe. Frutas Félix pagó además la F-0009 (77,22 €) el 21/09. | D7: Comprobar en el banco si Frutas Félix pagó dos veces o si el cobro está mal asignado.
A8: 4 | B8: Alquiler y luz (IVA e IRPF) | C8: El ERP contabiliza 535,50 € como 442,56 € + 21 % IVA. La factura real es de 525 € + 110,25 € IVA − 99,75 € de retención IRPF (y la luz repercutida igual). | D8: Contabilizar base, IVA y retención por separado y presentar el modelo 115 trimestral.
A9: 5 | B9: El abuelo Pedro | C9: Albarán A-2026-0011 (7/09, 124,20 € sin IVA) entregado y sin factura. | D9: Emitir la factura (o marcarlo como muestra si lo era).
A10: 6 | B10: Tequendama | C10: Pedido 30 cancelado, pero su albarán A-2026-0019 figura como «entregado». La F-0011 (29/09) es de un pedido que se entrega el 6/10. | D10: Anular el albarán. Revisar si la factura del evento debía emitirse antes de la entrega.
A11: 7 | B11: La Huerta | C11: Los albaranes A-0016 y A-0018 van sin el 20 % de descuento que llevan los demás; el pedido 28 decía 114,00 € y el albarán 138,60 €. La factura ya está cobrada. | D11: Confirmar el precio pactado con el cliente.
A12: 8 | B12: Albahaca Ecotienda | C12: La F-2026-0003 tiene fecha 21/08, pero el pedido y la entrega son del 3/09. | D12: Revisar la fecha de la factura.
A13: 9 | B13: Gastos duplicados | C13: Los gastos 156 y 159 son la misma factura de Anthropic (18 €, 27/09). | D13: Borrar uno.
A14: 10 | B14: Lotes de producción | C14: Hay 12 lotes (81 bandejas) con fecha de siembra 17-28/08, cuando en agosto no se sembró. Y varios lotes de septiembre siguen como «sembrado» pasado su ciclo (p. ej. el lote 71, cilantro del 1/09). | D14: Corregir las fechas y cerrar los lotes cosechados: el coste de producción por lote depende de ello.
A15: 11 | B15: Gastos que faltan | C15: No hay gestoría desde junio, falta la cuota de septiembre de Finetwork (solo hay un recargo por impago) y la cuota de autónomos de septiembre figura en 2,95 € (antes 88,56 €). | D15: Subir las facturas que falten para que el cierre sea completo.
