Workbook

Sheet Portada
B2: ROOTFLOW HYDROPONICS S.L.
B3: Modelo financiero V17 — Ronda: inversor privado (capital) + ENISA
B4: Microbrotes y flores comestibles · Madrid · DOS líneas de negocio: distribución + restaurantes
B6: Qué hay dentro
B7: · PRODUCTO: rendimiento, ciclos y coste bottom-up por variedad; TARIFAS REALES por canal (mayorista, tienda, restaurante).
B8: · TARIFAS: hoja para cargar el export del ERP (no alimenta todavía el modelo).
B9: · RESTAURANTES: la palanca (% de la nave para restaurantes), ticket, riders, microhub, lanzadera, captación, agosto y techo de mercado con el censo municipal.
B10: · PIPELINE: clientes de distribución identificados. Alimentan la demanda de la línea de distribución.
B11: · HIPÓTESIS: escenarios, nóminas, financiación y estructura del inversor (capital 10 %, suelo 1,5×, salida año 4).
B12: · LOGÍSTICA: distribución con furgo propia en Madrid y Athos fuera. CAPEX: nave, automatización, microhub y fianzas.
B13: · MODELO_MENSUAL (escenario activo) y Esc_* (los tres casos, 84 meses). Bloque de líneas de negocio en filas 168-217.
B14: · LINEAS_NEGOCIO: cuenta de resultados por línea (distribución, restaurantes y costes comunes), cuadrada con el EBITDA.
... B37: V17 · Octubre 2026

Sheet Resumen
A1: ROOTFLOW — Resumen para ENISA e inversores
A2: Cuadro de mando. Portfolio real + demanda identificada + capital stack.
A4: COMPARATIVA DE ESCENARIOS — se recalcula sola al cambiar cualquier variable del modelo
A5: Palanca / resultado | C5: CONSERVADOR | D5: BASE | E5: OPTIMISTA
A6: LO QUE SE MODIFICA EN CADA CASO
A7: Minutos por bandeja | C7: =Producto!$D$8 -> 4 | D7: =Producto!$D$9 -> 3 | E7: =Producto!$D$10 -> 2
A8: Precio — línea distribución (índice sobre tarifa actual) | C8: =Hipótesis!$C$16 -> 0.9 | D8: =Hipótesis!$D$16 -> 1 | E8: =Hipótesis!$E$16 -> 1.1
A9: Coste de producto (índice sobre el coste bottom-up) | C9: =Hipótesis!$C$18 -> 1.05 | D9: =Hipótesis!$D$18 -> 1 | E9: =Hipótesis!$E$18 -> 0.9
A10: Inversión en automatización (€) | C10: =CAPEX!$E$10 -> 0 | D10: =CAPEX!$F$10 -> 10000 | E10: =CAPEX!$G$10 -> 35000
A11: Inversión total = necesidad de financiación (€) | C11: =CAPEX!$E$26 -> 161048 | D11: =CAPEX!$F$26 -> 173048 | E11: =CAPEX!$G$26 -> 196598
A12: PLANTILLA (se calcula sola según los minutos)
A13: Operarios de cultivo en régimen (nº) | C13: =Esc_Conservador!$CH$30 -> 6 | D13: =Esc_Base!$CH$30 -> 4 | E13: =Esc_Optimista!$CH$30 -> 2
A14: Plantilla TOTAL en régimen (nº) | C14: =Esc_Conservador!$CH$31 -> 11 | D14: =Esc_Base!$CH$31 -> 9 | E14: =Esc_Optimista!$CH$31 -> 7
A15: Coste de nóminas en régimen (€/mes) | C15: =-Esc_Conservador!$CH$51 -> 46141.316 | D15: =-Esc_Base!$CH$51 -> 40782.41 | E15: =-Esc_Optimista!$CH$51 -> 35423.503
A16: RESULTADO EN RÉGIMEN (año 5)
A17: Ingresos (€) | C17: =SUM(Esc_Conservador!$AY$36:$BJ$36) -> 1452128.7 | D17: =SUM(Esc_Base!$AY$36:$BJ$36) -> 1720250.3 | E17: =SUM(Esc_Optimista!$AY$36:$BJ$36) -> 1980363.9
A18: EBITDA (€) | C18: =SUM(Esc_Conservador!$AY$56:$BJ$56) -> 388642.64 | D18: =SUM(Esc_Base!$AY$56:$BJ$56) -> 713969.37 | E18: =SUM(Esc_Optimista!$AY$56:$BJ$56) -> 1051015.8
A19: Margen EBITDA (%) | C19: =IFERROR(SUM(Esc_Conservador!$AY$56:$BJ$56)/SUM(Esc_Conservador!$AY$36:$BJ$36),0) -> 0.2676365 | D19: =IFERROR(SUM(Esc_Base!$AY$56:$BJ$56)/SUM(Esc_Base!$AY$36:$BJ$36),0) -> 0.41503807 | E19: =IFERROR(SUM(Esc_Optimista!$AY$56:$BJ$56)/SUM(Esc_Optimista!$AY$36:$BJ$36),0) -> 0.53071854
A20: Producción (kg/mes) | C20: =Esc_Conservador!$CH$26 -> 2970.9393 | D20: =Esc_Base!$CH$26 -> 3128.4564 | E20: =Esc_Optimista!$CH$26 -> 3246.5942
A21: RESULTADO DE LA OPERACIÓN
A22: Ingresos año 1 (€) | C22: =Esc_Conservador!$C$147 -> 193490.03 | D22: =Esc_Base!$C$147 -> 248408.39 | E22: =Esc_Optimista!$C$147 -> 311861.83
A23: Caja mínima del plan (€) | C23: =Esc_Conservador!$C$146 -> 30000 | D23: =Esc_Base!$C$146 -> 30000 | E23: =Esc_Optimista!$C$146 -> 30000
A24: DSCR mínimo (años 2-7) | C24: =Esc_Conservador!$C$145 -> 9.5465253 | D24: =Esc_Base!$C$145 -> 15.940181 | E24: =Esc_Optimista!$C$145 -> 20.439219
A25: TIR del inversor (TAE) | C25: =IFERROR(Esc_Conservador!$C$128,0) -> 0.28212158 | D25: =IFERROR(Esc_Base!$C$128,0) -> 0.50716006 | E25: =IFERROR(Esc_Optimista!$C$128,0) -> 0.66568722
A26: MOIC (múltiplo) | C26: =Esc_Conservador!$C$129 -> 2.702196 | D26: =Esc_Base!$C$129 -> 5.1598551 | E26: =Esc_Optimista!$C$129 -> 7.6979274
A27: Payback del inversor (meses) | C27: =Esc_Conservador!$C$130 -> 48 | D27: =Esc_Base!$C$130 -> 48 | E27: =Esc_Optimista!$C$130 -> 48
A28: Financiación levantada (€) | C28: =Hipótesis!$D$122 -> 200000 | D28: =Hipótesis!$D$122 -> 200000 | E28: =Hipótesis!$D$122 -> 200000
A29: Póliza de crédito — máximo dispuesto (€) | C29: =Esc_Conservador!$C$150 -> 29593.795 | D29: =Esc_Base!$C$150 -> 15580.848 | E29: =Esc_Optimista!$C$150 -> 10049.702
A30: LO QUE SE LLEVA CADA SOCIO (30% cada uno)
A31: Neto €/mes en el año 3 (sueldo) | C31: =Esc_Conservador!$E$149 -> 2800 | D31: =Esc_Base!$E$149 -> 2800 | E31: =Esc_Optimista!$E$149 -> 2800
A32: Neto €/mes en el año 5 (sueldo + dividendo) | C32: =Esc_Conservador!$G$149 -> 3500 | D32: =Esc_Base!$G$149 -> 3500 | E32: =Esc_Optimista!$G$149 -> 3500
A33: Neto €/mes en el año 7 (sueldo + dividendo) | C33: =Esc_Conservador!$I$149 -> 4200 | D33: =Esc_Base!$I$149 -> 4200 | E33: =Esc_Optimista!$I$149 -> 4200
A34: Dividendos cobrados por socio en 7 años (neto) | C34: =SUM(Esc_Conservador!$C$117:$CH$117) -> 0 | D34: =SUM(Esc_Base!$C$117:$CH$117) -> 0 | E34: =SUM(Esc_Optimista!$C$117:$CH$117) -> 0
A35: Fondo Hito 4 acumulado (€) | C35: =Esc_Conservador!$CH$115 -> 408483.29 | D35: =Esc_Base!$CH$115 -> 789076.66 | E35: =Esc_Optimista!$CH$115 -> 1180015.9
A36: Caja + fondo Hito 4 en la empresa (año 7) | C36: =Esc_Conservador!$CH$86+Esc_Conservador!$CH$115 -> 1131856.2 | D36: =Esc_Base!$CH$86+Esc_Base!$CH$115 -> 2484862.8 | E36: =Esc_Optimista!$CH$86+Esc_Optimista!$CH$115 -> 3878963.6
A37: · de eso, le corresponde a CADA socio (30%) | C37: =(Esc_Conservador!$CH$86+Esc_Conservador!$CH$115)*Hipótesis!$D$82 -> 339556.86 | D37: =(Esc_Base!$CH$86+Esc_Base!$CH$115)*Hipótesis!$D$82 -> 745458.85 | E37: =(Esc_Optimista!$CH$86+Esc_Optimista!$CH$115)*Hipótesis!$D$82 -> 1163689.1
A38: Valor de su 30% al múltiplo de salida | C38: =Esc_Conservador!$C$133*Hipótesis!$D$82 -> 810658.79 | D38: =Esc_Base!$C$133*Hipótesis!$D$82 -> 1547956.5 | E38: =Esc_Optimista!$C$133*Hipótesis!$D$82 -> 2309378.2
A40: ¿La financiación CUBRE la necesidad? | C40: =IF(Hipótesis!$D$122>=CAPEX!$E$26,"SÍ","NO — faltan "&TEXT(CAPEX!$E$26-Hipótesis!$D$122,"#,##0")&" €") -> SÍ | D40: =IF(Hipótesis!$D$122>=CAPEX!$F$26,"SÍ","NO — faltan "&TEXT(CAPEX!$F$26-Hipótesis!$D$122,"#,##0")&" €") -> SÍ | E40: =IF(Hipótesis!$D$122>=CAPEX!$G$26,"SÍ","NO — faltan "&TEXT(CAPEX!$G$26-Hipótesis!$D$122,"#,##0")&" €") -> SÍ
A41: Todo lo de arriba son FÓRMULAS: cambia precios, minutos, SUELDOS, circulante o CAPEX y los tres casos se actualizan a la vez.
A42: El circulante (clientes a 30 días) se financia con la póliza, no con la ronda de la caja. El fondo Hito 4 aparta dinero para la siguiente ampliación.
A44: ESCENARIO ACTIVO EN EL MODELO (detalle mensual y financiación)
A45: Caja mínima acumulada (€) | C45: =MIN(Modelo_Mensual!$C$86:$CH$86) -> 30000
A46: DSCR mínimo años 2-7 | C46: =MIN(Resumen_Anual!$D$23:$I$23) -> 15.940181
A47: Precio medio ponderado — mayorista (€/kg) | C47: =Producto!$D$35 -> 43.670034
A48: Plantilla total en régimen (nº) | C48: =Modelo_Mensual!$CH$31 -> 9
A49: Producción en régimen (kg/mes) | C49: =Modelo_Mensual!$CH$26 -> 3128.4564
A50: % del AÑO 1 ya identificado | C50: =IFERROR(SUM(Modelo_Mensual!$C$184:$N$184)/SUM(Modelo_Mensual!$C$36:$N$36),0) -> 0.48309811
A51: Pipeline ponderado por probabilidad (€/mes) | C51: =Pipeline!$R$23 -> 32131.275
A52: Payback (meses) | C52: =Modelo_Mensual!$C$130 -> 48
A53: Estructura del tramo inversor | C53: =CHOOSE(Hipótesis!$D$94,"Préstamo simple","Préstamo participativo","Cuentas en participación","Revenue-share","Capital (equity)") -> Capital (equity)
A54: Coste efectivo ENISA (TAE) | C54: =Modelo_Mensual!$C$136 -> 0.17416682
A55: Múltiplo (MOIC) | C55: =Modelo_Mensual!$C$129 -> 5.1598551
A57: DEMANDA — PIPELINE (escenario activo)
A58: TIR anual del inversor (TAE) | C58: =Modelo_Mensual!$C$128 -> 0.50716006
A59: ¿Cubre la inversión? | C59: =IF(Hipótesis!$D$122>=CAPEX!$C$26,"SÍ","NO — faltan "&TEXT(CAPEX!$C$26-Hipótesis!$D$122,"#,##0")&" €") -> SÍ
A60: Necesidad de inversión (€) | C60: =CAPEX!$C$26 -> 173048
A61: Total financiación levantada (€) | C61: =Hipótesis!$D$122 -> 200000
A62: Escenario activo | C62: =CHOOSE(Hipótesis!$C$4,"CONSERVADOR","BASE","OPTIMISTA") -> BASE
A64: LÍNEA RESTAURANTES vs DISTRIBUCIÓN — año 5 (régimen)
C65: CONSERVADOR | D65: BASE | E65: OPTIMISTA
A66: Precio restaurantes (índice sobre tarifa 30 g) | C66: =Restaurantes!$C$26 -> 0.9 | D66: =Restaurantes!$D$26 -> 1 | E66: =Restaurantes!$E$26 -> 1.1
A67: % de la nave reservado a restaurantes (objetivo) | C67: =Restaurantes!$D$7 -> 0.05 | D67: =Restaurantes!$D$7 -> 0.05 | E67: =Restaurantes!$D$7 -> 0.05
A68: Restaurantes en cartera (mes 60) | C68: =Esc_Conservador!$BJ$196 -> 113.21622 | D68: =Esc_Base!$BJ$196 -> 123.0611 | E68: =Esc_Optimista!$BJ$196 -> 130.44477
A69: Techo de restaurantes alcanzables | C69: =Restaurantes!$D$13 -> 175.5 | D69: =Restaurantes!$D$13 -> 175.5 | E69: =Restaurantes!$D$13 -> 175.5
A70: Pedidos al mes (media año 5) | C70: =SUM(Esc_Conservador!$AY$188:$BJ$188)/12 -> 914.3099 | D70: =SUM(Esc_Base!$AY$188:$BJ$188)/12 -> 993.81511 | E70: =SUM(Esc_Optimista!$AY$188:$BJ$188)/12 -> 1053.444
A71: Riders (mes 60) | C71: =Esc_Conservador!$BJ$200 -> 2 | D71: =Esc_Base!$BJ$200 -> 2 | E71: =Esc_Optimista!$BJ$200 -> 2
A72: % de la producción (kg) a restaurantes | C72: =IFERROR(SUM(Esc_Conservador!$AY$181:$BJ$181)/SUM(Esc_Conservador!$AY$26:$BJ$26),0) -> 0.051706036 | D72: =IFERROR(SUM(Esc_Base!$AY$181:$BJ$181)/SUM(Esc_Base!$AY$26:$BJ$26),0) -> 0.053379224 | E72: =IFERROR(SUM(Esc_Optimista!$AY$181:$BJ$181)/SUM(Esc_Optimista!$AY$26:$BJ$26),0) -> 0.054527814
A73: Ingresos restaurantes (año 5) | C73: =SUM(Esc_Conservador!$AY$35:$BJ$35) -> 285621.27 | D73: =SUM(Esc_Base!$AY$35:$BJ$35) -> 344953.22 | E73: =SUM(Esc_Optimista!$AY$35:$BJ$35) -> 402215.46
A74: % de los ingresos de restaurantes | C74: =IFERROR(SUM(Esc_Conservador!$AY$35:$BJ$35)/SUM(Esc_Conservador!$AY$36:$BJ$36),0) -> 0.19669143 | D74: =IFERROR(SUM(Esc_Base!$AY$35:$BJ$35)/SUM(Esc_Base!$AY$36:$BJ$36),0) -> 0.20052502 | E74: =IFERROR(SUM(Esc_Optimista!$AY$35:$BJ$35)/SUM(Esc_Optimista!$AY$36:$BJ$36),0) -> 0.2031018
A75: Margen de contribución restaurantes (año 5) | C75: =SUM(Esc_Conservador!$AY$215:$BJ$215) -> 178850.59 | D75: =SUM(Esc_Base!$AY$215:$BJ$215) -> 239866.59 | E75: =SUM(Esc_Optimista!$AY$215:$BJ$215) -> 294318.43
A76: · sobre sus ingresos | C76: =IFERROR(SUM(Esc_Conservador!$AY$215:$BJ$215)/SUM(Esc_Conservador!$AY$35:$BJ$35),0) -> 0.62618091 | D76: =IFERROR(SUM(Esc_Base!$AY$215:$BJ$215)/SUM(Esc_Base!$AY$35:$BJ$35),0) -> 0.69535977 | E76: =IFERROR(SUM(Esc_Optimista!$AY$215:$BJ$215)/SUM(Esc_Optimista!$AY$35:$BJ$35),0) -> 0.73174319
A77: Margen de contribución distribución (año 5) | C77: =SUM(Esc_Conservador!$AY$214:$BJ$214) -> 772833.76 | D77: =SUM(Esc_Base!$AY$214:$BJ$214) -> 972655.09 | E77: =SUM(Esc_Optimista!$AY$214:$BJ$214) -> 1179870.8
A78: · sobre sus ingresos | C78: =IFERROR(SUM(Esc_Conservador!$AY$214:$BJ$214)/SUM(Esc_Conservador!$AY$34:$BJ$34),0) -> 0.66251938 | D78: =IFERROR(SUM(Esc_Base!$AY$214:$BJ$214)/SUM(Esc_Base!$AY$34:$BJ$34),0) -> 0.70723272 | E78: =IFERROR(SUM(Esc_Optimista!$AY$214:$BJ$214)/SUM(Esc_Optimista!$AY$34:$BJ$34),0) -> 0.74762981
A79: Coste de última milla por pedido (año 5) | C79: =IFERROR(-SUM(Esc_Conservador!$AY$207:$BJ$207)/SUM(Esc_Conservador!$AY$188:$BJ$188),0) -> 5.4278832 | D79: =IFERROR(-SUM(Esc_Base!$AY$207:$BJ$207)/SUM(Esc_Base!$AY$188:$BJ$188),0) -> 4.4202227 | E79: =IFERROR(-SUM(Esc_Optimista!$AY$207:$BJ$207)/SUM(Esc_Optimista!$AY$188:$BJ$188),0) -> 4.0695639

Sheet Producto
A1: ROOTFLOW — Portfolio de producto y COGS reales
A2: Coste real por bandeja (semilla + sustrato + envase, sin IVA). Solo se produce lo ACTIVO. El % de luz de las activas debe sumar 100%.
A4: Parámetros globales
A5: (obsoleto desde V17) Ratio precio DIRECTO ÷ DISTRIBUCIÓN — los precios por canal están en las columnas de tarifas | D5: 1.3
A6: Días medios por mes (365/12) | D6: 30.42
A7: Días muertos entre ciclos (limpieza/resiembra) | D7: 0 | F7: INPUT. Ciclos/mes = 30,42 ÷ (días de luz + días muertos). Con 1 día muerto, un rábano de 3 días de luz pasa de 10,1 a 7,6 ciclos/mes.
A8: Minutos por bandeja — CONSERVADOR (a mano, sin automatización) | D8: 4 | F8: CLAVE: el tiempo por bandeja es LA variable del negocio y define cuántos operarios hacen falta. Cada nivel de minutos se consigue con la automatización del CAPEX (ver hoja CAPEX).
A9: Minutos por bandeja — BASE (lavadora + cinta/cosecha asistida) | D9: 3
A10: Minutos por bandeja — OPTIMISTA (+ sembradora automática) | D10: 2
A11: MINUTOS POR BANDEJA — según escenario activo | D11: =CHOOSE(Hipótesis!$C$4,D8,D9,D10) -> 3
A12: Coste envase tarrina PEQUEÑA (5-15 g), sin IVA | D12: 0.1 | F12: COSTES_ROOTFLOW.xlsx · hoja 1
A13: Coste envase tarrina GRANDE (30-100 g), sin IVA | D13: 0.17 | F13: COSTES_ROOTFLOW.xlsx · hoja 1
A14: Sustrato por bandeja, sin IVA (saco 100 L a 18 € con IVA; 2,5 L por bandeja) | D14: =(18/1.21)*(2.5/100) -> 0.37190083 | F14: COSTES_ROOTFLOW.xlsx · hoja 1
A15: Variedad | B15: Estado dato | C15: Activo (1/0) | D15: % luz (bandejas) | E15: Formato MAYORISTA (g) | F15: Precio MAYORISTA €/tarrina | G15: €/kg MAYORISTA | H15: Días luz | I15: Días germ. | J15: Ciclos/mes — calc | K15: Rendim. (g/band) | L15: Tarrinas/band mayorista | M15: kg/band /mes — calc | N15: Semilla €/band | O15: Sustrato €/band | P15: Envase €/tarrina (may.) | Q15: Envase €/band — calc | R15: COGS €/band /ciclo (may.) | S15: COGS MAYOR. €/band/mes | T15: Ingreso MAYOR. €/band/mes | U15: MB % | V15: MARGEN €/hora trabajo | W15: Formato RESTAUR. (g) | X15: Precio RESTAUR. €/tarrina | Y15: €/kg RESTAUR. | Z15: Tarrinas/band restaur. | AA15: Envase rest. €/tarrina | AB15: Ingreso RESTAUR. €/band/mes | AC15: COGS RESTAUR. €/band/mes | AD15: Formato TIENDA (g) | AE15: Precio TIENDA €/tarrina | AF15: €/kg TIENDA | AG15: Tarrinas/band tienda | AH15: Envase tienda €/tarrina | AI15: Ingreso TIENDA €/band/mes | AJ15: COGS TIENDA €/band/mes
A16: Micromezclum (mix 7 var.) | B16: PROVISIONAL | C16: 1 | D16: 0.4 | E16: 100 | F16: 3 | G16: =F16/E16*1000 -> 30 | H16: 3.7 | I16: 3.7 | J16: =Producto!$D$6/(H16+Producto!$D$7) -> 8.2216216 | K16: 170 | L16: =K16/E16 -> 1.7 | M16: =J16*K16/1000 -> 1.3976757 | N16: 0.3144 | O16: =Producto!$D$14 -> 0.37190083 | P16: =IF(E16<=15,Producto!$D$12,Producto!$D$13) -> 0.17 | Q16: =L16*P16 -> 0.289 | R16: =N16+O16+Q16 -> 0.97530083 | S16: =R16*J16 -> 8.0185544 | T16: =L16*F16*J16 -> 41.93027 | U16: =IFERROR((T16-S16)/T16,0) -> 0.80876454 | V16: =IFERROR((T16-S16)/(J16*Producto!$D$11/60),0) -> 82.493983 | W16: 50 | X16: 5.5 | Y16: =IFERROR(X16/W16*1000,0) -> 110 | Z16: =IFERROR(K16/W16,0) -> 3.4 | AA16: =IF(W16<=15,Producto!$D$12,Producto!$D$13) -> 0.17 | AB16: =Z16*X16*J16 -> 153.74432 | AC16: =(N16+O16+Z16*AA16)*J16 -> 10.394603 | AD16: 50 | AE16: 3 | AF16: =IFERROR(AE16/AD16*1000,0) -> 60 | AG16: =IFERROR(K16/AD16,0) -> 3.4 | AH16: =IF(AD16<=15,Producto!$D$12,Producto!$D$13) -> 0.17 | AI16: =AG16*AE16*J16 -> 83.860541 | AJ16: =(N16+O16+AG16*AH16)*J16 -> 10.394603
A17: Cilantro split | B17: CONFIRMADO | C17: 1 | D17: 0.15 | E17: 30 | F17: 2.5 | G17: =F17/E17*1000 -> 83.333333 | H17: 10 | I17: 5 | J17: =Producto!$D$6/(H17+Producto!$D$7) -> 3.042 | K17: 145 | L17: =K17/E17 -> 4.8333333 | M17: =J17*K17/1000 -> 0.44109 | N17: 0.225 | O17: =Producto!$D$14 -> 0.37190083 | P17: =IF(E17<=15,Producto!$D$12,Producto!$D$13) -> 0.17 | Q17: =L17*P17 -> 0.82166667 | R17: =N17+O17+Q17 -> 1.4185675 | S17: =R17*J17 -> 4.3152823 | T17: =L17*F17*J17 -> 36.7575 | U17: =IFERROR((T17-S17)/T17,0) -> 0.88260131 | V17: =IFERROR((T17-S17)/(J17*Producto!$D$11/60),0) -> 213.29532 | W17: 30 | X17: 7.85 | Y17: =IFERROR(X17/W17*1000,0) -> 261.66667 | Z17: =IFERROR(K17/W17,0) -> 4.8333333 | AA17: =IF(W17<=15,Producto!$D$12,Producto!$D$13) -> 0.17 | AB17: =Z17*X17*J17 -> 115.41855 | AC17: =(N17+O17+Z17*AA17)*J17 -> 4.3152823 | AD17: 15 | AE17: 1.75 | AF17: =IFERROR(AE17/AD17*1000,0) -> 116.66667 | AG17: =IFERROR(K17/AD17,0) -> 9.6666667 | AH17: =IF(AD17<=15,Producto!$D$12,Producto!$D$13) -> 0.1 | AI17: =AG17*AE17*J17 -> 51.4605 | AJ17: =(N17+O17+AG17*AH17)*J17 -> 4.7563723
A18: Albahaca genovesa | B18: CONFIRMADO | C18: 1 | D18: 0.1 | E18: 30 | F18: 2.5 | G18: =F18/E18*1000 -> 83.333333 | H18: 13 | I18: 5 | J18: =Producto!$D$6/(H18+Producto!$D$7) -> 2.34 | K18: 90 | L18: =K18/E18 -> 3 | M18: =J18*K18/1000 -> 0.2106 | N18: 0.333 | O18: =Producto!$D$14 -> 0.37190083 | P18: =IF(E18<=15,Producto!$D$12,Producto!$D$13) -> 0.17 | Q18: =L18*P18 -> 0.51 | R18: =N18+O18+Q18 -> 1.2149008 | S18: =R18*J18 -> 2.8428679 | T18: =L18*F18*J18 -> 17.55 | U18: =IFERROR((T18-S18)/T18,0) -> 0.83801322 | V18: =IFERROR((T18-S18)/(J18*Producto!$D$11/60),0) -> 125.70198 | W18: 30 | X18: 9.3 | Y18: =IFERROR(X18/W18*1000,0) -> 310 | Z18: =IFERROR(K18/W18,0) -> 3 | AA18: =IF(W18<=15,Producto!$D$12,Producto!$D$13) -> 0.17 | AB18: =Z18*X18*J18 -> 65.286 | AC18: =(N18+O18+Z18*AA18)*J18 -> 2.8428679 | AD18: 15 | AE18: 1.65 | AF18: =IFERROR(AE18/AD18*1000,0) -> 110 | AG18: =IFERROR(K18/AD18,0) -> 6 | AH18: =IF(AD18<=15,Producto!$D$12,Producto!$D$13) -> 0.1 | AI18: =AG18*AE18*J18 -> 23.166 | AJ18: =(N18+O18+AG18*AH18)*J18 -> 3.0534679
A19: Rábano daikon | B19: PROVISIONAL | C19: 1 | D19: 0.08 | E19: 30 | F19: 1.5 | G19: =F19/E19*1000 -> 50 | H19: 3 | I19: 3 | J19: =Producto!$D$6/(H19+Producto!$D$7) -> 10.14 | K19: 245 | L19: =K19/E19 -> 8.1666667 | M19: =J19*K19/1000 -> 2.4843 | N19: 0.34 | O19: =Producto!$D$14 -> 0.37190083 | P19: =IF(E19<=15,Producto!$D$12,Producto!$D$13) -> 0.17 | Q19: =L19*P19 -> 1.3883333 | R19: =N19+O19+Q19 -> 2.1002342 | S19: =R19*J19 -> 21.296374 | T19: =L19*F19*J19 -> 124.215 | U19: =IFERROR((T19-S19)/T19,0) -> 0.82855231 | V19: =IFERROR((T19-S19)/(J19*Producto!$D$11/60),0) -> 202.99532 | W19: 30 | X19: 5.95 | Y19: =IFERROR(X19/W19*1000,0) -> 198.33333 | Z19: =IFERROR(K19/W19,0) -> 8.1666667 | AA19: =IF(W19<=15,Producto!$D$12,Producto!$D$13) -> 0.17 | AB19: =Z19*X19*J19 -> 492.7195 | AC19: =(N19+O19+Z19*AA19)*J19 -> 21.296374 | AD19: 15 | AE19: 1.85 | AF19: =IFERROR(AE19/AD19*1000,0) -> 123.33333 | AG19: =IFERROR(K19/AD19,0) -> 16.333333 | AH19: =IF(AD19<=15,Producto!$D$12,Producto!$D$13) -> 0.1 | AI19: =AG19*AE19*J19 -> 306.397 | AJ19: =(N19+O19+AG19*AH19)*J19 -> 23.780674
A20: Rúcula rocket | B20: PROVISIONAL | C20: 1 | D20: 0.08 | E20: 30 | F20: 1.5 | G20: =F20/E20*1000 -> 50 | H20: 4 | I20: 3 | J20: =Producto!$D$6/(H20+Producto!$D$7) -> 7.605 | K20: 170 | L20: =K20/E20 -> 5.6666667 | M20: =J20*K20/1000 -> 1.29285 | N20: 0.165 | O20: =Producto!$D$14 -> 0.37190083 | P20: =IF(E20<=15,Producto!$D$12,Producto!$D$13) -> 0.17 | Q20: =L20*P20 -> 0.96333333 | R20: =N20+O20+Q20 -> 1.5002342 | S20: =R20*J20 -> 11.409281 | T20: =L20*F20*J20 -> 64.6425 | U20: =IFERROR((T20-S20)/T20,0) -> 0.82350186 | V20: =IFERROR((T20-S20)/(J20*Producto!$D$11/60),0) -> 139.99532 | W20: 30 | X20: 6.8 | Y20: =IFERROR(X20/W20*1000,0) -> 226.66667 | Z20: =IFERROR(K20/W20,0) -> 5.6666667 | AA20: =IF(W20<=15,Producto!$D$12,Producto!$D$13) -> 0.17 | AB20: =Z20*X20*J20 -> 293.046 | AC20: =(N20+O20+Z20*AA20)*J20 -> 11.409281 | AD20: 15 | AE20: 1.6 | AF20: =IFERROR(AE20/AD20*1000,0) -> 106.66667 | AG20: =IFERROR(K20/AD20,0) -> 11.333333 | AH20: =IF(AD20<=15,Producto!$D$12,Producto!$D$13) -> 0.1 | AI20: =AG20*AE20*J20 -> 137.904 | AJ20: =(N20+O20+AG20*AH20)*J20 -> 12.702131
A21: Rábano rose | B21: PROVISIONAL | C21: 1 | D21: 0.07 | E21: 30 | F21: 1.5 | G21: =F21/E21*1000 -> 50 | H21: 3 | I21: 3 | J21: =Producto!$D$6/(H21+Producto!$D$7) -> 10.14 | K21: 245 | L21: =K21/E21 -> 8.1666667 | M21: =J21*K21/1000 -> 2.4843 | N21: 0.3366 | O21: =Producto!$D$14 -> 0.37190083 | P21: =IF(E21<=15,Producto!$D$12,Producto!$D$13) -> 0.17 | Q21: =L21*P21 -> 1.3883333 | R21: =N21+O21+Q21 -> 2.0968342 | S21: =R21*J21 -> 21.261898 | T21: =L21*F21*J21 -> 124.215 | U21: =IFERROR((T21-S21)/T21,0) -> 0.82882986 | V21: =IFERROR((T21-S21)/(J21*Producto!$D$11/60),0) -> 203.06332 | W21: 30 | X21: 6.2 | Y21: =IFERROR(X21/W21*1000,0) -> 206.66667 | Z21: =IFERROR(K21/W21,0) -> 8.1666667 | AA21: =IF(W21<=15,Producto!$D$12,Producto!$D$13) -> 0.17 | AB21: =Z21*X21*J21 -> 513.422 | AC21: =(N21+O21+Z21*AA21)*J21 -> 21.261898 | AD21: 15 | AE21: 1.85 | AF21: =IFERROR(AE21/AD21*1000,0) -> 123.33333 | AG21: =IFERROR(K21/AD21,0) -> 16.333333 | AH21: =IF(AD21<=15,Producto!$D$12,Producto!$D$13) -> 0.1 | AI21: =AG21*AE21*J21 -> 306.397 | AJ21: =(N21+O21+AG21*AH21)*J21 -> 23.746198
A22: Mostaza Red Giant | B22: PROVISIONAL | C22: 1 | D22: 0.05 | E22: 30 | F22: 1.5 | G22: =F22/E22*1000 -> 50 | H22: 4 | I22: 3 | J22: =Producto!$D$6/(H22+Producto!$D$7) -> 7.605 | K22: 160 | L22: =K22/E22 -> 5.3333333 | M22: =J22*K22/1000 -> 1.2168 | N22: 0.44 | O22: =Producto!$D$14 -> 0.37190083 | P22: =IF(E22<=15,Producto!$D$12,Producto!$D$13) -> 0.17 | Q22: =L22*P22 -> 0.90666667 | R22: =N22+O22+Q22 -> 1.7185675 | S22: =R22*J22 -> 13.069706 | T22: =L22*F22*J22 -> 60.84 | U22: =IFERROR((T22-S22)/T22,0) -> 0.78517906 | V22: =IFERROR((T22-S22)/(J22*Producto!$D$11/60),0) -> 125.62865 | W22: 30 | X22: 6.9 | Y22: =IFERROR(X22/W22*1000,0) -> 230 | Z22: =IFERROR(K22/W22,0) -> 5.3333333 | AA22: =IF(W22<=15,Producto!$D$12,Producto!$D$13) -> 0.17 | AB22: =Z22*X22*J22 -> 279.864 | AC22: =(N22+O22+Z22*AA22)*J22 -> 13.069706 | AD22: 15 | AE22: 1.55 | AF22: =IFERROR(AE22/AD22*1000,0) -> 103.33333 | AG22: =IFERROR(K22/AD22,0) -> 10.666667 | AH22: =IF(AD22<=15,Producto!$D$12,Producto!$D$13) -> 0.1 | AI22: =AG22*AE22*J22 -> 125.736 | AJ22: =(N22+O22+AG22*AH22)*J22 -> 14.286506
A23: Brócoli calabrese | B23: PROVISIONAL | C23: 1 | D23: 0.04 | E23: 30 | F23: 1.5 | G23: =F23/E23*1000 -> 50 | H23: 4 | I23: 3 | J23: =Producto!$D$6/(H23+Producto!$D$7) -> 7.605 | K23: 170 | L23: =K23/E23 -> 5.6666667 | M23: =J23*K23/1000 -> 1.29285 | N23: 0.484 | O23: =Producto!$D$14 -> 0.37190083 | P23: =IF(E23<=15,Producto!$D$12,Producto!$D$13) -> 0.17 | Q23: =L23*P23 -> 0.96333333 | R23: =N23+O23+Q23 -> 1.8192342 | S23: =R23*J23 -> 13.835276 | T23: =L23*F23*J23 -> 64.6425 | U23: =IFERROR((T23-S23)/T23,0) -> 0.78597245 | V23: =IFERROR((T23-S23)/(J23*Producto!$D$11/60),0) -> 133.61532 | W23: 15 | X23: 4 | Y23: =IFERROR(X23/W23*1000,0) -> 266.66667 | Z23: =IFERROR(K23/W23,0) -> 11.333333 | AA23: =IF(W23<=15,Producto!$D$12,Producto!$D$13) -> 0.1 | AB23: =Z23*X23*J23 -> 344.76 | AC23: =(N23+O23+Z23*AA23)*J23 -> 15.128126 | AD23: 15 | AE23: 1.85 | AF23: =IFERROR(AE23/AD23*1000,0) -> 123.33333 | AG23: =IFERROR(K23/AD23,0) -> 11.333333 | AH23: =IF(AD23<=15,Producto!$D$12,Producto!$D$13) -> 0.1 | AI23: =AG23*AE23*J23 -> 159.4515 | AJ23: =(N23+O23+AG23*AH23)*J23 -> 15.128126
A24: Amaranto rojo | B24: PROVISIONAL | C24: 1 | D24: 0.03 | E24: 30 | F24: 3 | G24: =F24/E24*1000 -> 100 | H24: 9 | I24: 3 | J24: =Producto!$D$6/(H24+Producto!$D$7) -> 3.38 | K24: 80 | L24: =K24/E24 -> 2.6666667 | M24: =J24*K24/1000 -> 0.2704 | N24: 0.45 | O24: =Producto!$D$14 -> 0.37190083 | P24: =IF(E24<=15,Producto!$D$12,Producto!$D$13) -> 0.17 | Q24: =L24*P24 -> 0.45333333 | R24: =N24+O24+Q24 -> 1.2752342 | S24: =R24*J24 -> 4.3102915 | T24: =L24*F24*J24 -> 27.04 | U24: =IFERROR((T24-S24)/T24,0) -> 0.84059573 | V24: =IFERROR((T24-S24)/(J24*Producto!$D$11/60),0) -> 134.49532 | W24: 30 | X24: 10.8 | Y24: =IFERROR(X24/W24*1000,0) -> 360 | Z24: =IFERROR(K24/W24,0) -> 2.6666667 | AA24: =IF(W24<=15,Producto!$D$12,Producto!$D$13) -> 0.17 | AB24: =Z24*X24*J24 -> 97.344 | AC24: =(N24+O24+Z24*AA24)*J24 -> 4.3102915 | AD24: 15 | AE24: 1.65 | AF24: =IFERROR(AE24/AD24*1000,0) -> 110 | AG24: =IFERROR(K24/AD24,0) -> 5.3333333 | AH24: =IF(AD24<=15,Producto!$D$12,Producto!$D$13) -> 0.1 | AI24: =AG24*AE24*J24 -> 29.744 | AJ24: =(N24+O24+AG24*AH24)*J24 -> 4.5806915
A25: Rábano red | B25: INACTIVO | C25: 0 | D25: 0 | E25: 30 | F25: 1.3 | G25: =F25/E25*1000 -> 43.333333 | H25: 2 | I25: 3 | J25: =Producto!$D$6/(H25+Producto!$D$7) -> 15.21 | K25: 200 | L25: =K25/E25 -> 6.6666667 | M25: =J25*K25/1000 -> 3.042 | N25: 0.3 | O25: =Producto!$D$14 -> 0.37190083 | P25: =IF(E25<=15,Producto!$D$12,Producto!$D$13) -> 0.17 | Q25: =L25*P25 -> 1.1333333 | R25: =N25+O25+Q25 -> 1.8052342 | S25: =R25*J25 -> 27.457612 | T25: =L25*F25*J25 -> 131.82 | U25: =IFERROR((T25-S25)/T25,0) -> 0.79170375 | V25: =IFERROR((T25-S25)/(J25*Producto!$D$11/60),0) -> 137.22865 | W25: 30 | X25: 6.2 | Y25: =IFERROR(X25/W25*1000,0) -> 206.66667 | Z25: =IFERROR(K25/W25,0) -> 6.6666667 | AA25: =IF(W25<=15,Producto!$D$12,Producto!$D$13) -> 0.17 | AB25: =Z25*X25*J25 -> 628.68 | AC25: =(N25+O25+Z25*AA25)*J25 -> 27.457612 | AD25: =E25 -> 30 | AE25: =F25 -> 1.3 | AF25: =IFERROR(AE25/AD25*1000,0) -> 43.333333 | AG25: =IFERROR(K25/AD25,0) -> 6.6666667 | AH25: =IF(AD25<=15,Producto!$D$12,Producto!$D$13) -> 0.17 | AI25: =AG25*AE25*J25 -> 131.82 | AJ25: =(N25+O25+AG25*AH25)*J25 -> 27.457612
A26: Guisante (pea shoots) | B26: INACTIVO | C26: 0 | D26: 0 | E26: 30 | F26: 1.44 | G26: =F26/E26*1000 -> 48 | H26: 8 | I26: 3 | J26: =Producto!$D$6/(H26+Producto!$D$7) -> 3.8025 | K26: 220 | L26: =K26/E26 -> 7.3333333 | M26: =J26*K26/1000 -> 0.83655 | N26: 1.5 | O26: =Producto!$D$14 -> 0.37190083 | P26: =IF(E26<=15,Producto!$D$12,Producto!$D$13) -> 0.17 | Q26: =L26*P26 -> 1.2466667 | R26: =N26+O26+Q26 -> 3.1185675 | S26: =R26*J26 -> 11.858353 | T26: =L26*F26*J26 -> 40.1544 | U26: =IFERROR((T26-S26)/T26,0) -> 0.70468111 | V26: =IFERROR((T26-S26)/(J26*Producto!$D$11/60),0) -> 148.82865 | W26: 30 | X26: 6 | Y26: =IFERROR(X26/W26*1000,0) -> 200 | Z26: =IFERROR(K26/W26,0) -> 7.3333333 | AA26: =IF(W26<=15,Producto!$D$12,Producto!$D$13) -> 0.17 | AB26: =Z26*X26*J26 -> 167.31 | AC26: =(N26+O26+Z26*AA26)*J26 -> 11.858353 | AD26: =E26 -> 30 | AE26: =F26 -> 1.44 | AF26: =IFERROR(AE26/AD26*1000,0) -> 48 | AG26: =IFERROR(K26/AD26,0) -> 7.3333333 | AH26: =IF(AD26<=15,Producto!$D$12,Producto!$D$13) -> 0.17 | AI26: =AG26*AE26*J26 -> 40.1544 | AJ26: =(N26+O26+AG26*AH26)*J26 -> 11.858353
A27: Remolacha roja | B27: INACTIVO | C27: 0 | D27: 0 | E27: 30 | F27: 1.8 | G27: =F27/E27*1000 -> 60 | H27: 8 | I27: 4 | J27: =Producto!$D$6/(H27+Producto!$D$7) -> 3.8025 | K27: 150 | L27: =K27/E27 -> 5 | M27: =J27*K27/1000 -> 0.570375 | N27: 0.6 | O27: =Producto!$D$14 -> 0.37190083 | P27: =IF(E27<=15,Producto!$D$12,Producto!$D$13) -> 0.17 | Q27: =L27*P27 -> 0.85 | R27: =N27+O27+Q27 -> 1.8219008 | S27: =R27*J27 -> 6.9277779 | T27: =L27*F27*J27 -> 34.2225 | U27: =IFERROR((T27-S27)/T27,0) -> 0.79756657 | V27: =IFERROR((T27-S27)/(J27*Producto!$D$11/60),0) -> 143.56198 | W27: 30 | X27: 8.05 | Y27: =IFERROR(X27/W27*1000,0) -> 268.33333 | Z27: =IFERROR(K27/W27,0) -> 5 | AA27: =IF(W27<=15,Producto!$D$12,Producto!$D$13) -> 0.17 | AB27: =Z27*X27*J27 -> 153.05062 | AC27: =(N27+O27+Z27*AA27)*J27 -> 6.9277779 | AD27: =E27 -> 30 | AE27: =F27 -> 1.8 | AF27: =IFERROR(AE27/AD27*1000,0) -> 60 | AG27: =IFERROR(K27/AD27,0) -> 5 | AH27: =IF(AD27<=15,Producto!$D$12,Producto!$D$13) -> 0.17 | AI27: =AG27*AE27*J27 -> 34.2225 | AJ27: =(N27+O27+AG27*AH27)*J27 -> 6.9277779
A28: Remolacha amarilla | B28: INACTIVO | C28: 0 | D28: 0 | E28: 30 | F28: 1.8 | G28: =F28/E28*1000 -> 60 | H28: 8 | I28: 4 | J28: =Producto!$D$6/(H28+Producto!$D$7) -> 3.8025 | K28: 115 | L28: =K28/E28 -> 3.8333333 | M28: =J28*K28/1000 -> 0.4372875 | N28: 0.6 | O28: =Producto!$D$14 -> 0.37190083 | P28: =IF(E28<=15,Producto!$D$12,Producto!$D$13) -> 0.17 | Q28: =L28*P28 -> 0.65166667 | R28: =N28+O28+Q28 -> 1.6235675 | S28: =R28*J28 -> 6.1736154 | T28: =L28*F28*J28 -> 26.23725 | U28: =IFERROR((T28-S28)/T28,0) -> 0.76470036 | V28: =IFERROR((T28-S28)/(J28*Producto!$D$11/60),0) -> 105.52865 | W28: 30 | X28: 8.05 | Y28: =IFERROR(X28/W28*1000,0) -> 268.33333 | Z28: =IFERROR(K28/W28,0) -> 3.8333333 | AA28: =IF(W28<=15,Producto!$D$12,Producto!$D$13) -> 0.17 | AB28: =Z28*X28*J28 -> 117.33881 | AC28: =(N28+O28+Z28*AA28)*J28 -> 6.1736154 | AD28: =E28 -> 30 | AE28: =F28 -> 1.8 | AF28: =IFERROR(AE28/AD28*1000,0) -> 60 | AG28: =IFERROR(K28/AD28,0) -> 3.8333333 | AH28: =IF(AD28<=15,Producto!$D$12,Producto!$D$13) -> 0.17 | AI28: =AG28*AE28*J28 -> 26.23725 | AJ28: =(N28+O28+AG28*AH28)*J28 -> 6.1736154
A29: Hinojo | B29: INACTIVO | C29: 0 | D29: 0 | E29: 30 | F29: 2.6 | G29: =F29/E29*1000 -> 86.666667 | H29: 12 | I29: 5 | J29: =Producto!$D$6/(H29+Producto!$D$7) -> 2.535 | K29: 90 | L29: =K29/E29 -> 3 | M29: =J29*K29/1000 -> 0.22815 | N29: 0.5 | O29: =Producto!$D$14 -> 0.37190083 | P29: =IF(E29<=15,Producto!$D$12,Producto!$D$13) -> 0.17 | Q29: =L29*P29 -> 0.51 | R29: =N29+O29+Q29 -> 1.3819008 | S29: =R29*J29 -> 3.5031186 | T29: =L29*F29*J29 -> 19.773 | U29: =IFERROR((T29-S29)/T29,0) -> 0.82283323 | V29: =IFERROR((T29-S29)/(J29*Producto!$D$11/60),0) -> 128.36198 | W29: 30 | X29: 9.3 | Y29: =IFERROR(X29/W29*1000,0) -> 310 | Z29: =IFERROR(K29/W29,0) -> 3 | AA29: =IF(W29<=15,Producto!$D$12,Producto!$D$13) -> 0.17 | AB29: =Z29*X29*J29 -> 70.7265 | AC29: =(N29+O29+Z29*AA29)*J29 -> 3.5031186 | AD29: =E29 -> 30 | AE29: =F29 -> 2.6 | AF29: =IFERROR(AE29/AD29*1000,0) -> 86.666667 | AG29: =IFERROR(K29/AD29,0) -> 3 | AH29: =IF(AD29<=15,Producto!$D$12,Producto!$D$13) -> 0.17 | AI29: =AG29*AE29*J29 -> 19.773 | AJ29: =(N29+O29+AG29*AH29)*J29 -> 3.5031186
A30: Cebolla Barbra | B30: INACTIVO | C30: 0 | D30: 0 | E30: 30 | F30: 2.4 | G30: =F30/E30*1000 -> 80 | H30: 12 | I30: 6 | J30: =Producto!$D$6/(H30+Producto!$D$7) -> 2.535 | K30: 75 | L30: =K30/E30 -> 2.5 | M30: =J30*K30/1000 -> 0.190125 | N30: 0.6 | O30: =Producto!$D$14 -> 0.37190083 | P30: =IF(E30<=15,Producto!$D$12,Producto!$D$13) -> 0.17 | Q30: =L30*P30 -> 0.425 | R30: =N30+O30+Q30 -> 1.3969008 | S30: =R30*J30 -> 3.5411436 | T30: =L30*F30*J30 -> 15.21 | U30: =IFERROR((T30-S30)/T30,0) -> 0.7671832 | V30: =IFERROR((T30-S30)/(J30*Producto!$D$11/60),0) -> 92.061983 | W30: 30 | X30: 9.3 | Y30: =IFERROR(X30/W30*1000,0) -> 310 | Z30: =IFERROR(K30/W30,0) -> 2.5 | AA30: =IF(W30<=15,Producto!$D$12,Producto!$D$13) -> 0.17 | AB30: =Z30*X30*J30 -> 58.93875 | AC30: =(N30+O30+Z30*AA30)*J30 -> 3.5411436 | AD30: =E30 -> 30 | AE30: =F30 -> 2.4 | AF30: =IFERROR(AE30/AD30*1000,0) -> 80 | AG30: =IFERROR(K30/AD30,0) -> 2.5 | AH30: =IF(AD30<=15,Producto!$D$12,Producto!$D$13) -> 0.17 | AI30: =AG30*AE30*J30 -> 15.21 | AJ30: =(N30+O30+AG30*AH30)*J30 -> 3.5411436
A31: Cebollino chino | B31: INACTIVO | C31: 0 | D31: 0 | E31: 30 | F31: 2.6 | G31: =F31/E31*1000 -> 86.666667 | H31: 14 | I31: 6 | J31: =Producto!$D$6/(H31+Producto!$D$7) -> 2.1728571 | K31: 70 | L31: =K31/E31 -> 2.3333333 | M31: =J31*K31/1000 -> 0.1521 | N31: 0.7 | O31: =Producto!$D$14 -> 0.37190083 | P31: =IF(E31<=15,Producto!$D$12,Producto!$D$13) -> 0.17 | Q31: =L31*P31 -> 0.39666667 | R31: =N31+O31+Q31 -> 1.4685675 | S31: =R31*J31 -> 3.1909874 | T31: =L31*F31*J31 -> 13.182 | U31: =IFERROR((T31-S31)/T31,0) -> 0.75792844 | V31: =IFERROR((T31-S31)/(J31*Producto!$D$11/60),0) -> 91.961983 | W31: 30 | X31: 10.15 | Y31: =IFERROR(X31/W31*1000,0) -> 338.33333 | Z31: =IFERROR(K31/W31,0) -> 2.3333333 | AA31: =IF(W31<=15,Producto!$D$12,Producto!$D$13) -> 0.17 | AB31: =Z31*X31*J31 -> 51.4605 | AC31: =(N31+O31+Z31*AA31)*J31 -> 3.1909874 | AD31: =E31 -> 30 | AE31: =F31 -> 2.6 | AF31: =IFERROR(AE31/AD31*1000,0) -> 86.666667 | AG31: =IFERROR(K31/AD31,0) -> 2.3333333 | AH31: =IF(AD31<=15,Producto!$D$12,Producto!$D$13) -> 0.17 | AI31: =AG31*AE31*J31 -> 13.182 | AJ31: =(N31+O31+AG31*AH31)*J31 -> 3.1909874
A32: PORTFOLIO ACTIVO (media ponderada por % de luz) | D32: =SUMPRODUCT(C16:C31,D16:D31) -> 1 | J32: =SUMPRODUCT(C16:C31,D16:D31,J16:J31) -> 6.8941986 | M32: =SUMPRODUCT(C16:C31,D16:D31,M16:M31) -> 1.2430328 | S32: =SUMPRODUCT(C16:C31,D16:D31,S16:S31) -> 9.5799912 | T32: =SUMPRODUCT(C16:C31,D16:D31,T16:T31) -> 54.283283 | U32: =IFERROR((T32-S32)/T32,0) -> 0.82351857 | V32: =IFERROR((T32-S32)/(J32*Producto!$D$11/60),0) -> 129.68379 | AB32: =SUMPRODUCT(C16:C31,D16:D31,AB16:AB31) -> 214.84381 | AC32: =SUMPRODUCT(C16:C31,D16:D31,AC16:AC31) -> 10.582125 | AI32: =SUMPRODUCT(C16:C31,D16:D31,AI16:AI31) -> 114.12894 | AJ32: =SUMPRODUCT(C16:C31,D16:D31,AJ16:AJ31) -> 11.214373
A34: Comprobación: % de luz de las ACTIVAS suma | D34: =IF(ABS(D32-1)<0.001,"OK — 100%","REVISAR: "&TEXT(D32,"0%")) -> OK — 100% | F34: MARGEN €/HORA de trabajo: la métrica que manda cuando la mano de obra es el cuello de botella. Compárala con el coste/hora cargado (~14 €/h).
A35: Precio medio ponderado MAYORISTA (€/kg) | D35: =IFERROR(T32/M32,0) -> 43.670034
A36: Margen bruto del portfolio (s/ ingreso directo) | D36: =U32 -> 0.82351857
A38: REVISIÓN OPERATIVA (socio de producción) — 23/09/2026
A39: Rendimientos actualizados: cilantro 120→145 g · albahaca 100→90 g · rábano daikon y rose 175→245 g (solo los ACTIVOS).
A40: PENDIENTE DE CONFIRMAR: 'Rábano red' (INACTIVO) sigue en 200 g y 'Micromezclum' (mix de 7 variedades) sigue en 170 g. Si el mix lleva rábano, su rendimiento sube también — revisar con producción.
A41: OJO: los rábanos ACTIVOS tienen 3 días de luz (10,1 ciclos/mes). El 'rábano de ciclo corto' del deck (2 días de luz, 15 ciclos/mes) es el rábano red, que está INACTIVO.
A43: PRECIO MEDIO PONDERADO POR CANAL (tarifa, sin índice de escenario)
A44: Mayorista (distribución, Mercamadrid) | D44: =IFERROR(T32/M32,0) -> 43.670034
A45: Tienda / retail | D45: =IFERROR(AI32/M32,0) -> 91.814909
A46: Restaurante (formato de 30 g, el de menor €/g) | D46: =IFERROR(AB32/M32,0) -> 172.83841
A47: MARGEN BRUTO DE PRODUCTO POR CANAL (antes de logística y merma)
A48: Mayorista | D48: =IFERROR((T32-S32)/T32,0) -> 0.82351857
A49: Tienda / retail | D49: =IFERROR((AI32-AJ32)/AI32,0) -> 0.90173944
A50: Restaurante | D50: =IFERROR((AB32-AC32)/AB32,0) -> 0.95074503
A52: Tarifas: COSTES_ROOTFLOW.xlsx (hoja 4). Restaurante usa el formato de 30 g, el de MENOR margen por gramo (criterio de la propia hoja). Las variedades inactivas toman la tarifa facilitada de 30 g y, en tienda, la de mayorista. El rendimiento por bandeja sigue siendo el validado por producción (V16).

Sheet Tarifas
A1: ROOTFLOW — Tarifas reales por cliente, variedad y formato
A2: Pega aquí el export del ERP. El precio medio ponderado por variedad se calcula solo y se copia a mano en Producto!F (Precio DIR €/tarrina). NADA de esta hoja alimenta el modelo todavía: primero hay que revisar los datos.
A4: Cliente | B4: Variedad | C4: Canal (DIR/DIST) | D4: Formato (g/tarrina) | E4: Precio €/tarrina | F4: Tarrinas/mes | G4: €/mes — calc | H4: kg/mes — calc | I4: €/kg — calc | K4: RESUMEN POR VARIEDAD (se rellena solo desde la tabla)
G5: =IF(N(E5)*N(F5)=0,"",E5*F5) | H5: =IF(N(D5)*N(F5)=0,"",D5*F5/1000) | I5: =IFERROR(G5/H5,"") | K5: Variedad | L5: €/mes | M5: kg/mes | N5: €/kg ponderado | O5: €/tarrina medio
G6: =IF(N(E6)*N(F6)=0,"",E6*F6) | H6: =IF(N(D6)*N(F6)=0,"",D6*F6/1000) | I6: =IFERROR(G6/H6,"") | K6: =Producto!A16 -> Micromezclum (mix 7 var.) | L6: =SUMIF($B$5:$B$204,$K6,$G$5:$G$204) -> 0 | M6: =SUMIF($B$5:$B$204,$K6,$H$5:$H$204) -> 0 | N6: =IFERROR(L6/M6,"") | O6: =IFERROR(SUMIF($B$5:$B$204,$K6,$G$5:$G$204)/SUMIF($B$5:$B$204,$K6,$F$5:$F$204),"")
G7: =IF(N(E7)*N(F7)=0,"",E7*F7) | H7: =IF(N(D7)*N(F7)=0,"",D7*F7/1000) | I7: =IFERROR(G7/H7,"") | K7: =Producto!A17 -> Cilantro split | L7: =SUMIF($B$5:$B$204,$K7,$G$5:$G$204) -> 0 | M7: =SUMIF($B$5:$B$204,$K7,$H$5:$H$204) -> 0 | N7: =IFERROR(L7/M7,"") | O7: =IFERROR(SUMIF($B$5:$B$204,$K7,$G$5:$G$204)/SUMIF($B$5:$B$204,$K7,$F$5:$F$204),"")
G8: =IF(N(E8)*N(F8)=0,"",E8*F8) | H8: =IF(N(D8)*N(F8)=0,"",D8*F8/1000) | I8: =IFERROR(G8/H8,"") | K8: =Producto!A18 -> Albahaca genovesa | L8: =SUMIF($B$5:$B$204,$K8,$G$5:$G$204) -> 0 | M8: =SUMIF($B$5:$B$204,$K8,$H$5:$H$204) -> 0 | N8: =IFERROR(L8/M8,"") | O8: =IFERROR(SUMIF($B$5:$B$204,$K8,$G$5:$G$204)/SUMIF($B$5:$B$204,$K8,$F$5:$F$204),"")
G9: =IF(N(E9)*N(F9)=0,"",E9*F9) | H9: =IF(N(D9)*N(F9)=0,"",D9*F9/1000) | I9: =IFERROR(G9/H9,"") | K9: =Producto!A19 -> Rábano daikon | L9: =SUMIF($B$5:$B$204,$K9,$G$5:$G$204) -> 0 | M9: =SUMIF($B$5:$B$204,$K9,$H$5:$H$204) -> 0 | N9: =IFERROR(L9/M9,"") | O9: =IFERROR(SUMIF($B$5:$B$204,$K9,$G$5:$G$204)/SUMIF($B$5:$B$204,$K9,$F$5:$F$204),"")
G10: =IF(N(E10)*N(F10)=0,"",E10*F10) | H10: =IF(N(D10)*N(F10)=0,"",D10*F10/1000) | I10: =IFERROR(G10/H10,"") | K10: =Producto!A20 -> Rúcula rocket | L10: =SUMIF($B$5:$B$204,$K10,$G$5:$G$204) -> 0 | M10: =SUMIF($B$5:$B$204,$K10,$H$5:$H$204) -> 0 | N10: =IFERROR(L10/M10,"") | O10: =IFERROR(SUMIF($B$5:$B$204,$K10,$G$5:$G$204)/SUMIF($B$5:$B$204,$K10,$F$5:$F$204),"")
G11: =IF(N(E11)*N(F11)=0,"",E11*F11) | H11: =IF(N(D11)*N(F11)=0,"",D11*F11/1000) | I11: =IFERROR(G11/H11,"") | K11: =Producto!A21 -> Rábano rose | L11: =SUMIF($B$5:$B$204,$K11,$G$5:$G$204) -> 0 | M11: =SUMIF($B$5:$B$204,$K11,$H$5:$H$204) -> 0 | N11: =IFERROR(L11/M11,"") | O11: =IFERROR(SUMIF($B$5:$B$204,$K11,$G$5:$G$204)/SUMIF($B$5:$B$204,$K11,$F$5:$F$204),"")
G12: =IF(N(E12)*N(F12)=0,"",E12*F12) | H12: =IF(N(D12)*N(F12)=0,"",D12*F12/1000) | I12: =IFERROR(G12/H12,"") | K12: =Producto!A22 -> Mostaza Red Giant | L12: =SUMIF($B$5:$B$204,$K12,$G$5:$G$204) -> 0 | M12: =SUMIF($B$5:$B$204,$K12,$H$5:$H$204) -> 0 | N12: =IFERROR(L12/M12,"") | O12: =IFERROR(SUMIF($B$5:$B$204,$K12,$G$5:$G$204)/SUMIF($B$5:$B$204,$K12,$F$5:$F$204),"")
G13: =IF(N(E13)*N(F13)=0,"",E13*F13) | H13: =IF(N(D13)*N(F13)=0,"",D13*F13/1000) | I13: =IFERROR(G13/H13,"") | K13: =Producto!A23 -> Brócoli calabrese | L13: =SUMIF($B$5:$B$204,$K13,$G$5:$G$204) -> 0 | M13: =SUMIF($B$5:$B$204,$K13,$H$5:$H$204) -> 0 | N13: =IFERROR(L13/M13,"") | O13: =IFERROR(SUMIF($B$5:$B$204,$K13,$G$5:$G$204)/SUMIF($B$5:$B$204,$K13,$F$5:$F$204),"")
G14: =IF(N(E14)*N(F14)=0,"",E14*F14) | H14: =IF(N(D14)*N(F14)=0,"",D14*F14/1000) | I14: =IFERROR(G14/H14,"") | K14: =Producto!A24 -> Amaranto rojo | L14: =SUMIF($B$5:$B$204,$K14,$G$5:$G$204) -> 0 | M14: =SUMIF($B$5:$B$204,$K14,$H$5:$H$204) -> 0 | N14: =IFERROR(L14/M14,"") | O14: =IFERROR(SUMIF($B$5:$B$204,$K14,$G$5:$G$204)/SUMIF($B$5:$B$204,$K14,$F$5:$F$204),"")
G15: =IF(N(E15)*N(F15)=0,"",E15*F15) | H15: =IF(N(D15)*N(F15)=0,"",D15*F15/1000) | I15: =IFERROR(G15/H15,"") | K15: =Producto!A25 -> Rábano red | L15: =SUMIF($B$5:$B$204,$K15,$G$5:$G$204) -> 0 | M15: =SUMIF($B$5:$B$204,$K15,$H$5:$H$204) -> 0 | N15: =IFERROR(L15/M15,"") | O15: =IFERROR(SUMIF($B$5:$B$204,$K15,$G$5:$G$204)/SUMIF($B$5:$B$204,$K15,$F$5:$F$204),"")
G16: =IF(N(E16)*N(F16)=0,"",E16*F16) | H16: =IF(N(D16)*N(F16)=0,"",D16*F16/1000) | I16: =IFERROR(G16/H16,"") | K16: =Producto!A26 -> Guisante (pea shoots) | L16: =SUMIF($B$5:$B$204,$K16,$G$5:$G$204) -> 0 | M16: =SUMIF($B$5:$B$204,$K16,$H$5:$H$204) -> 0 | N16: =IFERROR(L16/M16,"") | O16: =IFERROR(SUMIF($B$5:$B$204,$K16,$G$5:$G$204)/SUMIF($B$5:$B$204,$K16,$F$5:$F$204),"")
G17: =IF(N(E17)*N(F17)=0,"",E17*F17) | H17: =IF(N(D17)*N(F17)=0,"",D17*F17/1000) | I17: =IFERROR(G17/H17,"") | K17: =Producto!A27 -> Remolacha roja | L17: =SUMIF($B$5:$B$204,$K17,$G$5:$G$204) -> 0 | M17: =SUMIF($B$5:$B$204,$K17,$H$5:$H$204) -> 0 | N17: =IFERROR(L17/M17,"") | O17: =IFERROR(SUMIF($B$5:$B$204,$K17,$G$5:$G$204)/SUMIF($B$5:$B$204,$K17,$F$5:$F$204),"")
... G21: =IF(N(E21)*N(F21)=0,"",E21*F21) | H21: =IF(N(D21)*N(F21)=0,"",D21*F21/1000) | I21: =IFERROR(G21/H21,"") | K21: =Producto!A31 -> Cebollino chino | L21: =SUMIF($B$5:$B$204,$K21,$G$5:$G$204) -> 0 | M21: =SUMIF($B$5:$B$204,$K21,$H$5:$H$204) -> 0 | N21: =IFERROR(L21/M21,"") | O21: =IFERROR(SUMIF($B$5:$B$204,$K21,$G$5:$G$204)/SUMIF($B$5:$B$204,$K21,$F$5:$F$204),"")
G22: =IF(N(E22)*N(F22)=0,"",E22*F22) | H22: =IF(N(D22)*N(F22)=0,"",D22*F22/1000) | I22: =IFERROR(G22/H22,"")
G23: =IF(N(E23)*N(F23)=0,"",E23*F23) | H23: =IF(N(D23)*N(F23)=0,"",D23*F23/1000) | I23: =IFERROR(G23/H23,"") | K23: TOTAL / PONDERADO | L23: =SUM(L6:L21) -> 0 | M23: =SUM(M6:M21) -> 0 | N23: =IFERROR(L23/M23,"")
G24: =IF(N(E24)*N(F24)=0,"",E24*F24) | H24: =IF(N(D24)*N(F24)=0,"",D24*F24/1000) | I24: =IFERROR(G24/H24,"")
G25: =IF(N(E25)*N(F25)=0,"",E25*F25) | H25: =IF(N(D25)*N(F25)=0,"",D25*F25/1000) | I25: =IFERROR(G25/H25,"") | K25: Precio medio ponderado que usa HOY el modelo (Producto!D35): | N25: =Producto!D35 -> 43.670034
G26: =IF(N(E26)*N(F26)=0,"",E26*F26) | H26: =IF(N(D26)*N(F26)=0,"",D26*F26/1000) | I26: =IFERROR(G26/H26,"") | K26: Diferencia vs. tarifas reales (€/kg): | N26: =IFERROR(N23-N25,"")
G27: =IF(N(E27)*N(F27)=0,"",E27*F27) | H27: =IF(N(D27)*N(F27)=0,"",D27*F27/1000) | I27: =IFERROR(G27/H27,"")
G28: =IF(N(E28)*N(F28)=0,"",E28*F28) | H28: =IF(N(D28)*N(F28)=0,"",D28*F28/1000) | I28: =IFERROR(G28/H28,"")
G29: =IF(N(E29)*N(F29)=0,"",E29*F29) | H29: =IF(N(D29)*N(F29)=0,"",D29*F29/1000) | I29: =IFERROR(G29/H29,"")
G30: =IF(N(E30)*N(F30)=0,"",E30*F30) | H30: =IF(N(D30)*N(F30)=0,"",D30*F30/1000) | I30: =IFERROR(G30/H30,"")
G31: =IF(N(E31)*N(F31)=0,"",E31*F31) | H31: =IF(N(D31)*N(F31)=0,"",D31*F31/1000) | I31: =IFERROR(G31/H31,"")
G32: =IF(N(E32)*N(F32)=0,"",E32*F32) | H32: =IF(N(D32)*N(F32)=0,"",D32*F32/1000) | I32: =IFERROR(G32/H32,"")
G33: =IF(N(E33)*N(F33)=0,"",E33*F33) | H33: =IF(N(D33)*N(F33)=0,"",D33*F33/1000) | I33: =IFERROR(G33/H33,"")
G34: =IF(N(E34)*N(F34)=0,"",E34*F34) | H34: =IF(N(D34)*N(F34)=0,"",D34*F34/1000) | I34: =IFERROR(G34/H34,"")
G35: =IF(N(E35)*N(F35)=0,"",E35*F35) | H35: =IF(N(D35)*N(F35)=0,"",D35*F35/1000) | I35: =IFERROR(G35/H35,"")
G36: =IF(N(E36)*N(F36)=0,"",E36*F36) | H36: =IF(N(D36)*N(F36)=0,"",D36*F36/1000) | I36: =IFERROR(G36/H36,"")
G37: =IF(N(E37)*N(F37)=0,"",E37*F37) | H37: =IF(N(D37)*N(F37)=0,"",D37*F37/1000) | I37: =IFERROR(G37/H37,"")
G38: =IF(N(E38)*N(F38)=0,"",E38*F38) | H38: =IF(N(D38)*N(F38)=0,"",D38*F38/1000) | I38: =IFERROR(G38/H38,"")
... G204: =IF(N(E204)*N(F204)=0,"",E204*F204) | H204: =IF(N(D204)*N(F204)=0,"",D204*F204/1000) | I204: =IFERROR(G204/H204,"")

Sheet Restaurantes
A1: ROOTFLOW — Línea RESTAURANTES (reparto propio con riders desde un microhub)
A2: Segunda línea de negocio. La nave produce; una parte se reserva para restaurantes de las 8 zonas calientes, que reciben dos pedidos por semana con riders desde una cámara refrigerada alquilada. Celdas amarillas = inputs. El resto se calcula. La columna F sigue al selector de escenario (Hipótesis!C4).
A4: Concepto | B4: Unidad | C4: Conservador | D4: Base | E4: Optimista | F4: Activo | G4: Fuente / nota
A6: 1 · CUÁNTO DE LA NAVE VA A RESTAURANTES — la palanca del modelo
A7: % de la capacidad de la nave que se destina a restaurantes (objetivo) | B7: % | D7: 0.05 | G7: LA PALANCA. Sale de la distribución: la ocupación total no sube, cambia a quién se vende. 0 % = solo distribución. 5 % = reparto de COSTES_ROOTFLOW (5 % restaurante).
A8: Mes de lanzamiento de la línea | B8: mes | D8: 1 | G8: Mes del modelo en que arrancan microhub, riders y lanzadera.
A9: Meses de rampa hasta alcanzar el objetivo | B9: meses | C9: 36 | D9: 24 | E9: 18 | F9: =CHOOSE(Hipótesis!$C$4,C9,D9,E9) -> 24 | G9: Ritmo comercial. Base: 24 meses (~5 restaurantes netos nuevos al mes). Conservador más lento.
A10: ¿Limitar al mercado real de las zonas? (1 = sí) | B10: 1/0 | D10: 1 | G10: Con 1, nunca se vende a más restaurantes de los que el techo de abajo permite.
A11: Restaurantes abiertos en las 8 zonas (censo municipal) | B11: nº | D11: =D83 -> 585 | G11: Enlazado a la tabla de zonas (sección 7).
A12: Penetración máxima alcanzable | B12: % | D12: 0.3 | G12: Supuesto prudente: 3 de cada 10 restaurantes de la zona. Validar con los primeros meses.
A13: TECHO de restaurantes alcanzables | B13: nº | D13: =D11*D12 -> 175.5
A15: 2 · TICKET, FRECUENCIA Y PRECIO (modelo MICROHUB_COSTES · hoja Facturación)
A16: Cliente MÍNIMO — % de restaurantes | B16: % | D16: 0.55 | G16: MICROHUB_COSTES.xlsx
A17: Cliente MÍNIMO — ticket por pedido | B17: € | D17: 18.5
A18: Cliente MEDIO — % de restaurantes | B18: % | D18: 0.3
A19: Cliente MEDIO — ticket por pedido | B19: € | D19: 30
A20: Cliente PREMIUM — % de restaurantes | B20: % | D20: 0.15
A21: Cliente PREMIUM — ticket por pedido | B21: € | D21: 65
A22: TICKET MEDIO PONDERADO por pedido | B22: € | D22: =D16*D17+D18*D19+D20*D21 -> 28.925 | G22: 28,93 € con el mix de MICROHUB.
A23: Comprobación del mix (debe sumar 100 %) | D23: =IF(ABS(D16+D18+D20-1)<0.0001,"OK","REVISAR") -> OK
A24: Pedidos por semana y restaurante | B24: nº | D24: 2 | G24: Dos pedidos para tenerlo siempre fresco.
A25: Semanas por mes | B25: nº | D25: =Producto!$D$6/7 -> 4.3457143
A26: Ajuste de PRECIO restaurantes (índice sobre la tarifa de 30 g) | B26: índice | C26: 0.9 | D26: 1 | E26: 1.1 | F26: =CHOOSE(Hipótesis!$C$4,C26,D26,E26) -> 1 | G26: La tarifa de 30 g es la de MENOR €/g. Conservador = descuento de captación; optimista = más 15 g y 5 g.
A27: Merma + impagados restaurantes | B27: % | D27: 0.1 | G27: Igual que distribución.
A28: Días de cobro restaurantes | B28: días | D28: 30 | G28: Prudente. Sin factoring: son facturas pequeñas.
A29: Porte cobrado a pedidos pequeños (0 = no se cobra) | B29: €/pedido | D29: 0 | G29: Palanca de upside: la tarifa de referencia cobra 12 € a pedidos <35 €. Desactivado.
A30: % de pedidos que pagarían porte | B30: % | D30: =D16 -> 0.55 | G30: El segmento 'mínimo'.
A31: Estacionalidad: demanda de restaurantes en AGOSTO (factor) | B31: x | D31: 0.15 | G31: -85 % en agosto (MICROHUB). Esa producción no se siembra.
A32: Mes natural en que arranca el modelo (mes 1) | B32: 1-12 | D32: 4 | G32: Abril de 2027 (nave tras cerrar la financiación). Solo sirve para ubicar agosto.
A34: 3 · REPARTO CON RIDERS (autónomos, bici/moto, tipo Glovo)
A35: Días de reparto al mes | B35: días | D35: 25 | G35: MICROHUB_COSTES.xlsx
A36: Entregas por hora y rider (salida con la bolsa llena) | B36: entregas/h | C36: 5 | D36: 7 | E36: 8 | F36: =CHOOSE(Hipótesis!$C$4,C36,D36,E36) -> 7 | G36: 7-8 por salida de una hora (dato de producción). Conservador = 5.
A37: Coste rider (coste empresa) | B37: €/h | D37: 16 | G37: Cobran 12-13 €/h brutos; 16 €/h coste empresa.
A38: Ventana de reparto por rider y día | B38: h/día | D38: 5 | G38: Mañana antes del servicio + tarde antes de cenas. Fija cuándo hace falta el 2º rider.
A39: Horas mínimas pagadas por rider activo y día | B39: h/día | D39: 2 | G39: Prudente: con pocos pedidos se paga igualmente un turno mínimo.
A40: Kit por rider: mochila isotérmica + acumuladores (CAPEX) | B40: €/rider | D40: 150
A41: Riders previstos para el kit (CAPEX) | B41: nº | D41: 2
A43: 4 · MICROHUB (cámara refrigerada alquilada en la zona de reparto)
A44: Alquiler del microhub con cámaras refrigeradas | B44: €/mes | D44: 500 | G44: MICROHUB_COSTES.xlsx
A45: Suministros del microhub (luz de cámaras, si no van incluidos) | B45: €/mes | D45: 100 | G45: Supuesto.
A46: Acondicionamiento: estanterías, mesa inox, balanza, etiquetadora, sondas APPCC (CAPEX) | B46: € | D46: 3500 | G46: Supuesto. Validar con presupuesto.
A47: Cámara o armario refrigerado propio (CAPEX; 0 si va en el alquiler) | B47: € | D47: 0 | G47: La cámara va alquilada: 0.
A48: Fianza del alquiler del microhub | B48: meses | D48: 2
A50: 5 · LANZADERA NAVE → MICROHUB Y PREPARACIÓN DE PEDIDOS
A51: Viajes nave → microhub al mes | B51: nº | D51: =D35 -> 25 | G51: Uno por día de reparto.
A52: Kilómetros ida y vuelta por viaje | B52: km | D52: 30 | G52: Nave en el sur de Madrid → Salamanca/Chamberí.
A53: Combustible por km (9 L/100 km × 2,09 €/L) | B53: €/km | D53: =0.09*2.09 -> 0.1881 | G53: MICROHUB_COSTES · Furgoneta. El renting ya está en OPEX.
A54: Horas de conductor por viaje (con carga y descarga) | B54: h | D54: 1
A55: Coste hora de conductor | B55: €/h | D55: 16
A56: Minutos de preparación por pedido (picking + etiquetado) | B56: min | D56: 3 | G56: MICROHUB no lo incluía: se añade.
A57: Coste hora de preparación | B57: €/h | D57: 16
A58: Embalaje por pedido (bolsa, etiqueta) | B58: € | D58: 0.15 | G58: Supuesto.
A60: 6 · CAPTACIÓN Y CARTERA
A61: Coste de captación por restaurante (muestras, visitas) | B61: € | D61: 40 | G61: Supuesto.
A62: Rotación mensual de restaurantes (churn) | B62: % | D62: 0.015 | G62: ≈17 % al año. Hay que reponerlos y eso cuesta captación.
A63: Restaurantes que puede atender un comercial | B63: nº | D63: 100 | G63: Para el chequeo de capacidad comercial.
A64: LO QUE IMPLICA LA PALANCA — escenario activo, año 5 (se calcula solo)
A65: Restaurantes en cartera (mes 60) | B65: nº | D65: =Modelo_Mensual!$BJ$196 -> 123.0611
A66: Riders necesarios (mes 60) | B66: nº | D66: =Modelo_Mensual!$BJ$200 -> 2
A67: Entregas al día (media del año 5) | B67: nº | D67: =SUM(Modelo_Mensual!$AY$198:$BJ$198)/12 -> 39.752604
A68: % de los kilos que van a restaurantes (año 5) | B68: % | D68: =IFERROR(SUM(Modelo_Mensual!$AY$181:$BJ$181)/SUM(Modelo_Mensual!$AY$26:$BJ$26),0) -> 0.053379224
A69: % de los ingresos que vienen de restaurantes (año 5) | B69: % | D69: =IFERROR(SUM(Modelo_Mensual!$AY$35:$BJ$35)/SUM(Modelo_Mensual!$AY$36:$BJ$36),0) -> 0.20052502
A70: ¿El techo de mercado limita la palanca? | D70: =IF(Modelo_Mensual!$BJ$176<D7*Hipótesis!$D$13*Hipótesis!$F$26-0.5,"SÍ: subir la palanca ya no añade restaurantes","No") -> No
A72: 7 · ZONAS CALIENTES — restaurantes abiertos (Censo de Locales, Ayto. de Madrid, epígrafe 561001)
A73: Barrio | B73: Distrito | D73: Restaurantes
A74: Justicia | B74: Centro | D74: 140
A75: Recoletos | B75: Salamanca | D75: 92
A76: Castellana | B76: Salamanca | D76: 69
A77: Goya | B77: Salamanca | D77: 64
A78: Trafalgar | B78: Chamberí | D78: 62
A79: Almagro | B79: Chamberí | D79: 57
A80: Ríos Rosas | B80: Chamberí | D80: 54
A81: Lista | B81: Salamanca | D81: 47
A83: TOTAL 8 ZONAS | D83: =SUM(D74:D81) -> 585
A84: Fuente: datos.madrid.es · Censo de locales, sus actividades y terrazas (actualizado 01/10/2026). Locales en situación 'Abierto' con epígrafe 561001 RESTAURANTE. No incluye 714 bar-restaurantes de las mismas zonas: son mercado adicional no contado.

Sheet Pipeline
A1: ROOTFLOW — Pipeline comercial: demanda identificada por cliente y variedad
A2: Esta hoja ALIMENTA el modelo: cada cliente pide tarrinas/semana de variedades concretas. El modelo sirve primero esta demanda y añade encima la capa de nuevas cuentas.
A4: Semanas por mes (365/7/12) | D4: 4.35
A6: Parámetros por variedad (enlazados de Producto — no tocar) | G6: Micromez. | H6: Cilantro | I6: Albahaca | J6: R. daikon | K6: Rúcula | L6: R. rose | M6: Mostaza | N6: Brócoli | O6: Amaranto
A7: Precio MAYORISTA €/tarrina | G7: =Producto!F16 -> 3 | H7: =Producto!F17 -> 2.5 | I7: =Producto!F18 -> 2.5 | J7: =Producto!F19 -> 1.5 | K7: =Producto!F20 -> 1.5 | L7: =Producto!F21 -> 1.5 | M7: =Producto!F22 -> 1.5 | N7: =Producto!F23 -> 1.5 | O7: =Producto!F24 -> 3
A8: Tarrinas por bandeja | G8: =Producto!L16 -> 1.7 | H8: =Producto!L17 -> 4.8333333 | I8: =Producto!L18 -> 3 | J8: =Producto!L19 -> 8.1666667 | K8: =Producto!L20 -> 5.6666667 | L8: =Producto!L21 -> 8.1666667 | M8: =Producto!L22 -> 5.3333333 | N8: =Producto!L23 -> 5.6666667 | O8: =Producto!L24 -> 2.6666667
A9: Ciclos/mes | G9: =Producto!J16 -> 8.2216216 | H9: =Producto!J17 -> 3.042 | I9: =Producto!J18 -> 2.34 | J9: =Producto!J19 -> 10.14 | K9: =Producto!J20 -> 7.605 | L9: =Producto!J21 -> 10.14 | M9: =Producto!J22 -> 7.605 | N9: =Producto!J23 -> 7.605 | O9: =Producto!J24 -> 3.38
A10: COGS €/tarrina | G10: =Producto!R16/Producto!L16 -> 0.57370637 | H10: =Producto!R17/Producto!L17 -> 0.29349672 | I10: =Producto!R18/Producto!L18 -> 0.40496694 | J10: =Producto!R19/Producto!L19 -> 0.25717153 | K10: =Producto!R20/Producto!L20 -> 0.2647472 | L10: =Producto!R21/Producto!L21 -> 0.2567552 | M10: =Producto!R22/Producto!L22 -> 0.3222314 | N10: =Producto!R23/Producto!L23 -> 0.32104132 | O10: =Producto!R24/Producto!L24 -> 0.47821281
A11: Peso tarrina (g) | G11: =Producto!E16 -> 100 | H11: =Producto!E17 -> 30 | I11: =Producto!E18 -> 30 | J11: =Producto!E19 -> 30 | K11: =Producto!E20 -> 30 | L11: =Producto!E21 -> 30 | M11: =Producto!E22 -> 30 | N11: =Producto!E23 -> 30 | O11: =Producto!E24 -> 30
A12: Posiciones por tarrina·mes | G12: =1/(G8*G9) -> 0.071547357 | H12: =1/(H8*H9) -> 0.068013331 | I12: =1/(I8*I9) -> 0.14245014 | J12: =1/(J8*J9) -> 0.012075836 | K12: =1/(K8*K9) -> 0.023204548 | L12: =1/(L8*L9) -> 0.012075836 | M12: =1/(M8*M9) -> 0.024654832 | N12: =1/(N8*N9) -> 0.023204548 | O12: =1/(O8*O9) -> 0.11094675
A13: Bandejas por tarrina | G13: =1/G8 -> 0.58823529 | H13: =1/H8 -> 0.20689655 | I13: =1/I8 -> 0.33333333 | J13: =1/J8 -> 0.12244898 | K13: =1/K8 -> 0.17647059 | L13: =1/L8 -> 0.12244898 | M13: =1/M8 -> 0.1875 | N13: =1/N8 -> 0.17647059 | O13: =1/O8 -> 0.375
G14: tarrinas por SEMANA que pide cada cliente, por variedad
A15: Cliente | B15: Estado | C15: Desc. canal | D15: Prob. | E15: Mes inicio | F15: Rampa (meses) | G15: Micromez. | H15: Cilantro | I15: Albahaca | J15: R. daikon | K15: Rúcula | L15: R. rose | M15: Mostaza | N15: Brócoli | O15: Amaranto | P15: Tarrinas /mes | Q15: €/mes POTENCIAL | R15: €/mes PONDERADO | S15: kg/mes | T15: Bandejas /mes | U15: Posic. de luz | V15: % de la nave | W15: COGS €/mes | X15: Notas / próximos pasos
A16: Frutería La Huerta de Aranjuez | B16: ACTIVO | C16: 0 | D16: 0.95 | E16: 1 | F16: 3 | G16: 0 | H16: 200 | I16: 100 | J16: 0 | K16: 0 | L16: 0 | M16: 0 | N16: 0 | O16: 0 | P16: =SUM(G16:O16)*Pipeline!$D$4 -> 1305 | Q16: =SUMPRODUCT(G$7:O$7,G16:O16)*Pipeline!$D$4*(1-C16) -> 3262.5 | R16: =Q16*D16 -> 3099.375 | S16: =SUMPRODUCT(G$11:O$11,G16:O16)*Pipeline!$D$4/1000 -> 39.15 | T16: =SUMPRODUCT(G$13:O$13,G16:O16)*Pipeline!$D$4 -> 325 | U16: =SUMPRODUCT(G$12:O$12,G16:O16)*Pipeline!$D$4 -> 121.13741 | V16: =IFERROR(U16/(Hipótesis!$F$26*Hipótesis!$D$13),0) -> 0.042061601 | W16: =SUMPRODUCT(G$10:O$10,G16:O16)*Pipeline!$D$4 -> 431.50277 | X16: Cliente actual — crece gradual en nave nueva
A17: Sushita | B17: EN CONVERSACIÓN | C17: 0 | D17: 0.6 | E17: 2 | F17: 3 | G17: 30 | H17: 0 | I17: 0 | J17: 0 | K17: 0 | L17: 0 | M17: 0 | N17: 0 | O17: 0 | P17: =SUM(G17:O17)*Pipeline!$D$4 -> 130.5 | Q17: =SUMPRODUCT(G$7:O$7,G17:O17)*Pipeline!$D$4*(1-C17) -> 391.5 | R17: =Q17*D17 -> 234.9 | S17: =SUMPRODUCT(G$11:O$11,G17:O17)*Pipeline!$D$4/1000 -> 13.05 | T17: =SUMPRODUCT(G$13:O$13,G17:O17)*Pipeline!$D$4 -> 76.764706 | U17: =SUMPRODUCT(G$12:O$12,G17:O17)*Pipeline!$D$4 -> 9.33693 | V17: =IFERROR(U17/(Hipótesis!$F$26*Hipótesis!$D$13),0) -> 0.0032419896 | W17: =SUMPRODUCT(G$10:O$10,G17:O17)*Pipeline!$D$4 -> 74.868681 | X17: Cuenta HORECA pequeña — cerrar ya
A18: Frutas Eloy | B18: EN CONVERSACIÓN | C18: 0 | D18: 0.85 | E18: 3 | F18: 8 | G18: 600 | H18: 100 | I18: 100 | J18: 200 | K18: 0 | L18: 0 | M18: 0 | N18: 0 | O18: 0 | P18: =SUM(G18:O18)*Pipeline!$D$4 -> 4350 | Q18: =SUMPRODUCT(G$7:O$7,G18:O18)*Pipeline!$D$4*(1-C18) -> 11310 | R18: =Q18*D18 -> 9613.5 | S18: =SUMPRODUCT(G$11:O$11,G18:O18)*Pipeline!$D$4/1000 -> 313.2 | T18: =SUMPRODUCT(G$13:O$13,G18:O18)*Pipeline!$D$4 -> 1876.8247 | U18: =SUMPRODUCT(G$12:O$12,G18:O18)*Pipeline!$D$4 -> 288.79619 | V18: =IFERROR(U18/(Hipótesis!$F$26*Hipótesis!$D$13),0) -> 0.10027645 | W18: =SUMPRODUCT(G$10:O$10,G18:O18)*Pipeline!$D$4 -> 2024.9445 | X18: Cliente recurrente — sube despacio a micromezclum
A19: Mercamadrid (asentadores) | B19: POR ABRIR | C19: 0.2 | D19: 0.55 | E19: 6 | F19: 8 | G19: 1000 | H19: 0 | I19: 0 | J19: 0 | K19: 0 | L19: 0 | M19: 0 | N19: 0 | O19: 0 | P19: =SUM(G19:O19)*Pipeline!$D$4 -> 4350 | Q19: =SUMPRODUCT(G$7:O$7,G19:O19)*Pipeline!$D$4*(1-C19) -> 10440 | R19: =Q19*D19 -> 5742 | S19: =SUMPRODUCT(G$11:O$11,G19:O19)*Pipeline!$D$4/1000 -> 435 | T19: =SUMPRODUCT(G$13:O$13,G19:O19)*Pipeline!$D$4 -> 2558.8235 | U19: =SUMPRODUCT(G$12:O$12,G19:O19)*Pipeline!$D$4 -> 311.231 | V19: =IFERROR(U19/(Hipótesis!$F$26*Hipótesis!$D$13),0) -> 0.10806632 | W19: =SUMPRODUCT(G$10:O$10,G19:O19)*Pipeline!$D$4 -> 2495.6227 | X19: Micromezclum a granel — rampa larga de distribuidor
A20: Makro (cash & carry) | B20: EN CONVERSACIÓN | C20: 0.25 | D20: 0.25 | E20: 12 | F20: 10 | G20: 4000 | H20: 0 | I20: 0 | J20: 0 | K20: 0 | L20: 0 | M20: 0 | N20: 0 | O20: 0 | P20: =SUM(G20:O20)*Pipeline!$D$4 -> 17400 | Q20: =SUMPRODUCT(G$7:O$7,G20:O20)*Pipeline!$D$4*(1-C20) -> 39150 | R20: =Q20*D20 -> 9787.5 | S20: =SUMPRODUCT(G$11:O$11,G20:O20)*Pipeline!$D$4/1000 -> 1740 | T20: =SUMPRODUCT(G$13:O$13,G20:O20)*Pipeline!$D$4 -> 10235.294 | U20: =SUMPRODUCT(G$12:O$12,G20:O20)*Pipeline!$D$4 -> 1244.924 | V20: =IFERROR(U20/(Hipótesis!$F$26*Hipótesis!$D$13),0) -> 0.43226528 | W20: =SUMPRODUCT(G$10:O$10,G20:O20)*Pipeline!$D$4 -> 9982.4908 | X20: Gran cuenta: NO antes de capacidad probada. PENDIENTE LLAMADA
A21: Primaflor | B21: EN CONVERSACIÓN | C21: 0.3 | D21: 0.2 | E21: 14 | F21: 10 | G21: 2000 | H21: 0 | I21: 0 | J21: 0 | K21: 0 | L21: 0 | M21: 0 | N21: 0 | O21: 0 | P21: =SUM(G21:O21)*Pipeline!$D$4 -> 8700 | Q21: =SUMPRODUCT(G$7:O$7,G21:O21)*Pipeline!$D$4*(1-C21) -> 18270 | R21: =Q21*D21 -> 3654 | S21: =SUMPRODUCT(G$11:O$11,G21:O21)*Pipeline!$D$4/1000 -> 870 | T21: =SUMPRODUCT(G$13:O$13,G21:O21)*Pipeline!$D$4 -> 5117.6471 | U21: =SUMPRODUCT(G$12:O$12,G21:O21)*Pipeline!$D$4 -> 622.462 | V21: =IFERROR(U21/(Hipótesis!$F$26*Hipótesis!$D$13),0) -> 0.21613264 | W21: =SUMPRODUCT(G$10:O$10,G21:O21)*Pipeline!$D$4 -> 4991.2454 | X21: Co-packing: entra en año 2. PENDIENTE LLAMADA
A22: — hueco nueva cuenta — | C22: 0 | D22: 0 | E22: 1 | F22: 1 | G22: 0 | H22: 0 | I22: 0 | J22: 0 | K22: 0 | L22: 0 | M22: 0 | N22: 0 | O22: 0 | P22: =SUM(G22:O22)*Pipeline!$D$4 -> 0 | Q22: =SUMPRODUCT(G$7:O$7,G22:O22)*Pipeline!$D$4*(1-C22) -> 0 | R22: =Q22*D22 -> 0 | S22: =SUMPRODUCT(G$11:O$11,G22:O22)*Pipeline!$D$4/1000 -> 0 | T22: =SUMPRODUCT(G$13:O$13,G22:O22)*Pipeline!$D$4 -> 0 | U22: =SUMPRODUCT(G$12:O$12,G22:O22)*Pipeline!$D$4 -> 0 | V22: =IFERROR(U22/(Hipótesis!$F$26*Hipótesis!$D$13),0) -> 0 | W22: =SUMPRODUCT(G$10:O$10,G22:O22)*Pipeline!$D$4 -> 0
A23: TOTAL PIPELINE | P23: =SUM(P16:P22) -> 36235.5 | Q23: =SUM(Q16:Q22) -> 82824 | R23: =SUM(R16:R22) -> 32131.275 | S23: =SUM(S16:S22) -> 3410.4 | T23: =SUM(T16:T22) -> 20190.354 | U23: =SUM(U16:U22) -> 2597.8875 | V23: =IFERROR(U23/(Hipótesis!$F$26*Hipótesis!$D$13),0) -> 0.90204428 | W23: =SUM(W16:W22) -> 20000.675
A25: MIX QUE PIDE LA DEMANDA — posiciones de luz ponderadas (guía de siembra)
A26: Posiciones ponderadas | G26: =SUMPRODUCT($D$16:$D$22,G16:G22)*Pipeline!$D$4*G12 -> 771.23042 | H26: =SUMPRODUCT($D$16:$D$22,H16:H22)*Pipeline!$D$4*H12 -> 81.360947 | I26: =SUMPRODUCT($D$16:$D$22,I16:I22)*Pipeline!$D$4*I12 -> 111.53846 | J26: =SUMPRODUCT($D$16:$D$22,J16:J22)*Pipeline!$D$4*J12 -> 8.9300809 | K26: =SUMPRODUCT($D$16:$D$22,K16:K22)*Pipeline!$D$4*K12 -> 0 | L26: =SUMPRODUCT($D$16:$D$22,L16:L22)*Pipeline!$D$4*L12 -> 0 | M26: =SUMPRODUCT($D$16:$D$22,M16:M22)*Pipeline!$D$4*M12 -> 0 | N26: =SUMPRODUCT($D$16:$D$22,N16:N22)*Pipeline!$D$4*N12 -> 0 | O26: =SUMPRODUCT($D$16:$D$22,O16:O22)*Pipeline!$D$4*O12 -> 0
A27: % del mix demandado | G27: =IFERROR(G26/SUM($G$26:$O$26),0) -> 0.79258267 | H27: =IFERROR(H26/SUM($G$26:$O$26),0) -> 0.083613502 | I27: =IFERROR(I26/SUM($G$26:$O$26),0) -> 0.11462651 | J27: =IFERROR(J26/SUM($G$26:$O$26),0) -> 0.0091773187 | K27: =IFERROR(K26/SUM($G$26:$O$26),0) -> 0 | L27: =IFERROR(L26/SUM($G$26:$O$26),0) -> 0 | M27: =IFERROR(M26/SUM($G$26:$O$26),0) -> 0 | N27: =IFERROR(N26/SUM($G$26:$O$26),0) -> 0 | O27: =IFERROR(O26/SUM($G$26:$O$26),0) -> 0

Sheet Logistica
A1: ROOTFLOW — Logística: Madrid propio + resto de España (Athos)
A2: En Madrid repartimos con nuestras furgos (coste propio). Fuera de Madrid lo hace Athos: tarifa por CCAA y tramo de peso por envío. Ajusta el % de ventas fuera de Madrid y su reparto por CCAA.
A4: PARÁMETROS GENERALES
A5: % de las ventas (kg) que va FUERA de Madrid | B5: 0.35 | D5: El resto se reparte en Madrid con furgo propia
A6: Peso medio por ENVÍO fuera de Madrid (kg) | B6: 80 | D6: Determina el tramo de tarifa (0-25 / 26-50 / 51-100 / 101-150 / 151-200 / 201-299)
A7: Coste furgo PROPIA en Madrid (€/kg) | B7: 0.18 | D7: Combustible + amortización furgo + parte de reparto (no nómina de reparto, que ya está en OPEX)
A8: Recargo Athos (recogida 3€/pedido, seguro, etc.) % | B8: 0.05
A10: TARIFA ATHOS POR CCAA Y TRAMO DE PESO (€ por ENVÍO) — editable
A11: Comunidad Autónoma | B11: 0-25 kg | C11: 26-50 kg | D11: 51-100 kg | E11: 101-150 kg | F11: 151-200 kg | G11: 201-299 kg | H11: % de ventas fuera | I11: €/kg equivalente | J11: kg/mes régimen | K11: Coste/mes régimen
A12: Andalucía | B12: 29.05 | C12: 42.97 | D12: 59.17 | E12: 73.92 | F12: 84.56 | G12: 98.96 | H12: 0.12 | I12: =(IF($B$6<=25,B12,IF($B$6<=50,C12,IF($B$6<=100,D12,IF($B$6<=150,E12,IF($B$6<=200,F12,G12))))))/$B$6*(1+$B$8) -> 0.77660625 | J12: =$B$31*H12 -> 123.87731 | K12: =I12*J12 -> 96.203891
A13: Aragón | B13: 34.76 | C13: 46.14 | D13: 68.79 | E13: 77.41 | F13: 86.13 | G13: 94.68 | H13: 0.05 | I13: =(IF($B$6<=25,B13,IF($B$6<=50,C13,IF($B$6<=100,D13,IF($B$6<=150,E13,IF($B$6<=200,F13,G13))))))/$B$6*(1+$B$8) -> 0.90286875 | J13: =$B$31*H13 -> 51.615545 | K13: =I13*J13 -> 46.602062
A14: Asturias | B14: 27.08 | C14: 37.11 | D14: 48.64 | E14: 68.89 | F14: 83.48 | G14: 98.02 | H14: 0.03 | I14: =(IF($B$6<=25,B14,IF($B$6<=50,C14,IF($B$6<=100,D14,IF($B$6<=150,E14,IF($B$6<=200,F14,G14))))))/$B$6*(1+$B$8) -> 0.6384 | J14: =$B$31*H14 -> 30.969327 | K14: =I14*J14 -> 19.770818
A15: Cantabria | B15: 35.5 | C15: 43.1 | D15: 53.65 | E15: 68.71 | F15: 80.85 | G15: 99.06 | H15: 0.02 | I15: =(IF($B$6<=25,B15,IF($B$6<=50,C15,IF($B$6<=100,D15,IF($B$6<=150,E15,IF($B$6<=200,F15,G15))))))/$B$6*(1+$B$8) -> 0.70415625 | J15: =$B$31*H15 -> 20.646218 | K15: =I15*J15 -> 14.538163
A16: Castilla y León | B16: 37.7 | C16: 49.44 | D16: 61.97 | E16: 75.31 | F16: 90.68 | G16: 100.84 | H16: 0.1 | I16: =(IF($B$6<=25,B16,IF($B$6<=50,C16,IF($B$6<=100,D16,IF($B$6<=150,E16,IF($B$6<=200,F16,G16))))))/$B$6*(1+$B$8) -> 0.81335625 | J16: =$B$31*H16 -> 103.23109 | K16: =I16*J16 -> 83.963652
A17: Castilla-La Mancha | B17: 30.81 | C17: 40.86 | D17: 51.93 | E17: 65.67 | F17: 75.28 | G17: 87.47 | H17: 0.14 | I17: =(IF($B$6<=25,B17,IF($B$6<=50,C17,IF($B$6<=100,D17,IF($B$6<=150,E17,IF($B$6<=200,F17,G17))))))/$B$6*(1+$B$8) -> 0.68158125 | J17: =$B$31*H17 -> 144.52352 | K17: =I17*J17 -> 98.504525
A18: Cataluña | B18: 29.42 | C18: 42.71 | D18: 54.18 | E18: 66.64 | F18: 77.35 | G18: 91.02 | H18: 0.2 | I18: =(IF($B$6<=25,B18,IF($B$6<=50,C18,IF($B$6<=100,D18,IF($B$6<=150,E18,IF($B$6<=200,F18,G18))))))/$B$6*(1+$B$8) -> 0.7111125 | J18: =$B$31*H18 -> 206.46218 | K18: =I18*J18 -> 146.81784
A19: C. Valenciana | B19: 31.15 | C19: 41.35 | D19: 61.65 | E19: 69.37 | F19: 77.2 | G19: 84.84 | H19: 0.12 | I19: =(IF($B$6<=25,B19,IF($B$6<=50,C19,IF($B$6<=100,D19,IF($B$6<=150,E19,IF($B$6<=200,F19,G19))))))/$B$6*(1+$B$8) -> 0.80915625 | J19: =$B$31*H19 -> 123.87731 | K19: =I19*J19 -> 100.2361
A20: Extremadura | B20: 28.39 | C20: 42.97 | D20: 59.11 | E20: 73.62 | F20: 85.18 | G20: 98.3 | H20: 0.03 | I20: =(IF($B$6<=25,B20,IF($B$6<=50,C20,IF($B$6<=100,D20,IF($B$6<=150,E20,IF($B$6<=200,F20,G20))))))/$B$6*(1+$B$8) -> 0.77581875 | J20: =$B$31*H20 -> 30.969327 | K20: =I20*J20 -> 24.026584
A21: Galicia | B21: 28.39 | C21: 42.97 | D21: 59.11 | E21: 73.62 | F21: 85.18 | G21: 98.3 | H21: 0.05 | I21: =(IF($B$6<=25,B21,IF($B$6<=50,C21,IF($B$6<=100,D21,IF($B$6<=150,E21,IF($B$6<=200,F21,G21))))))/$B$6*(1+$B$8) -> 0.77581875 | J21: =$B$31*H21 -> 51.615545 | K21: =I21*J21 -> 40.044307
A22: La Rioja | B22: 36.87 | C22: 48.96 | D22: 73.02 | E22: 82.15 | F22: 91.44 | G22: 100.49 | H22: 0.02 | I22: =(IF($B$6<=25,B22,IF($B$6<=50,C22,IF($B$6<=100,D22,IF($B$6<=150,E22,IF($B$6<=200,F22,G22))))))/$B$6*(1+$B$8) -> 0.9583875 | J22: =$B$31*H22 -> 20.646218 | K22: =I22*J22 -> 19.787077
A23: Murcia | B23: 35.9 | C23: 47.66 | D23: 71.08 | E23: 79.96 | F23: 88.98 | G23: 97.8 | H23: 0.04 | I23: =(IF($B$6<=25,B23,IF($B$6<=50,C23,IF($B$6<=100,D23,IF($B$6<=150,E23,IF($B$6<=200,F23,G23))))))/$B$6*(1+$B$8) -> 0.932925 | J23: =$B$31*H23 -> 41.292436 | K23: =I23*J23 -> 38.522746
... A25: País Vasco | B25: 35.36 | C25: 42.9 | D25: 53.41 | E25: 68.41 | F25: 80.5 | G25: 98.63 | H25: 0.06 | I25: =(IF($B$6<=25,B25,IF($B$6<=50,C25,IF($B$6<=100,D25,IF($B$6<=150,E25,IF($B$6<=200,F25,G25))))))/$B$6*(1+$B$8) -> 0.70100625 | J25: =$B$31*H25 -> 61.938653 | K25: =I25*J25 -> 43.419383
A26: TOTAL FUERA DE MADRID | H26: =SUM(H12:H25) -> 1 | J26: =SUM(J12:J25) -> 1032.3109 | K26: =SUM(K12:K25) -> 792.22422
A28: REPARTO DE LA PRODUCCIÓN (régimen, mes 84)
A29: Producción que va a DISTRIBUCIÓN (kg/mes, régimen) | B29: =Modelo_Mensual!$CH$182 -> 2949.4597
A30: kg/mes en Madrid (furgo propia) | B30: =$B$29*(1-$B$5) -> 1917.1488
A31: kg/mes fuera de Madrid (Athos) | B31: =$B$29*$B$5 -> 1032.3109
A32: Coste logístico Madrid (€/mes) | B32: =$B$30*$B$7 -> 345.08678
A33: Coste logístico fuera Madrid (€/mes) | B33: =K26 -> 792.22422
A34: COSTE LOGÍSTICO TOTAL (€/mes régimen) | B34: =$B$32+$B$33 -> 1137.311
A35: Coste logístico medio (€/kg) | B35: =IFERROR($B$34/$B$29,0) -> 0.38559978
A36: Coste logístico de distribución como % de sus ingresos | B36: =IFERROR($B$34/Modelo_Mensual!$CH$34,0) -> 0.0099234792
A37: Nota: Athos cobra por ENVÍO según peso; agrupar pedidos de una misma CCAA en un envío mayor abarata mucho el €/kg (mira cómo baja al subir el peso medio por envío). Devoluciones +15%, aeropuerto +30€.
A39: €/kg medio ponderado FUERA (para el modelo mensual) | B39: =IFERROR(SUMPRODUCT(H12:H25,I12:I25)/SUM(H12:H25),0) -> 0.76742794

Sheet Hipótesis
A1: ROOTFLOW — Hipótesis del modelo
A2: Celdas azules = inputs. El selector de escenario reescribe la columna "Activo".
A4: ESCENARIO ACTIVO (1 = Conservador · 2 = Base · 3 = Optimista) | C4: 2 | D4: =CHOOSE($C$4,"CONSERVADOR","BASE","OPTIMISTA") -> BASE
A6: Concepto | B6: Unidad | C6: Conservador | D6: Base | E6: Optimista | F6: Activo
A7: GEOMETRÍA DEL RACK
A8: Rack ANTIGUO — bandejas por rack | B8: bandejas | D8: 32
A9: Rack NUEVO — superficie de cultivo POR NIVEL | B9: m²/nivel | D9: 24
A10: Rack NUEVO — nº de niveles | B10: niveles | D10: 6
A11: Superficie ocupada por bandeja | B11: m²/band | D11: 0.15
A12: Bandejas por nivel — CALCULADO | B12: bandejas | D12: =ROUNDDOWN(D9/D11,0) -> 160
A13: BANDEJAS POR RACK NUEVO — CALCULADO | B13: bandejas | D13: =D12*D10 -> 960
A14: Superficie de cultivo por rack — CALCULADO | B14: m² | D14: =D9*D10 -> 144
A15: AJUSTE POR ESCENARIO (flexiona la economía de Producto)
A16: Ajuste de PRECIO — línea DISTRIBUCIÓN (índice sobre la tarifa mayorista/tienda actual) | B16: % | C16: 0.9 | D16: 1 | E16: 1.1 | F16: =CHOOSE($C$4,C16,D16,E16) -> 1
A17: Ajuste de RENDIMIENTO / kg | B17: % | C17: 0.92 | D17: 1 | E17: 1.06 | F17: =CHOOSE($C$4,C17,D17,E17) -> 1
A18: Ajuste de COSTE de producto (índice sobre el coste bottom-up) | B18: % | C18: 1.05 | D18: 1 | E18: 0.9 | F18: =CHOOSE($C$4,C18,D18,E18) -> 1
A19: ECONOMÍA POR BANDEJA (Producto × escenario)
A20: Ingreso por bandeja — DISTRIBUCIÓN, nuevas cuentas (mezcla mayorista/tienda × índices) | B20: €/band/mes | C20: =((1-Hipótesis!$C$30)*Producto!$T$32+Hipótesis!$C$30*Producto!$AI$32)*Hipótesis!$C$16*Hipótesis!$C$17 -> 47.424169 | D20: =((1-Hipótesis!$D$30)*Producto!$T$32+Hipótesis!$D$30*Producto!$AI$32)*Hipótesis!$D$16*Hipótesis!$D$17 -> 57.275566 | E20: =((1-Hipótesis!$E$30)*Producto!$T$32+Hipótesis!$E$30*Producto!$AI$32)*Hipótesis!$E$16*Hipótesis!$E$17 -> 66.78331 | F20: =CHOOSE($C$4,C20,D20,E20) -> 57.275566
A21: Ingreso por bandeja — RESTAURANTES (tarifa 30 g × índice de precio restaurantes) | B21: €/band/mes | C21: =Producto!$AB$32*Restaurantes!$C$26*Hipótesis!$C$17 -> 177.89068 | D21: =Producto!$AB$32*Restaurantes!$D$26*Hipótesis!$D$17 -> 214.84381 | E21: =Producto!$AB$32*Restaurantes!$E$26*Hipótesis!$E$17 -> 250.50789 | F21: =CHOOSE($C$4,C21,D21,E21) -> 214.84381
A22: COGS por bandeja — DISTRIBUCIÓN (mezcla mayorista/tienda × índice de coste) | B22: €/band/mes | C22: =((1-Hipótesis!$C$30)*Producto!$S$32+Hipótesis!$C$30*Producto!$AJ$32)*Hipótesis!$C$18 -> 10.144796 | D22: =((1-Hipótesis!$D$30)*Producto!$S$32+Hipótesis!$D$30*Producto!$AJ$32)*Hipótesis!$D$18 -> 9.6617103 | E22: =((1-Hipótesis!$E$30)*Producto!$S$32+Hipótesis!$E$30*Producto!$AJ$32)*Hipótesis!$E$18 -> 8.6955393 | F22: =CHOOSE($C$4,C22,D22,E22) -> 9.6617103
A23: Rendimiento por bandeja | B23: kg/band/mes | C23: =Producto!$M$32*Hipótesis!$C$17 -> 1.1435901 | D23: =Producto!$M$32*Hipótesis!$D$17 -> 1.2430328 | E23: =Producto!$M$32*Hipótesis!$E$17 -> 1.3176147 | F23: =CHOOSE($C$4,C23,D23,E23) -> 1.2430328
A24: Ciclos (siembras) por posición y mes | B24: ciclos/mes | C24: =Producto!$J$32 -> 6.8941986 | D24: =Producto!$J$32 -> 6.8941986 | E24: =Producto!$J$32 -> 6.8941986 | F24: =CHOOSE($C$4,C24,D24,E24) -> 6.8941986
A25: CAPACIDAD Y RAMPA
A26: Capacidad total de la nave (racks NUEVOS) ← manda sobre el CAPEX | B26: racks | C26: 3 | D26: 3 | E26: 3 | F26: =CHOOSE($C$4,C26,D26,E26) -> 3
A27: Racks operativos al abrir (mes 1) | B27: racks | C27: 1 | D27: 1 | E27: 1 | F27: =CHOOSE($C$4,C27,D27,E27) -> 1
A28: Ritmo de instalación de racks | B28: racks/mes | C28: 0.5 | D28: 0.5 | E28: 0.5 | F28: =CHOOSE($C$4,C28,D28,E28) -> 0.5
A29: Capa ADICIONAL: mes de inicio de captación de nuevas cuentas | B29: mes | C29: 6 | D29: 6 | E29: 6 | F29: =CHOOSE($C$4,C29,D29,E29) -> 6
A30: Línea DISTRIBUCIÓN: % de las nuevas cuentas que son RETAIL (tienda) frente a mayorista | B30: % | C30: 0.05 | D30: 0.05 | E30: 0.05 | F30: =CHOOSE($C$4,C30,D30,E30) -> 0.05
A31: Capa ADICIONAL (nuevas cuentas): utilización inicial | B31: % | C31: 0 | D31: 0 | E31: 0 | F31: =CHOOSE($C$4,C31,D31,E31) -> 0
A32: Capa ADICIONAL: techo de utilización (igual en los 3 casos) | B32: % | C32: 0.55 | D32: 0.55 | E32: 0.55 | F32: =CHOOSE($C$4,C32,D32,E32) -> 0.55
A33: Capa ADICIONAL: meses hasta el techo | B33: meses | C33: 36 | D33: 36 | E33: 36 | F33: =CHOOSE($C$4,C33,D33,E33) -> 36
A34: Merma + comercial + impagados (igual en los 3) | B34: % | C34: 0.1 | D34: 0.1 | E34: 0.1 | F34: =CHOOSE($C$4,C34,D34,E34) -> 0.1
A35: COSTES FIJOS (mensual, sin nóminas)
A36: Alquiler de la nave (350 m²) | B36: €/mes | C36: 2250 | D36: 2000 | E36: 1800 | F36: =CHOOSE($C$4,C36,D36,E36) -> 2000
A37: Suministros — parte fija | B37: €/mes | C37: 400 | D37: 1000 | E37: 300 | F37: =CHOOSE($C$4,C37,D37,E37) -> 1000
A38: Electricidad variable por posición iluminada | B38: €/pos/mes | C38: 0.75 | D38: 0.55 | E38: 0.55 | F38: =CHOOSE($C$4,C38,D38,E38) -> 0.55
A39: Vehículo de reparto — renting + combustible | B39: €/mes | C39: 700 | D39: 800 | E39: 500 | F39: =CHOOSE($C$4,C39,D39,E39) -> 800
A40: Otros opex (gestoría, seguros, software, marketing) | B40: €/mes | C40: 700 | D40: 500 | E40: 500 | F40: =CHOOSE($C$4,C40,D40,E40) -> 500
A41: NÓMINAS — cada línea alimenta SU PROPIA fila de OPEX
A42: Coste Seguridad Social empresa (% s/ bruto) | B42: % | D42: 0.32
A43: SOCIOS — bruto €/mes POR AÑO (editable año a año) | C43: Año 1 | D43: Año 2 | E43: Año 3 | F43: Año 4 | G43: Año 5 | H43: Año 6 | I43: Año 7
A44: Bruto de CADA socio (aplica a las líneas con ¿Socio?=1) | C44: 2200 | D44: 3500 | E44: 4000 | F44: 4500 | G44: 5000 | H44: 5500 | I44: 6000
A45: Incremento salarial anual del RESTO de plantilla | B45: %/año | D45: 0.03
A46: Los socios cobran lo de la tabla de arriba según el año. El resto de plantilla parte de su bruto y sube ese % cada año.
A47: Rol | B47: Activo (1/0) | C47: Bruto €/mes | D47: Alta (mes) | E47: Cargado €/mes | F47: Horas bandeja/mes | G47: ¿Socio? (1/0)
A48: Pedro — socio (finanzas) | B48: 1 | C48: 2250 | D48: 1 | E48: =B48*IF(G48=1,Hipótesis!$C$44,C48)*(1+Hipótesis!$D$42) -> 2904 | F48: 0 | G48: 1
A49: Nico — socio (comercial) | B49: 1 | C49: 2250 | D49: 1 | E49: =B49*IF(G49=1,Hipótesis!$C$44,C49)*(1+Hipótesis!$D$42) -> 2904 | F49: 0 | G49: 1
A50: Guzmán — socio (producción) | B50: 1 | C50: 2250 | D50: 1 | E50: =B50*IF(G50=1,Hipótesis!$C$44,C50)*(1+Hipótesis!$D$42) -> 2904 | F50: 160 | G50: 1
A51: Encargado de producción | B51: 1 | C51: 2000 | D51: 1 | E51: =B51*IF(G51=1,Hipótesis!$C$44,C51)*(1+Hipótesis!$D$42) -> 2640 | F51: 160 | G51: 0
A52: Comercial / KAM | B52: 1 | C52: 2000 | D52: 20 | E52: =B52*IF(G52=1,Hipótesis!$C$44,C52)*(1+Hipótesis!$D$42) -> 2640 | F52: 0 | G52: 0
A53: (rol fijo libre) | B53: 0 | C53: 1700 | D53: 24 | E53: =B53*IF(G53=1,Hipótesis!$C$44,C53)*(1+Hipótesis!$D$42) -> 0 | F53: 160 | G53: 0
A54: Nóminas en régimen (todas las activas) | E54: =SUMPRODUCT($B$48:$B$53,IF($G$48:$G$53=1,Hipótesis!$I$44,$C$48:$C$53*(1+Hipótesis!$D$45)^6))*(1+Hipótesis!$D$42) -> 30064.596
A55: Nóminas activas en el MES 1 (para el colchón) | E55: =SUMPRODUCT(($D$48:$D$53<=1)*($B$48:$B$53)*IF($G$48:$G$53=1,Hipótesis!$C$44,$C$48:$C$53))*(1+Hipótesis!$D$42) -> 11352
A56: RONDA OBJETIVO — cuánto queremos pedir en total | B56: € | D56: 200000
A57: SUELDO MÁXIMO de socio (año 1) para que la necesidad = ronda objetivo | C57: =IFERROR(MAX(0,((Hipótesis!$D$56-CAPEX!$E$22)/CAPEX!$C$23-(Hipótesis!$C$36+Hipótesis!$C$37+Hipótesis!$C$39+Hipótesis!$C$40)-SUMPRODUCT(($D$48:$D$53<=1)*($B$48:$B$53)*($G$48:$G$53=0)*($C$48:$C$53))*(1+Hipótesis!$D$42))/(SUMPRODUCT(($D$48:$D$53<=1)*($B$48:$B$53)*($G$48:$G$53=1))*(1+Hipótesis!$D$42))),0) -> 5157.8283 | D57: =IFERROR(MAX(0,((Hipótesis!$D$56-CAPEX!$F$22)/CAPEX!$C$23-(Hipótesis!$D$36+Hipótesis!$D$37+Hipótesis!$D$39+Hipótesis!$D$40)-SUMPRODUCT(($D$48:$D$53<=1)*($B$48:$B$53)*($G$48:$G$53=0)*($C$48:$C$53))*(1+Hipótesis!$D$42))/(SUMPRODUCT(($D$48:$D$53<=1)*($B$48:$B$53)*($G$48:$G$53=1))*(1+Hipótesis!$D$42))),0) -> 4368.6869 | E57: =IFERROR(MAX(0,((Hipótesis!$D$56-CAPEX!$G$22)/CAPEX!$C$23-(Hipótesis!$E$36+Hipótesis!$E$37+Hipótesis!$E$39+Hipótesis!$E$40)-SUMPRODUCT(($D$48:$D$53<=1)*($B$48:$B$53)*($G$48:$G$53=0)*($C$48:$C$53))*(1+Hipótesis!$D$42))/(SUMPRODUCT(($D$48:$D$53<=1)*($B$48:$B$53)*($G$48:$G$53=1))*(1+Hipótesis!$D$42))),0) -> 2856.6919 | F57: =CHOOSE($C$4,C57,D57,E57) -> 4368.6869
A58: Copia ese importe en la casilla del AÑO 1 de la tabla de sueldos de arriba y la ronda cuadra sola. Columnas C/D/E = Conservador/Base/Optimista.
A59: Horas de bandeja de la plantilla FIJA (Guzmán + encargado) | E59: =SUMPRODUCT($B$48:$B$53,$F$48:$F$53) -> 320
A60: OPERARIOS DE CULTIVO — se calculan según los minutos del escenario
A61: Operario de cultivo — bruto €/mes | B61: €/mes | D61: 1700
A62: Operario de cultivo — coste cargado (con SS) | B62: €/mes | D62: =Hipótesis!$D$61*(1+Hipótesis!$D$42) -> 2244
A63: Operario de cultivo — horas de bandeja por mes | B63: h/mes | D63: 160
A64: Los operarios NO se listan a mano: el modelo calcula cuántos hacen falta cada mes según las bandejas y los minutos del escenario (a menos minutos, menos operarios).
A65: CIRCULANTE (NOF) — lo que tienes fuera en clientes
A66: Días de cobro a clientes (30 = máximo legal en perecederos) | B66: días | C66: 40 | D66: 30 | E66: 25 | F66: =CHOOSE($C$4,C66,D66,E66) -> 30
A67: Días de pago a proveedores | B67: días | C67: 30 | D67: 30 | E67: 45 | F67: =CHOOSE($C$4,C67,D67,E67) -> 30
A68: CAPEX de mantenimiento/reposición (% de ingresos) | B68: % | D68: 0.02
A69: PÓLIZA DE CRÉDITO (para financiar el circulante)
A70: Límite de la póliza de crédito | B70: € | D70: 50000
A71: Tipo de interés de la póliza | B71: % | D71: 0.055
A72: Caja objetivo — por debajo se dispone de la póliza | B72: € | D72: 30000
A73: % de facturas ANTICIPADAS (factoring sobre clientes grandes) | B73: % | D73: 0.6
A74: Coste todo incluido del factoring (comisión + interés) | B74: % | D74: 0.075
A75: REINVERSIÓN (Hito 4) Y REPARTO A SOCIOS
A76: Mes desde el que se aparta dinero para el Hito 4 | B76: mes | D76: 37
A77: % del beneficio neto que se reinvierte en Hito 4 | B77: % | D77: 0.4
A78: Mes mínimo para repartir (además exige deuda a cero) | B78: mes | D78: 37
A79: % del beneficio distribuible que se reparte | B79: % | D79: 0.5
A80: Caja mínima que NUNCA se reparte (colchón permanente) | B80: € | D80: 60000
A81: Capital social + prima tras la ampliación (base de la reserva legal) | B81: € | D81: 100030
A82: Participación de CADA socio | B82: % | D82: 0.3
A83: Tipo efectivo IRPF + SS trabajador sobre nómina | B83: % | D83: 0.3
A84: Tipo IRPF del ahorro sobre dividendos | B84: % | D84: 0.21
A85: AMORTIZACIÓN E IMPUESTOS
A86: Vida útil media de la inversión | B86: años | C86: 7 | D86: 7 | E86: 7 | F86: =CHOOSE($C$4,C86,D86,E86) -> 7
A87: Tipo IS reducido (entidad de nueva creación) | B87: % | C87: 0.15 | D87: 0.15 | E87: 0.15 | F87: =CHOOSE($C$4,C87,D87,E87) -> 0.15
A88: Tipo IS general (a partir del año indicado) | B88: % | C88: 0.25 | D88: 0.25 | E88: 0.25 | F88: =CHOOSE($C$4,C88,D88,E88) -> 0.25
A89: Año desde el que aplica el tipo GENERAL | B89: año | D89: 4
A90: TRAMO 1 · FFF / INVERSOR PRIVADO (aquí se calcula SU TIR y MOIC)
A91: ¿Activo? (1 = sí / 0 = no) | B91: 1/0 | D91: 1
A92: Importe FFF / inversor privado | B92: € | D92: 100000
A93: Capital FFF efectivo | B93: € | D93: =Hipótesis!$D$91*Hipótesis!$D$92 -> 100000
A94: Estructura (1=Préstamo·2=Participativo·3=Ctas.particip.·4=Rev-share·5=CAPITAL) | B94: 1-4 | D94: 5
A95: Interés fijo anual | B95: % | D95: 0.08
A96: Plazo (meses) | B96: meses | D96: 48
A97: Carencia de principal (meses) | B97: meses | D97: 6
A98: Componente variable s/ EBITDA (estructura 2) | B98: % | D98: 0.05
A99: % del beneficio para el inversor (estructura 3) | B99: % | D99: 0.4
A100: % de ingresos para el inversor (estructura 4) | B100: % | D100: 0.13
A101: Múltiplo tope MOIC (estructuras 3 y 4) | B101: x | D101: 2
A102: TRAMO 2 · ENISA AgroInnpulso — Línea Agro PYME (participativo). Términos EDITABLES: confírmalos con ENISA
...

Sheet Mano_de_obra
A1: ROOTFLOW — Mano de obra y dimensionamiento de plantilla
A2: La mano de obra es el coste real del negocio. Aquí se ve cuántas horas exige la producción y cuántas cubre la plantilla.
A4: MINUTOS POR BANDEJA (según escenario activo)
A5: Conservador (a mano) | B5: =Producto!$D$8 -> 4
A6: Base (lavadora + cinta/cosecha) | B6: =Producto!$D$9 -> 3
A7: Optimista (+ sembradora) | B7: =Producto!$D$10 -> 2
A8: MINUTOS/bandeja ACTIVO | B8: =Producto!$D$11 -> 3
A9: Escenario | B9: =CHOOSE(Hipótesis!$C$4,"Conservador","Base","Optimista") -> Base
A11: PLANTILLA (viene de Hipótesis) — horas de bandeja por persona
A12: Rol | B12: Activo | C12: Alta (mes) | D12: Horas bandeja/mes | E12: ¿Socio?
A13: =Hipótesis!A48 -> Pedro — socio (finanzas) | B13: =Hipótesis!B48 -> 1 | C13: =Hipótesis!D48 -> 1 | D13: =Hipótesis!F48 -> 0 | E13: =Hipótesis!G48 -> 1
A14: =Hipótesis!A49 -> Nico — socio (comercial) | B14: =Hipótesis!B49 -> 1 | C14: =Hipótesis!D49 -> 1 | D14: =Hipótesis!F49 -> 0 | E14: =Hipótesis!G49 -> 1
A15: =Hipótesis!A50 -> Guzmán — socio (producción) | B15: =Hipótesis!B50 -> 1 | C15: =Hipótesis!D50 -> 1 | D15: =Hipótesis!F50 -> 160 | E15: =Hipótesis!G50 -> 1
A16: =Hipótesis!A51 -> Encargado de producción | B16: =Hipótesis!B51 -> 1 | C16: =Hipótesis!D51 -> 1 | D16: =Hipótesis!F51 -> 160 | E16: =Hipótesis!G51 -> 0
A17: =Hipótesis!A52 -> Comercial / KAM | B17: =Hipótesis!B52 -> 1 | C17: =Hipótesis!D52 -> 20 | D17: =Hipótesis!F52 -> 0 | E17: =Hipótesis!G52 -> 0
A18: =Hipótesis!A53 -> (rol fijo libre) | B18: =Hipótesis!B53 -> 0 | C18: =Hipótesis!D53 -> 24 | D18: =Hipótesis!F53 -> 160 | E18: =Hipótesis!G53 -> 0
A19: Horas de bandeja disponibles en régimen (plantilla activa) | D19: =SUMPRODUCT(Hipótesis!$B$48:$B$53,Hipótesis!$F$48:$F$53) -> 320
A21: CARGA DE TRABAJO EN RÉGIMEN (mes 84)
A22: Bandejas sembradas/mes | B22: =Modelo_Mensual!$CH$27 -> 17860.226
A23: Horas de bandeja NECESARIAS/mes | B23: =Modelo_Mensual!$CH$28 -> 893.01132
A24: Horas de la plantilla FIJA (Guzmán + encargado) | B24: =Modelo_Mensual!$CH$29 -> 320
A25: OPERARIOS DE CULTIVO necesarios (nº) | B25: =Modelo_Mensual!$CH$30 -> 4
A26: Coste de esos operarios (€/mes) | B26: =-Modelo_Mensual!$CH$50 -> 10717.813
A27: PLANTILLA TOTAL (fijos + operarios) | B27: =Modelo_Mensual!$CH$31 -> 9
A28: Coste TOTAL de nóminas (€/mes) | B28: =-Modelo_Mensual!$CH$51 -> 40782.41
A30: Los operarios se calculan solos: a menos minutos por bandeja (más automatización), menos operarios. Por eso el Optimista tiene más CAPEX pero menos nómina.

Sheet CAPEX
A1: ROOTFLOW — Plan de inversión y necesidad de financiación
A2: Bottom-up de cuánto dinero hay que levantar para el salto a la nave.
A4: Concepto | C4: Importe (€) | D4: Nota | E4: CONSERVADOR | F4: BASE | G4: OPTIMISTA
A5: Adaptación de nave (clima, eléctrico trifásico, fontanería) | C5: 40000
A6: AUTOMATIZACIÓN (se activa según escenario):
A7: · Lavadora de bandejas | C7: 3000 | D7: Incluida en BASE y OPTIMISTA
A8: · Cinta / cosecha asistida | C8: 7000 | D8: Incluida en BASE y OPTIMISTA
A9: · Sembradora automática | C9: 25000 | D9: Incluida solo en OPTIMISTA
A10: Automatización incluida en el escenario ACTIVO | C10: =IF(Hipótesis!$C$4>=2,C7+C8,0)+IF(Hipótesis!$C$4=3,C9,0) -> 10000 | D10: Conservador=0 · Base=10.000 · Optimista=35.000 | E10: =0 -> 0 | F10: =C7+C8 -> 10000 | G10: =C7+C8+C9 -> 35000
A11: Coste de construcción por rack NUEVO | C11: 1600
A12: Nº de racks a construir | C12: =Hipótesis!$F$26 -> 3 | D12: ENLAZADO a la capacidad de Hipótesis (una sola fuente)
A13: Racks de cultivo (total) | C13: =C11*C12 -> 4800
A14: Instalación y montaje (mano de obra) | C14: 10000
A15: Vehículo de reparto (0 = renting) | C15: 0
A16: Mobiliario, utillaje, EPIs, varios | C16: 10000
A17: Licencias, proyecto técnico e ingeniería | C17: 6000
A18: Legal / estructuración (ENISA + inversor) | C18: 5000
A19: SUBTOTAL CAPEX | C19: =$C$38+C10+C15+C17+C18+$C$44 -> 89600 | D19: Incluye el microhub (fila 44). | E19: =$C$38+E10+C15+C17+C18+$C$44 -> 79600 | F19: =$C$38+F10+C15+C17+C18+$C$44 -> 89600 | G19: =$C$38+G10+C15+C17+C18+$C$44 -> 114600
A20: Contingencia (% s/ CAPEX) | C20: 0.15 | D20: Imprevistos de obra/equipo
A21: Contingencia (€) | C21: =C19*C20 -> 13440 | E21: =E19*C20 -> 11940 | F21: =F19*C20 -> 13440 | G21: =G19*C20 -> 17190
A22: CAPEX + Contingencia | C22: =C19+C21 -> 103040 | E22: =E19+E21 -> 91540 | F22: =F19+F21 -> 103040 | G22: =G19+G21 -> 131790
A23: Meses de colchón de arranque (pérdidas de la rampa) | C23: 4 | D23: El circulante va aparte, en su propia línea
A24: Coste fijo mensual al arrancar (€) | C24: =Hipótesis!$F$36+Hipótesis!$F$37+Hipótesis!$F$39+Hipótesis!$F$40+Hipótesis!$E$55+IF(AND(Restaurantes!$D$8<=1,Restaurantes!$D$7>0),Restaurantes!$D$44+Restaurantes!$D$45,0) -> 16252 | D24: Alquiler + suministros + vehículo + otros + NÓMINAS FIJAS DEL MES 1 | E24: =Hipótesis!$C$36+Hipótesis!$C$37+Hipótesis!$C$39+Hipótesis!$C$40+Hipótesis!$E$55+IF(AND(Restaurantes!$D$8<=1,Restaurantes!$D$7>0),Restaurantes!$D$44+Restaurantes!$D$45,0) -> 16002 | F24: =Hipótesis!$D$36+Hipótesis!$D$37+Hipótesis!$D$39+Hipótesis!$D$40+Hipótesis!$E$55+IF(AND(Restaurantes!$D$8<=1,Restaurantes!$D$7>0),Restaurantes!$D$44+Restaurantes!$D$45,0) -> 16252 | G24: =Hipótesis!$E$36+Hipótesis!$E$37+Hipótesis!$E$39+Hipótesis!$E$40+Hipótesis!$E$55+IF(AND(Restaurantes!$D$8<=1,Restaurantes!$D$7>0),Restaurantes!$D$44+Restaurantes!$D$45,0) -> 15052
A25: Colchón de circulante (€) | C25: =C23*C24 -> 65008 | E25: =C23*E24 -> 64008 | F25: =C23*F24 -> 65008 | G25: =C23*G24 -> 60208
A26: TOTAL INVERSIÓN = NECESIDAD DE FINANCIACIÓN | C26: =C22+C25+C50 -> 173048 | D26: CAPEX + contingencia + colchón de arranque + fianzas. | E26: =E22+E25+E50 -> 161048 | F26: =F22+F25+F50 -> 173048 | G26: =G22+G25+G50 -> 196598
A27: Circulante máximo (NOF) — NO se levanta: va a póliza de crédito | E27: =MAX(Esc_Conservador!$C$70:$CH$70) -> 46111.763 | F27: =MAX(Esc_Base!$C$70:$CH$70) -> 46623.466 | G27: =MAX(Esc_Optimista!$C$70:$CH$70) -> 41572.606
A28: Póliza máxima dispuesta en el plan (debe caber en el límite) | C28: Mes 1 | D28: Mes 2 | E28: =MAX(Esc_Conservador!$C$81:$CH$81) -> 29593.795 | F28: =MAX(Esc_Base!$C$81:$CH$81) -> 15580.848 | G28: =MAX(Esc_Optimista!$C$81:$CH$81) -> 10049.702 | H28: Mes 6 | I28: Mes 7 | J28: Mes 8 | K28: Mes 9 | L28: Mes 10 | M28: Mes 11 | N28: Mes 12
A29: % desplegado | C29: 0.3 | D29: 0.14 | E29: 0.1 | F29: 0.09 | G29: 0.08 | H29: 0.07 | I29: 0.06 | J29: 0.05 | K29: 0.04 | L29: 0.03 | M29: 0.02 | N29: 0.02
A30: Suma (debe ser 100%) | C30: =SUM(C29:N29) -> 1
A32: Las columnas Conservador/Base/Optimista calculan la inversión de cada caso a la vez (el Resumen las usa para comparar). La columna C es la del escenario ACTIVO.
A34: PRESUPUESTO DE OBRA — pendiente del presupuesto real
A35: Bloque nave + racks + acondicionamiento — bottom-up actual (€) | C35: =C5+C13+C14+C16 -> 64800
A36: PRESUPUESTO REAL del bloque (0 = usar el bottom-up de arriba) | C36: 0 | D36: Cuando llegue el presupuesto, escríbelo aquí y el modelo entero se recalcula.
A37: Ajuste % sobre el bloque (0 = ninguno · 0,25 = +25 %) | C37: 0 | D37: Para la sensibilidad rápida sin tocar el desglose.
A38: BLOQUE DE OBRA APLICADO (€) | C38: =IF($C$36>0,$C$36,$C$35*(1+$C$37)) -> 64800
A40: MICROHUB Y REPARTO A RESTAURANTES
A41: Acondicionamiento del microhub | C41: =Restaurantes!$D$46*(Restaurantes!$D$7>0) -> 3500
A42: Cámara / armario refrigerado propio | C42: =Restaurantes!$D$47*(Restaurantes!$D$7>0) -> 0
A43: Kit riders (mochilas isotérmicas + acumuladores) | C43: =Restaurantes!$D$40*Restaurantes!$D$41*(Restaurantes!$D$7>0) -> 300
A44: SUBTOTAL MICROHUB | C44: =SUM(C41:C43) -> 3800
A46: FIANZAS DE ALQUILER (salida de caja inicial; no se amortizan)
A47: Meses de fianza de la nave | C47: 2
A48: Fianza de la nave (€) | C48: =$C$47*Hipótesis!$F$36 -> 4000 | E48: =$C$47*Hipótesis!$C$36 -> 4500 | F48: =$C$47*Hipótesis!$D$36 -> 4000 | G48: =$C$47*Hipótesis!$E$36 -> 3600
A49: Fianza del microhub (€) | C49: =Restaurantes!$D$48*Restaurantes!$D$44*(Restaurantes!$D$7>0)*1 -> 1000
A50: TOTAL FIANZAS | C50: =C48+$C$49 -> 5000 | E50: =E48+$C$49 -> 5500 | F50: =F48+$C$49 -> 5000 | G50: =G48+$C$49 -> 4600

Sheet Modelo_Mensual
A1: ROOTFLOW — Modelo mensual · ESCENARIO ACTIVO (84 meses)
A2: Sigue al selector de Hipótesis!C4. Para el detalle mensual del caso que estés mirando.
A3: Mes | C3: 1 | D3: 2 | E3: 3 | F3: 4 | G3: 5 | H3: 6 | I3: 7 | J3: 8 | K3: 9 | L3: 10 | M3: 11 | N3: 12 | O3: 13 | P3: 14 | Q3: 15 | R3: 16 | S3: 17 | T3: 18 | U3: 19 | V3: 20 | W3: 21 | X3: 22 | Y3: 23 | Z3: 24 | AA3: 25 | AB3: 26 | AC3: 27 | AD3: 28 | AE3: 29 | AF3: 30 | AG3: 31 | AH3: 32 | AI3: 33 | AJ3: 34 | AK3: 35 | AL3: 36 | AM3: 37 | AN3: 38 | AO3: 39 | AP3: 40 | AQ3: 41 | AR3: 42 | AS3: 43 | AT3: 44 | AU3: 45 | AV3: 46 | AW3: 47 | AX3: 48 | AY3: 49 | AZ3: 50 | BA3: 51 | BB3: 52 | BC3: 53 | BD3: 54 | BE3: 55 | BF3: 56 | BG3: 57 | BH3: 58 | BI3: 59 | BJ3: 60 | BK3: 61 | BL3: 62 | BM3: 63 | BN3: 64 | BO3: 65 | BP3: 66 | BQ3: 67 | BR3: 68 | BS3: 69 | BT3: 70 | BU3: 71 | BV3: 72 | BW3: 73 | BX3: 74 | BY3: 75 | BZ3: 76 | CA3: 77 | CB3: 78 | CC3: 79 | CD3: 80 | CE3: 81 | CF3: 82 | CG3: 83 | CH3: 84
A4: Año | C4: =INT((1-1)/12)+1 -> 1 | D4: =INT((2-1)/12)+1 -> 1 | E4: =INT((3-1)/12)+1 -> 1 | F4: =INT((4-1)/12)+1 -> 1 | G4: =INT((5-1)/12)+1 -> 1 | H4: =INT((6-1)/12)+1 -> 1 | I4: =INT((7-1)/12)+1 -> 1 | J4: =INT((8-1)/12)+1 -> 1 | K4: =INT((9-1)/12)+1 -> 1 | L4: =INT((10-1)/12)+1 -> 1 | M4: =INT((11-1)/12)+1 -> 1 | N4: =INT((12-1)/12)+1 -> 1 | O4: =INT((13-1)/12)+1 -> 2 | P4: =INT((14-1)/12)+1 -> 2 | Q4: =INT((15-1)/12)+1 -> 2 | R4: =INT((16-1)/12)+1 -> 2 | S4: =INT((17-1)/12)+1 -> 2 | T4: =INT((18-1)/12)+1 -> 2 | U4: =INT((19-1)/12)+1 -> 2 | V4: =INT((20-1)/12)+1 -> 2 | W4: =INT((21-1)/12)+1 -> 2 | X4: =INT((22-1)/12)+1 -> 2 | Y4: =INT((23-1)/12)+1 -> 2 | Z4: =INT((24-1)/12)+1 -> 2 | AA4: =INT((25-1)/12)+1 -> 3 | AB4: =INT((26-1)/12)+1 -> 3 | AC4: =INT((27-1)/12)+1 -> 3 | AD4: =INT((28-1)/12)+1 -> 3 | AE4: =INT((29-1)/12)+1 -> 3 | AF4: =INT((30-1)/12)+1 -> 3 | AG4: =INT((31-1)/12)+1 -> 3 | AH4: =INT((32-1)/12)+1 -> 3 | AI4: =INT((33-1)/12)+1 -> 3 | AJ4: =INT((34-1)/12)+1 -> 3 | AK4: =INT((35-1)/12)+1 -> 3 | AL4: =INT((36-1)/12)+1 -> 3 | AM4: =INT((37-1)/12)+1 -> 4 | AN4: =INT((38-1)/12)+1 -> 4 | AO4: =INT((39-1)/12)+1 -> 4 | AP4: =INT((40-1)/12)+1 -> 4 | AQ4: =INT((41-1)/12)+1 -> 4 | AR4: =INT((42-1)/12)+1 -> 4 | AS4: =INT((43-1)/12)+1 -> 4 | AT4: =INT((44-1)/12)+1 -> 4 | AU4: =INT((45-1)/12)+1 -> 4 | AV4: =INT((46-1)/12)+1 -> 4 | AW4: =INT((47-1)/12)+1 -> 4 | AX4: =INT((48-1)/12)+1 -> 4 | AY4: =INT((49-1)/12)+1 -> 5 | AZ4: =INT((50-1)/12)+1 -> 5 | BA4: =INT((51-1)/12)+1 -> 5 | BB4: =INT((52-1)/12)+1 -> 5 | BC4: =INT((53-1)/12)+1 -> 5 | BD4: =INT((54-1)/12)+1 -> 5 | BE4: =INT((55-1)/12)+1 -> 5 | BF4: =INT((56-1)/12)+1 -> 5 | BG4: =INT((57-1)/12)+1 -> 5 | BH4: =INT((58-1)/12)+1 -> 5 | BI4: =INT((59-1)/12)+1 -> 5 | BJ4: =INT((60-1)/12)+1 -> 5 | BK4: =INT((61-1)/12)+1 -> 6 | BL4: =INT((62-1)/12)+1 -> 6 | BM4: =INT((63-1)/12)+1 -> 6 | BN4: =INT((64-1)/12)+1 -> 6 | BO4: =INT((65-1)/12)+1 -> 6 | BP4: =INT((66-1)/12)+1 -> 6 | BQ4: =INT((67-1)/12)+1 -> 6 | BR4: =INT((68-1)/12)+1 -> 6 | BS4: =INT((69-1)/12)+1 -> 6 | BT4: =INT((70-1)/12)+1 -> 6 | BU4: =INT((71-1)/12)+1 -> 6 | BV4: =INT((72-1)/12)+1 -> 6 | BW4: =INT((73-1)/12)+1 -> 7 | BX4: =INT((74-1)/12)+1 -> 7 | BY4: =INT((75-1)/12)+1 -> 7 | BZ4: =INT((76-1)/12)+1 -> 7 | CA4: =INT((77-1)/12)+1 -> 7 | CB4: =INT((78-1)/12)+1 -> 7 | CC4: =INT((79-1)/12)+1 -> 7 | CD4: =INT((80-1)/12)+1 -> 7 | CE4: =INT((81-1)/12)+1 -> 7 | CF4: =INT((82-1)/12)+1 -> 7 | CG4: =INT((83-1)/12)+1 -> 7 | CH4: =INT((84-1)/12)+1 -> 7
A6: CAPACIDAD, DEMANDA IDENTIFICADA Y MANO DE OBRA
A7: Racks instalados | C7: =MIN(Hipótesis!$F$26,Hipótesis!$F$27+Hipótesis!$F$28*(1-1)) -> 1 | D7: =MIN(Hipótesis!$F$26,Hipótesis!$F$27+Hipótesis!$F$28*(2-1)) -> 1.5 | E7: =MIN(Hipótesis!$F$26,Hipótesis!$F$27+Hipótesis!$F$28*(3-1)) -> 2 | F7: =MIN(Hipótesis!$F$26,Hipótesis!$F$27+Hipótesis!$F$28*(4-1)) -> 2.5 | G7: =MIN(Hipótesis!$F$26,Hipótesis!$F$27+Hipótesis!$F$28*(5-1)) -> 3 | H7: =MIN(Hipótesis!$F$26,Hipótesis!$F$27+Hipótesis!$F$28*(6-1)) -> 3 | I7: =MIN(Hipótesis!$F$26,Hipótesis!$F$27+Hipótesis!$F$28*(7-1)) -> 3 | J7: =MIN(Hipótesis!$F$26,Hipótesis!$F$27+Hipótesis!$F$28*(8-1)) -> 3 | K7: =MIN(Hipótesis!$F$26,Hipótesis!$F$27+Hipótesis!$F$28*(9-1)) -> 3 | L7: =MIN(Hipótesis!$F$26,Hipótesis!$F$27+Hipótesis!$F$28*(10-1)) -> 3 | M7: =MIN(Hipótesis!$F$26,Hipótesis!$F$27+Hipótesis!$F$28*(11-1)) -> 3 | N7: =MIN(Hipótesis!$F$26,Hipótesis!$F$27+Hipótesis!$F$28*(12-1)) -> 3 | O7: =MIN(Hipótesis!$F$26,Hipótesis!$F$27+Hipótesis!$F$28*(13-1)) -> 3 | P7: =MIN(Hipótesis!$F$26,Hipótesis!$F$27+Hipótesis!$F$28*(14-1)) -> 3 | Q7: =MIN(Hipótesis!$F$26,Hipótesis!$F$27+Hipótesis!$F$28*(15-1)) -> 3 | R7: =MIN(Hipótesis!$F$26,Hipótesis!$F$27+Hipótesis!$F$28*(16-1)) -> 3 | S7: =MIN(Hipótesis!$F$26,Hipótesis!$F$27+Hipótesis!$F$28*(17-1)) -> 3 | T7: =MIN(Hipótesis!$F$26,Hipótesis!$F$27+Hipótesis!$F$28*(18-1)) -> 3 | U7: =MIN(Hipótesis!$F$26,Hipótesis!$F$27+Hipótesis!$F$28*(19-1)) -> 3 | V7: =MIN(Hipótesis!$F$26,Hipótesis!$F$27+Hipótesis!$F$28*(20-1)) -> 3 | W7: =MIN(Hipótesis!$F$26,Hipótesis!$F$27+Hipótesis!$F$28*(21-1)) -> 3 | X7: =MIN(Hipótesis!$F$26,Hipótesis!$F$27+Hipótesis!$F$28*(22-1)) -> 3 | Y7: =MIN(Hipótesis!$F$26,Hipótesis!$F$27+Hipótesis!$F$28*(23-1)) -> 3 | Z7: =MIN(Hipótesis!$F$26,Hipótesis!$F$27+Hipótesis!$F$28*(24-1)) -> 3 | AA7: =MIN(Hipótesis!$F$26,Hipótesis!$F$27+Hipótesis!$F$28*(25-1)) -> 3 | AB7: =MIN(Hipótesis!$F$26,Hipótesis!$F$27+Hipótesis!$F$28*(26-1)) -> 3 | AC7: =MIN(Hipótesis!$F$26,Hipótesis!$F$27+Hipótesis!$F$28*(27-1)) -> 3 | AD7: =MIN(Hipótesis!$F$26,Hipótesis!$F$27+Hipótesis!$F$28*(28-1)) -> 3 | AE7: =MIN(Hipótesis!$F$26,Hipótesis!$F$27+Hipótesis!$F$28*(29-1)) -> 3 | AF7: =MIN(Hipótesis!$F$26,Hipótesis!$F$27+Hipótesis!$F$28*(30-1)) -> 3 | AG7: =MIN(Hipótesis!$F$26,Hipótesis!$F$27+Hipótesis!$F$28*(31-1)) -> 3 | AH7: =MIN(Hipótesis!$F$26,Hipótesis!$F$27+Hipótesis!$F$28*(32-1)) -> 3 | AI7: =MIN(Hipótesis!$F$26,Hipótesis!$F$27+Hipótesis!$F$28*(33-1)) -> 3 | AJ7: =MIN(Hipótesis!$F$26,Hipótesis!$F$27+Hipótesis!$F$28*(34-1)) -> 3 | AK7: =MIN(Hipótesis!$F$26,Hipótesis!$F$27+Hipótesis!$F$28*(35-1)) -> 3 | AL7: =MIN(Hipótesis!$F$26,Hipótesis!$F$27+Hipótesis!$F$28*(36-1)) -> 3 | AM7: =MIN(Hipótesis!$F$26,Hipótesis!$F$27+Hipótesis!$F$28*(37-1)) -> 3 | AN7: =MIN(Hipótesis!$F$26,Hipótesis!$F$27+Hipótesis!$F$28*(38-1)) -> 3 | AO7: =MIN(Hipótesis!$F$26,Hipótesis!$F$27+Hipótesis!$F$28*(39-1)) -> 3 | AP7: =MIN(Hipótesis!$F$26,Hipótesis!$F$27+Hipótesis!$F$28*(40-1)) -> 3 | AQ7: =MIN(Hipótesis!$F$26,Hipótesis!$F$27+Hipótesis!$F$28*(41-1)) -> 3 | AR7: =MIN(Hipótesis!$F$26,Hipótesis!$F$27+Hipótesis!$F$28*(42-1)) -> 3 | AS7: =MIN(Hipótesis!$F$26,Hipótesis!$F$27+Hipótesis!$F$28*(43-1)) -> 3 | AT7: =MIN(Hipótesis!$F$26,Hipótesis!$F$27+Hipótesis!$F$28*(44-1)) -> 3 | AU7: =MIN(Hipótesis!$F$26,Hipótesis!$F$27+Hipótesis!$F$28*(45-1)) -> 3 | AV7: =MIN(Hipótesis!$F$26,Hipótesis!$F$27+Hipótesis!$F$28*(46-1)) -> 3 | AW7: =MIN(Hipótesis!$F$26,Hipótesis!$F$27+Hipótesis!$F$28*(47-1)) -> 3 | AX7: =MIN(Hipótesis!$F$26,Hipótesis!$F$27+Hipótesis!$F$28*(48-1)) -> 3 | AY7: =MIN(Hipótesis!$F$26,Hipótesis!$F$27+Hipótesis!$F$28*(49-1)) -> 3 | AZ7: =MIN(Hipótesis!$F$26,Hipótesis!$F$27+Hipótesis!$F$28*(50-1)) -> 3 | BA7: =MIN(Hipótesis!$F$26,Hipótesis!$F$27+Hipótesis!$F$28*(51-1)) -> 3 | BB7: =MIN(Hipótesis!$F$26,Hipótesis!$F$27+Hipótesis!$F$28*(52-1)) -> 3 | BC7: =MIN(Hipótesis!$F$26,Hipótesis!$F$27+Hipótesis!$F$28*(53-1)) -> 3 | BD7: =MIN(Hipótesis!$F$26,Hipótesis!$F$27+Hipótesis!$F$28*(54-1)) -> 3 | BE7: =MIN(Hipótesis!$F$26,Hipótesis!$F$27+Hipótesis!$F$28*(55-1)) -> 3 | BF7: =MIN(Hipótesis!$F$26,Hipótesis!$F$27+Hipótesis!$F$28*(56-1)) -> 3 | BG7: =MIN(Hipótesis!$F$26,Hipótesis!$F$27+Hipótesis!$F$28*(57-1)) -> 3 | BH7: =MIN(Hipótesis!$F$26,Hipótesis!$F$27+Hipótesis!$F$28*(58-1)) -> 3 | BI7: =MIN(Hipótesis!$F$26,Hipótesis!$F$27+Hipótesis!$F$28*(59-1)) -> 3 | BJ7: =MIN(Hipótesis!$F$26,Hipótesis!$F$27+Hipótesis!$F$28*(60-1)) -> 3 | BK7: =MIN(Hipótesis!$F$26,Hipótesis!$F$27+Hipótesis!$F$28*(61-1)) -> 3 | BL7: =MIN(Hipótesis!$F$26,Hipótesis!$F$27+Hipótesis!$F$28*(62-1)) -> 3 | BM7: =MIN(Hipótesis!$F$26,Hipótesis!$F$27+Hipótesis!$F$28*(63-1)) -> 3 | BN7: =MIN(Hipótesis!$F$26,Hipótesis!$F$27+Hipótesis!$F$28*(64-1)) -> 3 | BO7: =MIN(Hipótesis!$F$26,Hipótesis!$F$27+Hipótesis!$F$28*(65-1)) -> 3 | BP7: =MIN(Hipótesis!$F$26,Hipótesis!$F$27+Hipótesis!$F$28*(66-1)) -> 3 | BQ7: =MIN(Hipótesis!$F$26,Hipótesis!$F$27+Hipótesis!$F$28*(67-1)) -> 3 | BR7: =MIN(Hipótesis!$F$26,Hipótesis!$F$27+Hipótesis!$F$28*(68-1)) -> 3 | BS7: =MIN(Hipótesis!$F$26,Hipótesis!$F$27+Hipótesis!$F$28*(69-1)) -> 3 | BT7: =MIN(Hipótesis!$F$26,Hipótesis!$F$27+Hipótesis!$F$28*(70-1)) -> 3 | BU7: =MIN(Hipótesis!$F$26,Hipótesis!$F$27+Hipótesis!$F$28*(71-1)) -> 3 | BV7: =MIN(Hipótesis!$F$26,Hipótesis!$F$27+Hipótesis!$F$28*(72-1)) -> 3 | BW7: =MIN(Hipótesis!$F$26,Hipótesis!$F$27+Hipótesis!$F$28*(73-1)) -> 3 | BX7: =MIN(Hipótesis!$F$26,Hipótesis!$F$27+Hipótesis!$F$28*(74-1)) -> 3 | BY7: =MIN(Hipótesis!$F$26,Hipótesis!$F$27+Hipótesis!$F$28*(75-1)) -> 3 | BZ7: =MIN(Hipótesis!$F$26,Hipótesis!$F$27+Hipótesis!$F$28*(76-1)) -> 3 | CA7: =MIN(Hipótesis!$F$26,Hipótesis!$F$27+Hipótesis!$F$28*(77-1)) -> 3 | CB7: =MIN(Hipótesis!$F$26,Hipótesis!$F$27+Hipótesis!$F$28*(78-1)) -> 3 | CC7: =MIN(Hipótesis!$F$26,Hipótesis!$F$27+Hipótesis!$F$28*(79-1)) -> 3 | CD7: =MIN(Hipótesis!$F$26,Hipótesis!$F$27+Hipótesis!$F$28*(80-1)) -> 3 | CE7: =MIN(Hipótesis!$F$26,Hipótesis!$F$27+Hipótesis!$F$28*(81-1)) -> 3 | CF7: =MIN(Hipótesis!$F$26,Hipótesis!$F$27+Hipótesis!$F$28*(82-1)) -> 3 | CG7: =MIN(Hipótesis!$F$26,Hipótesis!$F$27+Hipótesis!$F$28*(83-1)) -> 3 | CH7: =MIN(Hipótesis!$F$26,Hipótesis!$F$27+Hipótesis!$F$28*(84-1)) -> 3
A8: Posiciones de luz instaladas | C8: =C7*Hipótesis!$D$13 -> 960 | D8: =D7*Hipótesis!$D$13 -> 1440 | E8: =E7*Hipótesis!$D$13 -> 1920 | F8: =F7*Hipótesis!$D$13 -> 2400 | G8: =G7*Hipótesis!$D$13 -> 2880 | H8: =H7*Hipótesis!$D$13 -> 2880 | I8: =I7*Hipótesis!$D$13 -> 2880 | J8: =J7*Hipótesis!$D$13 -> 2880 | ... CH8: =CH7*Hipótesis!$D$13 -> 2880
A9: · Frutería La Huerta de Aranjuez (€/mes pond.) | C9: =Pipeline!$Q$16*Pipeline!$D$16*MIN(1,MAX(0,(1-Pipeline!$E$16+1)/MAX(Pipeline!$F$16,1))) -> 1033.125 | D9: =Pipeline!$Q$16*Pipeline!$D$16*MIN(1,MAX(0,(2-Pipeline!$E$16+1)/MAX(Pipeline!$F$16,1))) -> 2066.25 | E9: =Pipeline!$Q$16*Pipeline!$D$16*MIN(1,MAX(0,(3-Pipeline!$E$16+1)/MAX(Pipeline!$F$16,1))) -> 3099.375 | F9: =Pipeline!$Q$16*Pipeline!$D$16*MIN(1,MAX(0,(4-Pipeline!$E$16+1)/MAX(Pipeline!$F$16,1))) -> 3099.375 | G9: =Pipeline!$Q$16*Pipeline!$D$16*MIN(1,MAX(0,(5-Pipeline!$E$16+1)/MAX(Pipeline!$F$16,1))) -> 3099.375 | H9: =Pipeline!$Q$16*Pipeline!$D$16*MIN(1,MAX(0,(6-Pipeline!$E$16+1)/MAX(Pipeline!$F$16,1))) -> 3099.375 | I9: =Pipeline!$Q$16*Pipeline!$D$16*MIN(1,MAX(0,(7-Pipeline!$E$16+1)/MAX(Pipeline!$F$16,1))) -> 3099.375 | J9: =Pipeline!$Q$16*Pipeline!$D$16*MIN(1,MAX(0,(8-Pipeline!$E$16+1)/MAX(Pipeline!$F$16,1))) -> 3099.375 | K9: =Pipeline!$Q$16*Pipeline!$D$16*MIN(1,MAX(0,(9-Pipeline!$E$16+1)/MAX(Pipeline!$F$16,1))) -> 3099.375 | L9: =Pipeline!$Q$16*Pipeline!$D$16*MIN(1,MAX(0,(10-Pipeline!$E$16+1)/MAX(Pipeline!$F$16,1))) -> 3099.375 | M9: =Pipeline!$Q$16*Pipeline!$D$16*MIN(1,MAX(0,(11-Pipeline!$E$16+1)/MAX(Pipeline!$F$16,1))) -> 3099.375 | N9: =Pipeline!$Q$16*Pipeline!$D$16*MIN(1,MAX(0,(12-Pipeline!$E$16+1)/MAX(Pipeline!$F$16,1))) -> 3099.375 | O9: =Pipeline!$Q$16*Pipeline!$D$16*MIN(1,MAX(0,(13-Pipeline!$E$16+1)/MAX(Pipeline!$F$16,1))) -> 3099.375 | P9: =Pipeline!$Q$16*Pipeline!$D$16*MIN(1,MAX(0,(14-Pipeline!$E$16+1)/MAX(Pipeline!$F$16,1))) -> 3099.375 | Q9: =Pipeline!$Q$16*Pipeline!$D$16*MIN(1,MAX(0,(15-Pipeline!$E$16+1)/MAX(Pipeline!$F$16,1))) -> 3099.375 | R9: =Pipeline!$Q$16*Pipeline!$D$16*MIN(1,MAX(0,(16-Pipeline!$E$16+1)/MAX(Pipeline!$F$16,1))) -> 3099.375 | S9: =Pipeline!$Q$16*Pipeline!$D$16*MIN(1,MAX(0,(17-Pipeline!$E$16+1)/MAX(Pipeline!$F$16,1))) -> 3099.375 | T9: =Pipeline!$Q$16*Pipeline!$D$16*MIN(1,MAX(0,(18-Pipeline!$E$16+1)/MAX(Pipeline!$F$16,1))) -> 3099.375 | U9: =Pipeline!$Q$16*Pipeline!$D$16*MIN(1,MAX(0,(19-Pipeline!$E$16+1)/MAX(Pipeline!$F$16,1))) -> 3099.375 | V9: =Pipeline!$Q$16*Pipeline!$D$16*MIN(1,MAX(0,(20-Pipeline!$E$16+1)/MAX(Pipeline!$F$16,1))) -> 3099.375 | W9: =Pipeline!$Q$16*Pipeline!$D$16*MIN(1,MAX(0,(21-Pipeline!$E$16+1)/MAX(Pipeline!$F$16,1))) -> 3099.375 | X9: =Pipeline!$Q$16*Pipeline!$D$16*MIN(1,MAX(0,(22-Pipeline!$E$16+1)/MAX(Pipeline!$F$16,1))) -> 3099.375 | Y9: =Pipeline!$Q$16*Pipeline!$D$16*MIN(1,MAX(0,(23-Pipeline!$E$16+1)/MAX(Pipeline!$F$16,1))) -> 3099.375 | Z9: =Pipeline!$Q$16*Pipeline!$D$16*MIN(1,MAX(0,(24-Pipeline!$E$16+1)/MAX(Pipeline!$F$16,1))) -> 3099.375 | AA9: =Pipeline!$Q$16*Pipeline!$D$16*MIN(1,MAX(0,(25-Pipeline!$E$16+1)/MAX(Pipeline!$F$16,1))) -> 3099.375 | AB9: =Pipeline!$Q$16*Pipeline!$D$16*MIN(1,MAX(0,(26-Pipeline!$E$16+1)/MAX(Pipeline!$F$16,1))) -> 3099.375 | AC9: =Pipeline!$Q$16*Pipeline!$D$16*MIN(1,MAX(0,(27-Pipeline!$E$16+1)/MAX(Pipeline!$F$16,1))) -> 3099.375 | AD9: =Pipeline!$Q$16*Pipeline!$D$16*MIN(1,MAX(0,(28-Pipeline!$E$16+1)/MAX(Pipeline!$F$16,1))) -> 3099.375 | AE9: =Pipeline!$Q$16*Pipeline!$D$16*MIN(1,MAX(0,(29-Pipeline!$E$16+1)/MAX(Pipeline!$F$16,1))) -> 3099.375 | AF9: =Pipeline!$Q$16*Pipeline!$D$16*MIN(1,MAX(0,(30-Pipeline!$E$16+1)/MAX(Pipeline!$F$16,1))) -> 3099.375 | AG9: =Pipeline!$Q$16*Pipeline!$D$16*MIN(1,MAX(0,(31-Pipeline!$E$16+1)/MAX(Pipeline!$F$16,1))) -> 3099.375 | AH9: =Pipeline!$Q$16*Pipeline!$D$16*MIN(1,MAX(0,(32-Pipeline!$E$16+1)/MAX(Pipeline!$F$16,1))) -> 3099.375 | AI9: =Pipeline!$Q$16*Pipeline!$D$16*MIN(1,MAX(0,(33-Pipeline!$E$16+1)/MAX(Pipeline!$F$16,1))) -> 3099.375 | AJ9: =Pipeline!$Q$16*Pipeline!$D$16*MIN(1,MAX(0,(34-Pipeline!$E$16+1)/MAX(Pipeline!$F$16,1))) -> 3099.375 | AK9: =Pipeline!$Q$16*Pipeline!$D$16*MIN(1,MAX(0,(35-Pipeline!$E$16+1)/MAX(Pipeline!$F$16,1))) -> 3099.375 | AL9: =Pipeline!$Q$16*Pipeline!$D$16*MIN(1,MAX(0,(36-Pipeline!$E$16+1)/MAX(Pipeline!$F$16,1))) -> 3099.375 | AM9: =Pipeline!$Q$16*Pipeline!$D$16*MIN(1,MAX(0,(37-Pipeline!$E$16+1)/MAX(Pipeline!$F$16,1))) -> 3099.375 | AN9: =Pipeline!$Q$16*Pipeline!$D$16*MIN(1,MAX(0,(38-Pipeline!$E$16+1)/MAX(Pipeline!$F$16,1))) -> 3099.375 | AO9: =Pipeline!$Q$16*Pipeline!$D$16*MIN(1,MAX(0,(39-Pipeline!$E$16+1)/MAX(Pipeline!$F$16,1))) -> 3099.375 | AP9: =Pipeline!$Q$16*Pipeline!$D$16*MIN(1,MAX(0,(40-Pipeline!$E$16+1)/MAX(Pipeline!$F$16,1))) -> 3099.375 | AQ9: =Pipeline!$Q$16*Pipeline!$D$16*MIN(1,MAX(0,(41-Pipeline!$E$16+1)/MAX(Pipeline!$F$16,1))) -> 3099.375 | AR9: =Pipeline!$Q$16*Pipeline!$D$16*MIN(1,MAX(0,(42-Pipeline!$E$16+1)/MAX(Pipeline!$F$16,1))) -> 3099.375 | AS9: =Pipeline!$Q$16*Pipeline!$D$16*MIN(1,MAX(0,(43-Pipeline!$E$16+1)/MAX(Pipeline!$F$16,1))) -> 3099.375 | AT9: =Pipeline!$Q$16*Pipeline!$D$16*MIN(1,MAX(0,(44-Pipeline!$E$16+1)/MAX(Pipeline!$F$16,1))) -> 3099.375 | AU9: =Pipeline!$Q$16*Pipeline!$D$16*MIN(1,MAX(0,(45-Pipeline!$E$16+1)/MAX(Pipeline!$F$16,1))) -> 3099.375 | AV9: =Pipeline!$Q$16*Pipeline!$D$16*MIN(1,MAX(0,(46-Pipeline!$E$16+1)/MAX(Pipeline!$F$16,1))) -> 3099.375 | AW9: =Pipeline!$Q$16*Pipeline!$D$16*MIN(1,MAX(0,(47-Pipeline!$E$16+1)/MAX(Pipeline!$F$16,1))) -> 3099.375 | AX9: =Pipeline!$Q$16*Pipeline!$D$16*MIN(1,MAX(0,(48-Pipeline!$E$16+1)/MAX(Pipeline!$F$16,1))) -> 3099.375 | AY9: =Pipeline!$Q$16*Pipeline!$D$16*MIN(1,MAX(0,(49-Pipeline!$E$16+1)/MAX(Pipeline!$F$16,1))) -> 3099.375 | AZ9: =Pipeline!$Q$16*Pipeline!$D$16*MIN(1,MAX(0,(50-Pipeline!$E$16+1)/MAX(Pipeline!$F$16,1))) -> 3099.375 | BA9: =Pipeline!$Q$16*Pipeline!$D$16*MIN(1,MAX(0,(51-Pipeline!$E$16+1)/MAX(Pipeline!$F$16,1))) -> 3099.375 | BB9: =Pipeline!$Q$16*Pipeline!$D$16*MIN(1,MAX(0,(52-Pipeline!$E$16+1)/MAX(Pipeline!$F$16,1))) -> 3099.375 | BC9: =Pipeline!$Q$16*Pipeline!$D$16*MIN(1,MAX(0,(53-Pipeline!$E$16+1)/MAX(Pipeline!$F$16,1))) -> 3099.375 | BD9: =Pipeline!$Q$16*Pipeline!$D$16*MIN(1,MAX(0,(54-Pipeline!$E$16+1)/MAX(Pipeline!$F$16,1))) -> 3099.375 | BE9: =Pipeline!$Q$16*Pipeline!$D$16*MIN(1,MAX(0,(55-Pipeline!$E$16+1)/MAX(Pipeline!$F$16,1))) -> 3099.375 | BF9: =Pipeline!$Q$16*Pipeline!$D$16*MIN(1,MAX(0,(56-Pipeline!$E$16+1)/MAX(Pipeline!$F$16,1))) -> 3099.375 | BG9: =Pipeline!$Q$16*Pipeline!$D$16*MIN(1,MAX(0,(57-Pipeline!$E$16+1)/MAX(Pipeline!$F$16,1))) -> 3099.375 | BH9: =Pipeline!$Q$16*Pipeline!$D$16*MIN(1,MAX(0,(58-Pipeline!$E$16+1)/MAX(Pipeline!$F$16,1))) -> 3099.375 | BI9: =Pipeline!$Q$16*Pipeline!$D$16*MIN(1,MAX(0,(59-Pipeline!$E$16+1)/MAX(Pipeline!$F$16,1))) -> 3099.375 | BJ9: =Pipeline!$Q$16*Pipeline!$D$16*MIN(1,MAX(0,(60-Pipeline!$E$16+1)/MAX(Pipeline!$F$16,1))) -> 3099.375 | BK9: =Pipeline!$Q$16*Pipeline!$D$16*MIN(1,MAX(0,(61-Pipeline!$E$16+1)/MAX(Pipeline!$F$16,1))) -> 3099.375 | BL9: =Pipeline!$Q$16*Pipeline!$D$16*MIN(1,MAX(0,(62-Pipeline!$E$16+1)/MAX(Pipeline!$F$16,1))) -> 3099.375 | BM9: =Pipeline!$Q$16*Pipeline!$D$16*MIN(1,MAX(0,(63-Pipeline!$E$16+1)/MAX(Pipeline!$F$16,1))) -> 3099.375 | BN9: =Pipeline!$Q$16*Pipeline!$D$16*MIN(1,MAX(0,(64-Pipeline!$E$16+1)/MAX(Pipeline!$F$16,1))) -> 3099.375 | BO9: =Pipeline!$Q$16*Pipeline!$D$16*MIN(1,MAX(0,(65-Pipeline!$E$16+1)/MAX(Pipeline!$F$16,1))) -> 3099.375 | BP9: =Pipeline!$Q$16*Pipeline!$D$16*MIN(1,MAX(0,(66-Pipeline!$E$16+1)/MAX(Pipeline!$F$16,1))) -> 3099.375 | BQ9: =Pipeline!$Q$16*Pipeline!$D$16*MIN(1,MAX(0,(67-Pipeline!$E$16+1)/MAX(Pipeline!$F$16,1))) -> 3099.375 | BR9: =Pipeline!$Q$16*Pipeline!$D$16*MIN(1,MAX(0,(68-Pipeline!$E$16+1)/MAX(Pipeline!$F$16,1))) -> 3099.375 | BS9: =Pipeline!$Q$16*Pipeline!$D$16*MIN(1,MAX(0,(69-Pipeline!$E$16+1)/MAX(Pipeline!$F$16,1))) -> 3099.375 | BT9: =Pipeline!$Q$16*Pipeline!$D$16*MIN(1,MAX(0,(70-Pipeline!$E$16+1)/MAX(Pipeline!$F$16,1))) -> 3099.375 | BU9: =Pipeline!$Q$16*Pipeline!$D$16*MIN(1,MAX(0,(71-Pipeline!$E$16+1)/MAX(Pipeline!$F$16,1))) -> 3099.375 | BV9: =Pipeline!$Q$16*Pipeline!$D$16*MIN(1,MAX(0,(72-Pipeline!$E$16+1)/MAX(Pipeline!$F$16,1))) -> 3099.375 | BW9: =Pipeline!$Q$16*Pipeline!$D$16*MIN(1,MAX(0,(73-Pipeline!$E$16+1)/MAX(Pipeline!$F$16,1))) -> 3099.375 | BX9: =Pipeline!$Q$16*Pipeline!$D$16*MIN(1,MAX(0,(74-Pipeline!$E$16+1)/MAX(Pipeline!$F$16,1))) -> 3099.375 | BY9: =Pipeline!$Q$16*Pipeline!$D$16*MIN(1,MAX(0,(75-Pipeline!$E$16+1)/MAX(Pipeline!$F$16,1))) -> 3099.375 | BZ9: =Pipeline!$Q$16*Pipeline!$D$16*MIN(1,MAX(0,(76-Pipeline!$E$16+1)/MAX(Pipeline!$F$16,1))) -> 3099.375 | CA9: =Pipeline!$Q$16*Pipeline!$D$16*MIN(1,MAX(0,(77-Pipeline!$E$16+1)/MAX(Pipeline!$F$16,1))) -> 3099.375 | CB9: =Pipeline!$Q$16*Pipeline!$D$16*MIN(1,MAX(0,(78-Pipeline!$E$16+1)/MAX(Pipeline!$F$16,1))) -> 3099.375 | CC9: =Pipeline!$Q$16*Pipeline!$D$16*MIN(1,MAX(0,(79-Pipeline!$E$16+1)/MAX(Pipeline!$F$16,1))) -> 3099.375 | CD9: =Pipeline!$Q$16*Pipeline!$D$16*MIN(1,MAX(0,(80-Pipeline!$E$16+1)/MAX(Pipeline!$F$16,1))) -> 3099.375 | CE9: =Pipeline!$Q$16*Pipeline!$D$16*MIN(1,MAX(0,(81-Pipeline!$E$16+1)/MAX(Pipeline!$F$16,1))) -> 3099.375 | CF9: =Pipeline!$Q$16*Pipeline!$D$16*MIN(1,MAX(0,(82-Pipeline!$E$16+1)/MAX(Pipeline!$F$16,1))) -> 3099.375 | CG9: =Pipeline!$Q$16*Pipeline!$D$16*MIN(1,MAX(0,(83-Pipeline!$E$16+1)/MAX(Pipeline!$F$16,1))) -> 3099.375 | CH9: =Pipeline!$Q$16*Pipeline!$D$16*MIN(1,MAX(0,(84-Pipeline!$E$16+1)/MAX(Pipeline!$F$16,1))) -> 3099.375
A10: · Sushita (€/mes pond.) | C10: =Pipeline!$Q$17*Pipeline!$D$17*MIN(1,MAX(0,(1-Pipeline!$E$17+1)/MAX(Pipeline!$F$17,1))) -> 0 | D10: =Pipeline!$Q$17*Pipeline!$D$17*MIN(1,MAX(0,(2-Pipeline!$E$17+1)/MAX(Pipeline!$F$17,1))) -> 78.3 | E10: =Pipeline!$Q$17*Pipeline!$D$17*MIN(1,MAX(0,(3-Pipeline!$E$17+1)/MAX(Pipeline!$F$17,1))) -> 156.6 | F10: =Pipeline!$Q$17*Pipeline!$D$17*MIN(1,MAX(0,(4-Pipeline!$E$17+1)/MAX(Pipeline!$F$17,1))) -> 234.9 | G10: =Pipeline!$Q$17*Pipeline!$D$17*MIN(1,MAX(0,(5-Pipeline!$E$17+1)/MAX(Pipeline!$F$17,1))) -> 234.9 | H10: =Pipeline!$Q$17*Pipeline!$D$17*MIN(1,MAX(0,(6-Pipeline!$E$17+1)/MAX(Pipeline!$F$17,1))) -> 234.9 | I10: =Pipeline!$Q$17*Pipeline!$D$17*MIN(1,MAX(0,(7-Pipeline!$E$17+1)/MAX(Pipeline!$F$17,1))) -> 234.9 | J10: =Pipeline!$Q$17*Pipeline!$D$17*MIN(1,MAX(0,(8-Pipeline!$E$17+1)/MAX(Pipeline!$F$17,1))) -> 234.9 | K10: =Pipeline!$Q$17*Pipeline!$D$17*MIN(1,MAX(0,(9-Pipeline!$E$17+1)/MAX(Pipeline!$F$17,1))) -> 234.9 | L10: =Pipeline!$Q$17*Pipeline!$D$17*MIN(1,MAX(0,(10-Pipeline!$E$17+1)/MAX(Pipeline!$F$17,1))) -> 234.9 | M10: =Pipeline!$Q$17*Pipeline!$D$17*MIN(1,MAX(0,(11-Pipeline!$E$17+1)/MAX(Pipeline!$F$17,1))) -> 234.9 | N10: =Pipeline!$Q$17*Pipeline!$D$17*MIN(1,MAX(0,(12-Pipeline!$E$17+1)/MAX(Pipeline!$F$17,1))) -> 234.9 | O10: =Pipeline!$Q$17*Pipeline!$D$17*MIN(1,MAX(0,(13-Pipeline!$E$17+1)/MAX(Pipeline!$F$17,1))) -> 234.9 | P10: =Pipeline!$Q$17*Pipeline!$D$17*MIN(1,MAX(0,(14-Pipeline!$E$17+1)/MAX(Pipeline!$F$17,1))) -> 234.9 | Q10: =Pipeline!$Q$17*Pipeline!$D$17*MIN(1,MAX(0,(15-Pipeline!$E$17+1)/MAX(Pipeline!$F$17,1))) -> 234.9 | R10: =Pipeline!$Q$17*Pipeline!$D$17*MIN(1,MAX(0,(16-Pipeline!$E$17+1)/MAX(Pipeline!$F$17,1))) -> 234.9 | S10: =Pipeline!$Q$17*Pipeline!$D$17*MIN(1,MAX(0,(17-Pipeline!$E$17+1)/MAX(Pipeline!$F$17,1))) -> 234.9 | T10: =Pipeline!$Q$17*Pipeline!$D$17*MIN(1,MAX(0,(18-Pipeline!$E$17+1)/MAX(Pipeline!$F$17,1))) -> 234.9 | U10: =Pipeline!$Q$17*Pipeline!$D$17*MIN(1,MAX(0,(19-Pipeline!$E$17+1)/MAX(Pipeline!$F$17,1))) -> 234.9 | V10: =Pipeline!$Q$17*Pipeline!$D$17*MIN(1,MAX(0,(20-Pipeline!$E$17+1)/MAX(Pipeline!$F$17,1))) -> 234.9 | W10: =Pipeline!$Q$17*Pipeline!$D$17*MIN(1,MAX(0,(21-Pipeline!$E$17+1)/MAX(Pipeline!$F$17,1))) -> 234.9 | X10: =Pipeline!$Q$17*Pipeline!$D$17*MIN(1,MAX(0,(22-Pipeline!$E$17+1)/MAX(Pipeline!$F$17,1))) -> 234.9 | Y10: =Pipeline!$Q$17*Pipeline!$D$17*MIN(1,MAX(0,(23-Pipeline!$E$17+1)/MAX(Pipeline!$F$17,1))) -> 234.9 | Z10: =Pipeline!$Q$17*Pipeline!$D$17*MIN(1,MAX(0,(24-Pipeline!$E$17+1)/MAX(Pipeline!$F$17,1))) -> 234.9 | AA10: =Pipeline!$Q$17*Pipeline!$D$17*MIN(1,MAX(0,(25-Pipeline!$E$17+1)/MAX(Pipeline!$F$17,1))) -> 234.9 | AB10: =Pipeline!$Q$17*Pipeline!$D$17*MIN(1,MAX(0,(26-Pipeline!$E$17+1)/MAX(Pipeline!$F$17,1))) -> 234.9 | AC10: =Pipeline!$Q$17*Pipeline!$D$17*MIN(1,MAX(0,(27-Pipeline!$E$17+1)/MAX(Pipeline!$F$17,1))) -> 234.9 | AD10: =Pipeline!$Q$17*Pipeline!$D$17*MIN(1,MAX(0,(28-Pipeline!$E$17+1)/MAX(Pipeline!$F$17,1))) -> 234.9 | AE10: =Pipeline!$Q$17*Pipeline!$D$17*MIN(1,MAX(0,(29-Pipeline!$E$17+1)/MAX(Pipeline!$F$17,1))) -> 234.9 | AF10: =Pipeline!$Q$17*Pipeline!$D$17*MIN(1,MAX(0,(30-Pipeline!$E$17+1)/MAX(Pipeline!$F$17,1))) -> 234.9 | AG10: =Pipeline!$Q$17*Pipeline!$D$17*MIN(1,MAX(0,(31-Pipeline!$E$17+1)/MAX(Pipeline!$F$17,1))) -> 234.9 | AH10: =Pipeline!$Q$17*Pipeline!$D$17*MIN(1,MAX(0,(32-Pipeline!$E$17+1)/MAX(Pipeline!$F$17,1))) -> 234.9 | AI10: =Pipeline!$Q$17*Pipeline!$D$17*MIN(1,MAX(0,(33-Pipeline!$E$17+1)/MAX(Pipeline!$F$17,1))) -> 234.9 | AJ10: =Pipeline!$Q$17*Pipeline!$D$17*MIN(1,MAX(0,(34-Pipeline!$E$17+1)/MAX(Pipeline!$F$17,1))) -> 234.9 | AK10: =Pipeline!$Q$17*Pipeline!$D$17*MIN(1,MAX(0,(35-Pipeline!$E$17+1)/MAX(Pipeline!$F$17,1))) -> 234.9 | AL10: =Pipeline!$Q$17*Pipeline!$D$17*MIN(1,MAX(0,(36-Pipeline!$E$17+1)/MAX(Pipeline!$F$17,1))) -> 234.9 | AM10: =Pipeline!$Q$17*Pipeline!$D$17*MIN(1,MAX(0,(37-Pipeline!$E$17+1)/MAX(Pipeline!$F$17,1))) -> 234.9 | AN10: =Pipeline!$Q$17*Pipeline!$D$17*MIN(1,MAX(0,(38-Pipeline!$E$17+1)/MAX(Pipeline!$F$17,1))) -> 234.9 | AO10: =Pipeline!$Q$17*Pipeline!$D$17*MIN(1,MAX(0,(39-Pipeline!$E$17+1)/MAX(Pipeline!$F$17,1))) -> 234.9 | AP10: =Pipeline!$Q$17*Pipeline!$D$17*MIN(1,MAX(0,(40-Pipeline!$E$17+1)/MAX(Pipeline!$F$17,1))) -> 234.9 | AQ10: =Pipeline!$Q$17*Pipeline!$D$17*MIN(1,MAX(0,(41-Pipeline!$E$17+1)/MAX(Pipeline!$F$17,1))) -> 234.9 | AR10: =Pipeline!$Q$17*Pipeline!$D$17*MIN(1,MAX(0,(42-Pipeline!$E$17+1)/MAX(Pipeline!$F$17,1))) -> 234.9 | AS10: =Pipeline!$Q$17*Pipeline!$D$17*MIN(1,MAX(0,(43-Pipeline!$E$17+1)/MAX(Pipeline!$F$17,1))) -> 234.9 | AT10: =Pipeline!$Q$17*Pipeline!$D$17*MIN(1,MAX(0,(44-Pipeline!$E$17+1)/MAX(Pipeline!$F$17,1))) -> 234.9 | AU10: =Pipeline!$Q$17*Pipeline!$D$17*MIN(1,MAX(0,(45-Pipeline!$E$17+1)/MAX(Pipeline!$F$17,1))) -> 234.9 | AV10: =Pipeline!$Q$17*Pipeline!$D$17*MIN(1,MAX(0,(46-Pipeline!$E$17+1)/MAX(Pipeline!$F$17,1))) -> 234.9 | AW10: =Pipeline!$Q$17*Pipeline!$D$17*MIN(1,MAX(0,(47-Pipeline!$E$17+1)/MAX(Pipeline!$F$17,1))) -> 234.9 | AX10: =Pipeline!$Q$17*Pipeline!$D$17*MIN(1,MAX(0,(48-Pipeline!$E$17+1)/MAX(Pipeline!$F$17,1))) -> 234.9 | AY10: =Pipeline!$Q$17*Pipeline!$D$17*MIN(1,MAX(0,(49-Pipeline!$E$17+1)/MAX(Pipeline!$F$17,1))) -> 234.9 | AZ10: =Pipeline!$Q$17*Pipeline!$D$17*MIN(1,MAX(0,(50-Pipeline!$E$17+1)/MAX(Pipeline!$F$17,1))) -> 234.9 | BA10: =Pipeline!$Q$17*Pipeline!$D$17*MIN(1,MAX(0,(51-Pipeline!$E$17+1)/MAX(Pipeline!$F$17,1))) -> 234.9 | BB10: =Pipeline!$Q$17*Pipeline!$D$17*MIN(1,MAX(0,(52-Pipeline!$E$17+1)/MAX(Pipeline!$F$17,1))) -> 234.9 | BC10: =Pipeline!$Q$17*Pipeline!$D$17*MIN(1,MAX(0,(53-Pipeline!$E$17+1)/MAX(Pipeline!$F$17,1))) -> 234.9 | BD10: =Pipeline!$Q$17*Pipeline!$D$17*MIN(1,MAX(0,(54-Pipeline!$E$17+1)/MAX(Pipeline!$F$17,1))) -> 234.9 | BE10: =Pipeline!$Q$17*Pipeline!$D$17*MIN(1,MAX(0,(55-Pipeline!$E$17+1)/MAX(Pipeline!$F$17,1))) -> 234.9 | BF10: =Pipeline!$Q$17*Pipeline!$D$17*MIN(1,MAX(0,(56-Pipeline!$E$17+1)/MAX(Pipeline!$F$17,1))) -> 234.9 | BG10: =Pipeline!$Q$17*Pipeline!$D$17*MIN(1,MAX(0,(57-Pipeline!$E$17+1)/MAX(Pipeline!$F$17,1))) -> 234.9 | BH10: =Pipeline!$Q$17*Pipeline!$D$17*MIN(1,MAX(0,(58-Pipeline!$E$17+1)/MAX(Pipeline!$F$17,1))) -> 234.9 | BI10: =Pipeline!$Q$17*Pipeline!$D$17*MIN(1,MAX(0,(59-Pipeline!$E$17+1)/MAX(Pipeline!$F$17,1))) -> 234.9 | BJ10: =Pipeline!$Q$17*Pipeline!$D$17*MIN(1,MAX(0,(60-Pipeline!$E$17+1)/MAX(Pipeline!$F$17,1))) -> 234.9 | BK10: =Pipeline!$Q$17*Pipeline!$D$17*MIN(1,MAX(0,(61-Pipeline!$E$17+1)/MAX(Pipeline!$F$17,1))) -> 234.9 | BL10: =Pipeline!$Q$17*Pipeline!$D$17*MIN(1,MAX(0,(62-Pipeline!$E$17+1)/MAX(Pipeline!$F$17,1))) -> 234.9 | BM10: =Pipeline!$Q$17*Pipeline!$D$17*MIN(1,MAX(0,(63-Pipeline!$E$17+1)/MAX(Pipeline!$F$17,1))) -> 234.9 | BN10: =Pipeline!$Q$17*Pipeline!$D$17*MIN(1,MAX(0,(64-Pipeline!$E$17+1)/MAX(Pipeline!$F$17,1))) -> 234.9 | BO10: =Pipeline!$Q$17*Pipeline!$D$17*MIN(1,MAX(0,(65-Pipeline!$E$17+1)/MAX(Pipeline!$F$17,1))) -> 234.9 | BP10: =Pipeline!$Q$17*Pipeline!$D$17*MIN(1,MAX(0,(66-Pipeline!$E$17+1)/MAX(Pipeline!$F$17,1))) -> 234.9 | BQ10: =Pipeline!$Q$17*Pipeline!$D$17*MIN(1,MAX(0,(67-Pipeline!$E$17+1)/MAX(Pipeline!$F$17,1))) -> 234.9 | BR10: =Pipeline!$Q$17*Pipeline!$D$17*MIN(1,MAX(0,(68-Pipeline!$E$17+1)/MAX(Pipeline!$F$17,1))) -> 234.9 | BS10: =Pipeline!$Q$17*Pipeline!$D$17*MIN(1,MAX(0,(69-Pipeline!$E$17+1)/MAX(Pipeline!$F$17,1))) -> 234.9 | BT10: =Pipeline!$Q$17*Pipeline!$D$17*MIN(1,MAX(0,(70-Pipeline!$E$17+1)/MAX(Pipeline!$F$17,1))) -> 234.9 | BU10: =Pipeline!$Q$17*Pipeline!$D$17*MIN(1,MAX(0,(71-Pipeline!$E$17+1)/MAX(Pipeline!$F$17,1))) -> 234.9 | BV10: =Pipeline!$Q$17*Pipeline!$D$17*MIN(1,MAX(0,(72-Pipeline!$E$17+1)/MAX(Pipeline!$F$17,1))) -> 234.9 | BW10: =Pipeline!$Q$17*Pipeline!$D$17*MIN(1,MAX(0,(73-Pipeline!$E$17+1)/MAX(Pipeline!$F$17,1))) -> 234.9 | BX10: =Pipeline!$Q$17*Pipeline!$D$17*MIN(1,MAX(0,(74-Pipeline!$E$17+1)/MAX(Pipeline!$F$17,1))) -> 234.9 | BY10: =Pipeline!$Q$17*Pipeline!$D$17*MIN(1,MAX(0,(75-Pipeline!$E$17+1)/MAX(Pipeline!$F$17,1))) -> 234.9 | BZ10: =Pipeline!$Q$17*Pipeline!$D$17*MIN(1,MAX(0,(76-Pipeline!$E$17+1)/MAX(Pipeline!$F$17,1))) -> 234.9 | CA10: =Pipeline!$Q$17*Pipeline!$D$17*MIN(1,MAX(0,(77-Pipeline!$E$17+1)/MAX(Pipeline!$F$17,1))) -> 234.9 | CB10: =Pipeline!$Q$17*Pipeline!$D$17*MIN(1,MAX(0,(78-Pipeline!$E$17+1)/MAX(Pipeline!$F$17,1))) -> 234.9 | CC10: =Pipeline!$Q$17*Pipeline!$D$17*MIN(1,MAX(0,(79-Pipeline!$E$17+1)/MAX(Pipeline!$F$17,1))) -> 234.9 | CD10: =Pipeline!$Q$17*Pipeline!$D$17*MIN(1,MAX(0,(80-Pipeline!$E$17+1)/MAX(Pipeline!$F$17,1))) -> 234.9 | CE10: =Pipeline!$Q$17*Pipeline!$D$17*MIN(1,MAX(0,(81-Pipeline!$E$17+1)/MAX(Pipeline!$F$17,1))) -> 234.9 | CF10: =Pipeline!$Q$17*Pipeline!$D$17*MIN(1,MAX(0,(82-Pipeline!$E$17+1)/MAX(Pipeline!$F$17,1))) -> 234.9 | CG10: =Pipeline!$Q$17*Pipeline!$D$17*MIN(1,MAX(0,(83-Pipeline!$E$17+1)/MAX(Pipeline!$F$17,1))) -> 234.9 | CH10: =Pipeline!$Q$17*Pipeline!$D$17*MIN(1,MAX(0,(84-Pipeline!$E$17+1)/MAX(Pipeline!$F$17,1))) -> 234.9
A11: · Frutas Eloy (€/mes pond.) | C11: =Pipeline!$Q$18*Pipeline!$D$18*MIN(1,MAX(0,(1-Pipeline!$E$18+1)/MAX(Pipeline!$F$18,1))) -> 0 | D11: =Pipeline!$Q$18*Pipeline!$D$18*MIN(1,MAX(0,(2-Pipeline!$E$18+1)/MAX(Pipeline!$F$18,1))) -> 0 | E11: =Pipeline!$Q$18*Pipeline!$D$18*MIN(1,MAX(0,(3-Pipeline!$E$18+1)/MAX(Pipeline!$F$18,1))) -> 1201.6875 | F11: =Pipeline!$Q$18*Pipeline!$D$18*MIN(1,MAX(0,(4-Pipeline!$E$18+1)/MAX(Pipeline!$F$18,1))) -> 2403.375 | G11: =Pipeline!$Q$18*Pipeline!$D$18*MIN(1,MAX(0,(5-Pipeline!$E$18+1)/MAX(Pipeline!$F$18,1))) -> 3605.0625 | H11: =Pipeline!$Q$18*Pipeline!$D$18*MIN(1,MAX(0,(6-Pipeline!$E$18+1)/MAX(Pipeline!$F$18,1))) -> 4806.75 | I11: =Pipeline!$Q$18*Pipeline!$D$18*MIN(1,MAX(0,(7-Pipeline!$E$18+1)/MAX(Pipeline!$F$18,1))) -> 6008.4375 | J11: =Pipeline!$Q$18*Pipeline!$D$18*MIN(1,MAX(0,(8-Pipeline!$E$18+1)/MAX(Pipeline!$F$18,1))) -> 7210.125 | K11: =Pipeline!$Q$18*Pipeline!$D$18*MIN(1,MAX(0,(9-Pipeline!$E$18+1)/MAX(Pipeline!$F$18,1))) -> 8411.8125 | L11: =Pipeline!$Q$18*Pipeline!$D$18*MIN(1,MAX(0,(10-Pipeline!$E$18+1)/MAX(Pipeline!$F$18,1))) -> 9613.5 | M11: =Pipeline!$Q$18*Pipeline!$D$18*MIN(1,MAX(0,(11-Pipeline!$E$18+1)/MAX(Pipeline!$F$18,1))) -> 9613.5 | N11: =Pipeline!$Q$18*Pipeline!$D$18*MIN(1,MAX(0,(12-Pipeline!$E$18+1)/MAX(Pipeline!$F$18,1))) -> 9613.5 | O11: =Pipeline!$Q$18*Pipeline!$D$18*MIN(1,MAX(0,(13-Pipeline!$E$18+1)/MAX(Pipeline!$F$18,1))) -> 9613.5 | P11: =Pipeline!$Q$18*Pipeline!$D$18*MIN(1,MAX(0,(14-Pipeline!$E$18+1)/MAX(Pipeline!$F$18,1))) -> 9613.5 | Q11: =Pipeline!$Q$18*Pipeline!$D$18*MIN(1,MAX(0,(15-Pipeline!$E$18+1)/MAX(Pipeline!$F$18,1))) -> 9613.5 | R11: =Pipeline!$Q$18*Pipeline!$D$18*MIN(1,MAX(0,(16-Pipeline!$E$18+1)/MAX(Pipeline!$F$18,1))) -> 9613.5 | S11: =Pipeline!$Q$18*Pipeline!$D$18*MIN(1,MAX(0,(17-Pipeline!$E$18+1)/MAX(Pipeline!$F$18,1))) -> 9613.5 | T11: =Pipeline!$Q$18*Pipeline!$D$18*MIN(1,MAX(0,(18-Pipeline!$E$18+1)/MAX(Pipeline!$F$18,1))) -> 9613.5 | U11: =Pipeline!$Q$18*Pipeline!$D$18*MIN(1,MAX(0,(19-Pipeline!$E$18+1)/MAX(Pipeline!$F$18,1))) -> 9613.5 | V11: =Pipeline!$Q$18*Pipeline!$D$18*MIN(1,MAX(0,(20-Pipeline!$E$18+1)/MAX(Pipeline!$F$18,1))) -> 9613.5 | W11: =Pipeline!$Q$18*Pipeline!$D$18*MIN(1,MAX(0,(21-Pipeline!$E$18+1)/MAX(Pipeline!$F$18,1))) -> 9613.5 | X11: =Pipeline!$Q$18*Pipeline!$D$18*MIN(1,MAX(0,(22-Pipeline!$E$18+1)/MAX(Pipeline!$F$18,1))) -> 9613.5 | Y11: =Pipeline!$Q$18*Pipeline!$D$18*MIN(1,MAX(0,(23-Pipeline!$E$18+1)/MAX(Pipeline!$F$18,1))) -> 9613.5 | Z11: =Pipeline!$Q$18*Pipeline!$D$18*MIN(1,MAX(0,(24-Pipeline!$E$18+1)/MAX(Pipeline!$F$18,1))) -> 9613.5 | AA11: =Pipeline!$Q$18*Pipeline!$D$18*MIN(1,MAX(0,(25-Pipeline!$E$18+1)/MAX(Pipeline!$F$18,1))) -> 9613.5 | AB11: =Pipeline!$Q$18*Pipeline!$D$18*MIN(1,MAX(0,(26-Pipeline!$E$18+1)/MAX(Pipeline!$F$18,1))) -> 9613.5 | AC11: =Pipeline!$Q$18*Pipeline!$D$18*MIN(1,MAX(0,(27-Pipeline!$E$18+1)/MAX(Pipeline!$F$18,1))) -> 9613.5 | AD11: =Pipeline!$Q$18*Pipeline!$D$18*MIN(1,MAX(0,(28-Pipeline!$E$18+1)/MAX(Pipeline!$F$18,1))) -> 9613.5 | AE11: =Pipeline!$Q$18*Pipeline!$D$18*MIN(1,MAX(0,(29-Pipeline!$E$18+1)/MAX(Pipeline!$F$18,1))) -> 9613.5 | AF11: =Pipeline!$Q$18*Pipeline!$D$18*MIN(1,MAX(0,(30-Pipeline!$E$18+1)/MAX(Pipeline!$F$18,1))) -> 9613.5 | AG11: =Pipeline!$Q$18*Pipeline!$D$18*MIN(1,MAX(0,(31-Pipeline!$E$18+1)/MAX(Pipeline!$F$18,1))) -> 9613.5 | AH11: =Pipeline!$Q$18*Pipeline!$D$18*MIN(1,MAX(0,(32-Pipeline!$E$18+1)/MAX(Pipeline!$F$18,1))) -> 9613.5 | AI11: =Pipeline!$Q$18*Pipeline!$D$18*MIN(1,MAX(0,(33-Pipeline!$E$18+1)/MAX(Pipeline!$F$18,1))) -> 9613.5 | AJ11: =Pipeline!$Q$18*Pipeline!$D$18*MIN(1,MAX(0,(34-Pipeline!$E$18+1)/MAX(Pipeline!$F$18,1))) -> 9613.5 | AK11: =Pipeline!$Q$18*Pipeline!$D$18*MIN(1,MAX(0,(35-Pipeline!$E$18+1)/MAX(Pipeline!$F$18,1))) -> 9613.5 | AL11: =Pipeline!$Q$18*Pipeline!$D$18*MIN(1,MAX(0,(36-Pipeline!$E$18+1)/MAX(Pipeline!$F$18,1))) -> 9613.5 | AM11: =Pipeline!$Q$18*Pipeline!$D$18*MIN(1,MAX(0,(37-Pipeline!$E$18+1)/MAX(Pipeline!$F$18,1))) -> 9613.5 | AN11: =Pipeline!$Q$18*Pipeline!$D$18*MIN(1,MAX(0,(38-Pipeline!$E$18+1)/MAX(Pipeline!$F$18,1))) -> 9613.5 | AO11: =Pipeline!$Q$18*Pipeline!$D$18*MIN(1,MAX(0,(39-Pipeline!$E$18+1)/MAX(Pipeline!$F$18,1))) -> 9613.5 | AP11: =Pipeline!$Q$18*Pipeline!$D$18*MIN(1,MAX(0,(40-Pipeline!$E$18+1)/MAX(Pipeline!$F$18,1))) -> 9613.5 | AQ11: =Pipeline!$Q$18*Pipeline!$D$18*MIN(1,MAX(0,(41-Pipeline!$E$18+1)/MAX(Pipeline!$F$18,1))) -> 9613.5 | AR11: =Pipeline!$Q$18*Pipeline!$D$18*MIN(1,MAX(0,(42-Pipeline!$E$18+1)/MAX(Pipeline!$F$18,1))) -> 9613.5 | AS11: =Pipeline!$Q$18*Pipeline!$D$18*MIN(1,MAX(0,(43-Pipeline!$E$18+1)/MAX(Pipeline!$F$18,1))) -> 9613.5 | AT11: =Pipeline!$Q$18*Pipeline!$D$18*MIN(1,MAX(0,(44-Pipeline!$E$18+1)/MAX(Pipeline!$F$18,1))) -> 9613.5 | AU11: =Pipeline!$Q$18*Pipeline!$D$18*MIN(1,MAX(0,(45-Pipeline!$E$18+1)/MAX(Pipeline!$F$18,1))) -> 9613.5 | AV11: =Pipeline!$Q$18*Pipeline!$D$18*MIN(1,MAX(0,(46-Pipeline!$E$18+1)/MAX(Pipeline!$F$18,1))) -> 9613.5 | AW11: =Pipeline!$Q$18*Pipeline!$D$18*MIN(1,MAX(0,(47-Pipeline!$E$18+1)/MAX(Pipeline!$F$18,1))) -> 9613.5 | AX11: =Pipeline!$Q$18*Pipeline!$D$18*MIN(1,MAX(0,(48-Pipeline!$E$18+1)/MAX(Pipeline!$F$18,1))) -> 9613.5 | AY11: =Pipeline!$Q$18*Pipeline!$D$18*MIN(1,MAX(0,(49-Pipeline!$E$18+1)/MAX(Pipeline!$F$18,1))) -> 9613.5 | AZ11: =Pipeline!$Q$18*Pipeline!$D$18*MIN(1,MAX(0,(50-Pipeline!$E$18+1)/MAX(Pipeline!$F$18,1))) -> 9613.5 | BA11: =Pipeline!$Q$18*Pipeline!$D$18*MIN(1,MAX(0,(51-Pipeline!$E$18+1)/MAX(Pipeline!$F$18,1))) -> 9613.5 | BB11: =Pipeline!$Q$18*Pipeline!$D$18*MIN(1,MAX(0,(52-Pipeline!$E$18+1)/MAX(Pipeline!$F$18,1))) -> 9613.5 | BC11: =Pipeline!$Q$18*Pipeline!$D$18*MIN(1,MAX(0,(53-Pipeline!$E$18+1)/MAX(Pipeline!$F$18,1))) -> 9613.5 | BD11: =Pipeline!$Q$18*Pipeline!$D$18*MIN(1,MAX(0,(54-Pipeline!$E$18+1)/MAX(Pipeline!$F$18,1))) -> 9613.5 | BE11: =Pipeline!$Q$18*Pipeline!$D$18*MIN(1,MAX(0,(55-Pipeline!$E$18+1)/MAX(Pipeline!$F$18,1))) -> 9613.5 | BF11: =Pipeline!$Q$18*Pipeline!$D$18*MIN(1,MAX(0,(56-Pipeline!$E$18+1)/MAX(Pipeline!$F$18,1))) -> 9613.5 | BG11: =Pipeline!$Q$18*Pipeline!$D$18*MIN(1,MAX(0,(57-Pipeline!$E$18+1)/MAX(Pipeline!$F$18,1))) -> 9613.5 | BH11: =Pipeline!$Q$18*Pipeline!$D$18*MIN(1,MAX(0,(58-Pipeline!$E$18+1)/MAX(Pipeline!$F$18,1))) -> 9613.5 | BI11: =Pipeline!$Q$18*Pipeline!$D$18*MIN(1,MAX(0,(59-Pipeline!$E$18+1)/MAX(Pipeline!$F$18,1))) -> 9613.5 | BJ11: =Pipeline!$Q$18*Pipeline!$D$18*MIN(1,MAX(0,(60-Pipeline!$E$18+1)/MAX(Pipeline!$F$18,1))) -> 9613.5 | BK11: =Pipeline!$Q$18*Pipeline!$D$18*MIN(1,MAX(0,(61-Pipeline!$E$18+1)/MAX(Pipeline!$F$18,1))) -> 9613.5 | BL11: =Pipeline!$Q$18*Pipeline!$D$18*MIN(1,MAX(0,(62-Pipeline!$E$18+1)/MAX(Pipeline!$F$18,1))) -> 9613.5 | BM11: =Pipeline!$Q$18*Pipeline!$D$18*MIN(1,MAX(0,(63-Pipeline!$E$18+1)/MAX(Pipeline!$F$18,1))) -> 9613.5 | BN11: =Pipeline!$Q$18*Pipeline!$D$18*MIN(1,MAX(0,(64-Pipeline!$E$18+1)/MAX(Pipeline!$F$18,1))) -> 9613.5 | BO11: =Pipeline!$Q$18*Pipeline!$D$18*MIN(1,MAX(0,(65-Pipeline!$E$18+1)/MAX(Pipeline!$F$18,1))) -> 9613.5 | BP11: =Pipeline!$Q$18*Pipeline!$D$18*MIN(1,MAX(0,(66-Pipeline!$E$18+1)/MAX(Pipeline!$F$18,1))) -> 9613.5 | BQ11: =Pipeline!$Q$18*Pipeline!$D$18*MIN(1,MAX(0,(67-Pipeline!$E$18+1)/MAX(Pipeline!$F$18,1))) -> 9613.5 | BR11: =Pipeline!$Q$18*Pipeline!$D$18*MIN(1,MAX(0,(68-Pipeline!$E$18+1)/MAX(Pipeline!$F$18,1))) -> 9613.5 | BS11: =Pipeline!$Q$18*Pipeline!$D$18*MIN(1,MAX(0,(69-Pipeline!$E$18+1)/MAX(Pipeline!$F$18,1))) -> 9613.5 | BT11: =Pipeline!$Q$18*Pipeline!$D$18*MIN(1,MAX(0,(70-Pipeline!$E$18+1)/MAX(Pipeline!$F$18,1))) -> 9613.5 | BU11: =Pipeline!$Q$18*Pipeline!$D$18*MIN(1,MAX(0,(71-Pipeline!$E$18+1)/MAX(Pipeline!$F$18,1))) -> 9613.5 | BV11: =Pipeline!$Q$18*Pipeline!$D$18*MIN(1,MAX(0,(72-Pipeline!$E$18+1)/MAX(Pipeline!$F$18,1))) -> 9613.5 | BW11: =Pipeline!$Q$18*Pipeline!$D$18*MIN(1,MAX(0,(73-Pipeline!$E$18+1)/MAX(Pipeline!$F$18,1))) -> 9613.5 | BX11: =Pipeline!$Q$18*Pipeline!$D$18*MIN(1,MAX(0,(74-Pipeline!$E$18+1)/MAX(Pipeline!$F$18,1))) -> 9613.5 | BY11: =Pipeline!$Q$18*Pipeline!$D$18*MIN(1,MAX(0,(75-Pipeline!$E$18+1)/MAX(Pipeline!$F$18,1))) -> 9613.5 | BZ11: =Pipeline!$Q$18*Pipeline!$D$18*MIN(1,MAX(0,(76-Pipeline!$E$18+1)/MAX(Pipeline!$F$18,1))) -> 9613.5 | CA11: =Pipeline!$Q$18*Pipeline!$D$18*MIN(1,MAX(0,(77-Pipeline!$E$18+1)/MAX(Pipeline!$F$18,1))) -> 9613.5 | CB11: =Pipeline!$Q$18*Pipeline!$D$18*MIN(1,MAX(0,(78-Pipeline!$E$18+1)/MAX(Pipeline!$F$18,1))) -> 9613.5 | CC11: =Pipeline!$Q$18*Pipeline!$D$18*MIN(1,MAX(0,(79-Pipeline!$E$18+1)/MAX(Pipeline!$F$18,1))) -> 9613.5 | CD11: =Pipeline!$Q$18*Pipeline!$D$18*MIN(1,MAX(0,(80-Pipeline!$E$18+1)/MAX(Pipeline!$F$18,1))) -> 9613.5 | CE11: =Pipeline!$Q$18*Pipeline!$D$18*MIN(1,MAX(0,(81-Pipeline!$E$18+1)/MAX(Pipeline!$F$18,1))) -> 9613.5 | CF11: =Pipeline!$Q$18*Pipeline!$D$18*MIN(1,MAX(0,(82-Pipeline!$E$18+1)/MAX(Pipeline!$F$18,1))) -> 9613.5 | CG11: =Pipeline!$Q$18*Pipeline!$D$18*MIN(1,MAX(0,(83-Pipeline!$E$18+1)/MAX(Pipeline!$F$18,1))) -> 9613.5 | CH11: =Pipeline!$Q$18*Pipeline!$D$18*MIN(1,MAX(0,(84-Pipeline!$E$18+1)/MAX(Pipeline!$F$18,1))) -> 9613.5
A12: · Mercamadrid (asentadores) (€/mes pond.) | C12: =Pipeline!$Q$19*Pipeline!$D$19*MIN(1,MAX(0,(1-Pipeline!$E$19+1)/MAX(Pipeline!$F$19,1))) -> 0 | D12: =Pipeline!$Q$19*Pipeline!$D$19*MIN(1,MAX(0,(2-Pipeline!$E$19+1)/MAX(Pipeline!$F$19,1))) -> 0 | E12: =Pipeline!$Q$19*Pipeline!$D$19*MIN(1,MAX(0,(3-Pipeline!$E$19+1)/MAX(Pipeline!$F$19,1))) -> 0 | F12: =Pipeline!$Q$19*Pipeline!$D$19*MIN(1,MAX(0,(4-Pipeline!$E$19+1)/MAX(Pipeline!$F$19,1))) -> 0 | G12: =Pipeline!$Q$19*Pipeline!$D$19*MIN(1,MAX(0,(5-Pipeline!$E$19+1)/MAX(Pipeline!$F$19,1))) -> 0 | H12: =Pipeline!$Q$19*Pipeline!$D$19*MIN(1,MAX(0,(6-Pipeline!$E$19+1)/MAX(Pipeline!$F$19,1))) -> 717.75 | I12: =Pipeline!$Q$19*Pipeline!$D$19*MIN(1,MAX(0,(7-Pipeline!$E$19+1)/MAX(Pipeline!$F$19,1))) -> 1435.5 | J12: =Pipeline!$Q$19*Pipeline!$D$19*MIN(1,MAX(0,(8-Pipeline!$E$19+1)/MAX(Pipeline!$F$19,1))) -> 2153.25 | K12: =Pipeline!$Q$19*Pipeline!$D$19*MIN(1,MAX(0,(9-Pipeline!$E$19+1)/MAX(Pipeline!$F$19,1))) -> 2871 | L12: =Pipeline!$Q$19*Pipeline!$D$19*MIN(1,MAX(0,(10-Pipeline!$E$19+1)/MAX(Pipeline!$F$19,1))) -> 3588.75 | M12: =Pipeline!$Q$19*Pipeline!$D$19*MIN(1,MAX(0,(11-Pipeline!$E$19+1)/MAX(Pipeline!$F$19,1))) -> 4306.5 | N12: =Pipeline!$Q$19*Pipeline!$D$19*MIN(1,MAX(0,(12-Pipeline!$E$19+1)/MAX(Pipeline!$F$19,1))) -> 5024.25 | O12: =Pipeline!$Q$19*Pipeline!$D$19*MIN(1,MAX(0,(13-Pipeline!$E$19+1)/MAX(Pipeline!$F$19,1))) -> 5742 | P12: =Pipeline!$Q$19*Pipeline!$D$19*MIN(1,MAX(0,(14-Pipeline!$E$19+1)/MAX(Pipeline!$F$19,1))) -> 5742 | Q12: =Pipeline!$Q$19*Pipeline!$D$19*MIN(1,MAX(0,(15-Pipeline!$E$19+1)/MAX(Pipeline!$F$19,1))) -> 5742 | R12: =Pipeline!$Q$19*Pipeline!$D$19*MIN(1,MAX(0,(16-Pipeline!$E$19+1)/MAX(Pipeline!$F$19,1))) -> 5742 | S12: =Pipeline!$Q$19*Pipeline!$D$19*MIN(1,MAX(0,(17-Pipeline!$E$19+1)/MAX(Pipeline!$F$19,1))) -> 5742 | T12: =Pipeline!$Q$19*Pipeline!$D$19*MIN(1,MAX(0,(18-Pipeline!$E$19+1)/MAX(Pipeline!$F$19,1))) -> 5742 | U12: =Pipeline!$Q$19*Pipeline!$D$19*MIN(1,MAX(0,(19-Pipeline!$E$19+1)/MAX(Pipeline!$F$19,1))) -> 5742 | V12: =Pipeline!$Q$19*Pipeline!$D$19*MIN(1,MAX(0,(20-Pipeline!$E$19+1)/MAX(Pipeline!$F$19,1))) -> 5742 | W12: =Pipeline!$Q$19*Pipeline!$D$19*MIN(1,MAX(0,(21-Pipeline!$E$19+1)/MAX(Pipeline!$F$19,1))) -> 5742 | X12: =Pipeline!$Q$19*Pipeline!$D$19*MIN(1,MAX(0,(22-Pipeline!$E$19+1)/MAX(Pipeline!$F$19,1))) -> 5742 | Y12: =Pipeline!$Q$19*Pipeline!$D$19*MIN(1,MAX(0,(23-Pipeline!$E$19+1)/MAX(Pipeline!$F$19,1))) -> 5742 | Z12: =Pipeline!$Q$19*Pipeline!$D$19*MIN(1,MAX(0,(24-Pipeline!$E$19+1)/MAX(Pipeline!$F$19,1))) -> 5742 | AA12: =Pipeline!$Q$19*Pipeline!$D$19*MIN(1,MAX(0,(25-Pipeline!$E$19+1)/MAX(Pipeline!$F$19,1))) -> 5742 | AB12: =Pipeline!$Q$19*Pipeline!$D$19*MIN(1,MAX(0,(26-Pipeline!$E$19+1)/MAX(Pipeline!$F$19,1))) -> 5742 | AC12: =Pipeline!$Q$19*Pipeline!$D$19*MIN(1,MAX(0,(27-Pipeline!$E$19+1)/MAX(Pipeline!$F$19,1))) -> 5742 | AD12: =Pipeline!$Q$19*Pipeline!$D$19*MIN(1,MAX(0,(28-Pipeline!$E$19+1)/MAX(Pipeline!$F$19,1))) -> 5742 | AE12: =Pipeline!$Q$19*Pipeline!$D$19*MIN(1,MAX(0,(29-Pipeline!$E$19+1)/MAX(Pipeline!$F$19,1))) -> 5742 | AF12: =Pipeline!$Q$19*Pipeline!$D$19*MIN(1,MAX(0,(30-Pipeline!$E$19+1)/MAX(Pipeline!$F$19,1))) -> 5742 | AG12: =Pipeline!$Q$19*Pipeline!$D$19*MIN(1,MAX(0,(31-Pipeline!$E$19+1)/MAX(Pipeline!$F$19,1))) -> 5742 | AH12: =Pipeline!$Q$19*Pipeline!$D$19*MIN(1,MAX(0,(32-Pipeline!$E$19+1)/MAX(Pipeline!$F$19,1))) -> 5742 | AI12: =Pipeline!$Q$19*Pipeline!$D$19*MIN(1,MAX(0,(33-Pipeline!$E$19+1)/MAX(Pipeline!$F$19,1))) -> 5742 | AJ12: =Pipeline!$Q$19*Pipeline!$D$19*MIN(1,MAX(0,(34-Pipeline!$E$19+1)/MAX(Pipeline!$F$19,1))) -> 5742 | AK12: =Pipeline!$Q$19*Pipeline!$D$19*MIN(1,MAX(0,(35-Pipeline!$E$19+1)/MAX(Pipeline!$F$19,1))) -> 5742 | AL12: =Pipeline!$Q$19*Pipeline!$D$19*MIN(1,MAX(0,(36-Pipeline!$E$19+1)/MAX(Pipeline!$F$19,1))) -> 5742 | AM12: =Pipeline!$Q$19*Pipeline!$D$19*MIN(1,MAX(0,(37-Pipeline!$E$19+1)/MAX(Pipeline!$F$19,1))) -> 5742 | AN12: =Pipeline!$Q$19*Pipeline!$D$19*MIN(1,MAX(0,(38-Pipeline!$E$19+1)/MAX(Pipeline!$F$19,1))) -> 5742 | AO12: =Pipeline!$Q$19*Pipeline!$D$19*MIN(1,MAX(0,(39-Pipeline!$E$19+1)/MAX(Pipeline!$F$19,1))) -> 5742 | AP12: =Pipeline!$Q$19*Pipeline!$D$19*MIN(1,MAX(0,(40-Pipeline!$E$19+1)/MAX(Pipeline!$F$19,1))) -> 5742 | AQ12: =Pipeline!$Q$19*Pipeline!$D$19*MIN(1,MAX(0,(41-Pipeline!$E$19+1)/MAX(Pipeline!$F$19,1))) -> 5742 | AR12: =Pipeline!$Q$19*Pipeline!$D$19*MIN(1,MAX(0,(42-Pipeline!$E$19+1)/MAX(Pipeline!$F$19,1))) -> 5742 | AS12: =Pipeline!$Q$19*Pipeline!$D$19*MIN(1,MAX(0,(43-Pipeline!$E$19+1)/MAX(Pipeline!$F$19,1))) -> 5742 | AT12: =Pipeline!$Q$19*Pipeline!$D$19*MIN(1,MAX(0,(44-Pipeline!$E$19+1)/MAX(Pipeline!$F$19,1))) -> 5742 | AU12: =Pipeline!$Q$19*Pipeline!$D$19*MIN(1,MAX(0,(45-Pipeline!$E$19+1)/MAX(Pipeline!$F$19,1))) -> 5742 | AV12: =Pipeline!$Q$19*Pipeline!$D$19*MIN(1,MAX(0,(46-Pipeline!$E$19+1)/MAX(Pipeline!$F$19,1))) -> 5742 | AW12: =Pipeline!$Q$19*Pipeline!$D$19*MIN(1,MAX(0,(47-Pipeline!$E$19+1)/MAX(Pipeline!$F$19,1))) -> 5742 | AX12: =Pipeline!$Q$19*Pipeline!$D$19*MIN(1,MAX(0,(48-Pipeline!$E$19+1)/MAX(Pipeline!$F$19,1))) -> 5742 | AY12: =Pipeline!$Q$19*Pipeline!$D$19*MIN(1,MAX(0,(49-Pipeline!$E$19+1)/MAX(Pipeline!$F$19,1))) -> 5742 | AZ12: =Pipeline!$Q$19*Pipeline!$D$19*MIN(1,MAX(0,(50-Pipeline!$E$19+1)/MAX(Pipeline!$F$19,1))) -> 5742 | BA12: =Pipeline!$Q$19*Pipeline!$D$19*MIN(1,MAX(0,(51-Pipeline!$E$19+1)/MAX(Pipeline!$F$19,1))) -> 5742 | BB12: =Pipeline!$Q$19*Pipeline!$D$19*MIN(1,MAX(0,(52-Pipeline!$E$19+1)/MAX(Pipeline!$F$19,1))) -> 5742 | BC12: =Pipeline!$Q$19*Pipeline!$D$19*MIN(1,MAX(0,(53-Pipeline!$E$19+1)/MAX(Pipeline!$F$19,1))) -> 5742 | BD12: =Pipeline!$Q$19*Pipeline!$D$19*MIN(1,MAX(0,(54-Pipeline!$E$19+1)/MAX(Pipeline!$F$19,1))) -> 5742 | BE12: =Pipeline!$Q$19*Pipeline!$D$19*MIN(1,MAX(0,(55-Pipeline!$E$19+1)/MAX(Pipeline!$F$19,1))) -> 5742 | BF12: =Pipeline!$Q$19*Pipeline!$D$19*MIN(1,MAX(0,(56-Pipeline!$E$19+1)/MAX(Pipeline!$F$19,1))) -> 5742 | BG12: =Pipeline!$Q$19*Pipeline!$D$19*MIN(1,MAX(0,(57-Pipeline!$E$19+1)/MAX(Pipeline!$F$19,1))) -> 5742 | BH12: =Pipeline!$Q$19*Pipeline!$D$19*MIN(1,MAX(0,(58-Pipeline!$E$19+1)/MAX(Pipeline!$F$19,1))) -> 5742 | BI12: =Pipeline!$Q$19*Pipeline!$D$19*MIN(1,MAX(0,(59-Pipeline!$E$19+1)/MAX(Pipeline!$F$19,1))) -> 5742 | BJ12: =Pipeline!$Q$19*Pipeline!$D$19*MIN(1,MAX(0,(60-Pipeline!$E$19+1)/MAX(Pipeline!$F$19,1))) -> 5742 | BK12: =Pipeline!$Q$19*Pipeline!$D$19*MIN(1,MAX(0,(61-Pipeline!$E$19+1)/MAX(Pipeline!$F$19,1))) -> 5742 | BL12: =Pipeline!$Q$19*Pipeline!$D$19*MIN(1,MAX(0,(62-Pipeline!$E$19+1)/MAX(Pipeline!$F$19,1))) -> 5742 | BM12: =Pipeline!$Q$19*Pipeline!$D$19*MIN(1,MAX(0,(63-Pipeline!$E$19+1)/MAX(Pipeline!$F$19,1))) -> 5742 | BN12: =Pipeline!$Q$19*Pipeline!$D$19*MIN(1,MAX(0,(64-Pipeline!$E$19+1)/MAX(Pipeline!$F$19,1))) -> 5742 | BO12: =Pipeline!$Q$19*Pipeline!$D$19*MIN(1,MAX(0,(65-Pipeline!$E$19+1)/MAX(Pipeline!$F$19,1))) -> 5742 | BP12: =Pipeline!$Q$19*Pipeline!$D$19*MIN(1,MAX(0,(66-Pipeline!$E$19+1)/MAX(Pipeline!$F$19,1))) -> 5742 | BQ12: =Pipeline!$Q$19*Pipeline!$D$19*MIN(1,MAX(0,(67-Pipeline!$E$19+1)/MAX(Pipeline!$F$19,1))) -> 5742 | BR12: =Pipeline!$Q$19*Pipeline!$D$19*MIN(1,MAX(0,(68-Pipeline!$E$19+1)/MAX(Pipeline!$F$19,1))) -> 5742 | BS12: =Pipeline!$Q$19*Pipeline!$D$19*MIN(1,MAX(0,(69-Pipeline!$E$19+1)/MAX(Pipeline!$F$19,1))) -> 5742 | BT12: =Pipeline!$Q$19*Pipeline!$D$19*MIN(1,MAX(0,(70-Pipeline!$E$19+1)/MAX(Pipeline!$F$19,1))) -> 5742 | BU12: =Pipeline!$Q$19*Pipeline!$D$19*MIN(1,MAX(0,(71-Pipeline!$E$19+1)/MAX(Pipeline!$F$19,1))) -> 5742 | BV12: =Pipeline!$Q$19*Pipeline!$D$19*MIN(1,MAX(0,(72-Pipeline!$E$19+1)/MAX(Pipeline!$F$19,1))) -> 5742 | BW12: =Pipeline!$Q$19*Pipeline!$D$19*MIN(1,MAX(0,(73-Pipeline!$E$19+1)/MAX(Pipeline!$F$19,1))) -> 5742 | BX12: =Pipeline!$Q$19*Pipeline!$D$19*MIN(1,MAX(0,(74-Pipeline!$E$19+1)/MAX(Pipeline!$F$19,1))) -> 5742 | BY12: =Pipeline!$Q$19*Pipeline!$D$19*MIN(1,MAX(0,(75-Pipeline!$E$19+1)/MAX(Pipeline!$F$19,1))) -> 5742 | BZ12: =Pipeline!$Q$19*Pipeline!$D$19*MIN(1,MAX(0,(76-Pipeline!$E$19+1)/MAX(Pipeline!$F$19,1))) -> 5742 | CA12: =Pipeline!$Q$19*Pipeline!$D$19*MIN(1,MAX(0,(77-Pipeline!$E$19+1)/MAX(Pipeline!$F$19,1))) -> 5742 | CB12: =Pipeline!$Q$19*Pipeline!$D$19*MIN(1,MAX(0,(78-Pipeline!$E$19+1)/MAX(Pipeline!$F$19,1))) -> 5742 | CC12: =Pipeline!$Q$19*Pipeline!$D$19*MIN(1,MAX(0,(79-Pipeline!$E$19+1)/MAX(Pipeline!$F$19,1))) -> 5742 | CD12: =Pipeline!$Q$19*Pipeline!$D$19*MIN(1,MAX(0,(80-Pipeline!$E$19+1)/MAX(Pipeline!$F$19,1))) -> 5742 | CE12: =Pipeline!$Q$19*Pipeline!$D$19*MIN(1,MAX(0,(81-Pipeline!$E$19+1)/MAX(Pipeline!$F$19,1))) -> 5742 | CF12: =Pipeline!$Q$19*Pipeline!$D$19*MIN(1,MAX(0,(82-Pipeline!$E$19+1)/MAX(Pipeline!$F$19,1))) -> 5742 | CG12: =Pipeline!$Q$19*Pipeline!$D$19*MIN(1,MAX(0,(83-Pipeline!$E$19+1)/MAX(Pipeline!$F$19,1))) -> 5742 | CH12: =Pipeline!$Q$19*Pipeline!$D$19*MIN(1,MAX(0,(84-Pipeline!$E$19+1)/MAX(Pipeline!$F$19,1))) -> 5742
A13: · Makro (cash & carry) (€/mes pond.) | C13: =Pipeline!$Q$20*Pipeline!$D$20*MIN(1,MAX(0,(1-Pipeline!$E$20+1)/MAX(Pipeline!$F$20,1))) -> 0 | D13: =Pipeline!$Q$20*Pipeline!$D$20*MIN(1,MAX(0,(2-Pipeline!$E$20+1)/MAX(Pipeline!$F$20,1))) -> 0 | E13: =Pipeline!$Q$20*Pipeline!$D$20*MIN(1,MAX(0,(3-Pipeline!$E$20+1)/MAX(Pipeline!$F$20,1))) -> 0 | F13: =Pipeline!$Q$20*Pipeline!$D$20*MIN(1,MAX(0,(4-Pipeline!$E$20+1)/MAX(Pipeline!$F$20,1))) -> 0 | G13: =Pipeline!$Q$20*Pipeline!$D$20*MIN(1,MAX(0,(5-Pipeline!$E$20+1)/MAX(Pipeline!$F$20,1))) -> 0 | H13: =Pipeline!$Q$20*Pipeline!$D$20*MIN(1,MAX(0,(6-Pipeline!$E$20+1)/MAX(Pipeline!$F$20,1))) -> 0 | I13: =Pipeline!$Q$20*Pipeline!$D$20*MIN(1,MAX(0,(7-Pipeline!$E$20+1)/MAX(Pipeline!$F$20,1))) -> 0 | J13: =Pipeline!$Q$20*Pipeline!$D$20*MIN(1,MAX(0,(8-Pipeline!$E$20+1)/MAX(Pipeline!$F$20,1))) -> 0 | K13: =Pipeline!$Q$20*Pipeline!$D$20*MIN(1,MAX(0,(9-Pipeline!$E$20+1)/MAX(Pipeline!$F$20,1))) -> 0 | L13: =Pipeline!$Q$20*Pipeline!$D$20*MIN(1,MAX(0,(10-Pipeline!$E$20+1)/MAX(Pipeline!$F$20,1))) -> 0 | M13: =Pipeline!$Q$20*Pipeline!$D$20*MIN(1,MAX(0,(11-Pipeline!$E$20+1)/MAX(Pipeline!$F$20,1))) -> 0 | N13: =Pipeline!$Q$20*Pipeline!$D$20*MIN(1,MAX(0,(12-Pipeline!$E$20+1)/MAX(Pipeline!$F$20,1))) -> 978.75 | O13: =Pipeline!$Q$20*Pipeline!$D$20*MIN(1,MAX(0,(13-Pipeline!$E$20+1)/MAX(Pipeline!$F$20,1))) -> 1957.5 | P13: =Pipeline!$Q$20*Pipeline!$D$20*MIN(1,MAX(0,(14-Pipeline!$E$20+1)/MAX(Pipeline!$F$20,1))) -> 2936.25 | Q13: =Pipeline!$Q$20*Pipeline!$D$20*MIN(1,MAX(0,(15-Pipeline!$E$20+1)/MAX(Pipeline!$F$20,1))) -> 3915 | R13: =Pipeline!$Q$20*Pipeline!$D$20*MIN(1,MAX(0,(16-Pipeline!$E$20+1)/MAX(Pipeline!$F$20,1))) -> 4893.75 | S13: =Pipeline!$Q$20*Pipeline!$D$20*MIN(1,MAX(0,(17-Pipeline!$E$20+1)/MAX(Pipeline!$F$20,1))) -> 5872.5 | T13: =Pipeline!$Q$20*Pipeline!$D$20*MIN(1,MAX(0,(18-Pipeline!$E$20+1)/MAX(Pipeline!$F$20,1))) -> 6851.25 | U13: =Pipeline!$Q$20*Pipeline!$D$20*MIN(1,MAX(0,(19-Pipeline!$E$20+1)/MAX(Pipeline!$F$20,1))) -> 7830 | V13: =Pipeline!$Q$20*Pipeline!$D$20*MIN(1,MAX(0,(20-Pipeline!$E$20+1)/MAX(Pipeline!$F$20,1))) -> 8808.75 | W13: =Pipeline!$Q$20*Pipeline!$D$20*MIN(1,MAX(0,(21-Pipeline!$E$20+1)/MAX(Pipeline!$F$20,1))) -> 9787.5 | X13: =Pipeline!$Q$20*Pipeline!$D$20*MIN(1,MAX(0,(22-Pipeline!$E$20+1)/MAX(Pipeline!$F$20,1))) -> 9787.5 | Y13: =Pipeline!$Q$20*Pipeline!$D$20*MIN(1,MAX(0,(23-Pipeline!$E$20+1)/MAX(Pipeline!$F$20,1))) -> 9787.5 | Z13: =Pipeline!$Q$20*Pipeline!$D$20*MIN(1,MAX(0,(24-Pipeline!$E$20+1)/MAX(Pipeline!$F$20,1))) -> 9787.5 | AA13: =Pipeline!$Q$20*Pipeline!$D$20*MIN(1,MAX(0,(25-Pipeline!$E$20+1)/MAX(Pipeline!$F$20,1))) -> 9787.5 | AB13: =Pipeline!$Q$20*Pipeline!$D$20*MIN(1,MAX(0,(26-Pipeline!$E$20+1)/MAX(Pipeline!$F$20,1))) -> 9787.5 | AC13: =Pipeline!$Q$20*Pipeline!$D$20*MIN(1,MAX(0,(27-Pipeline!$E$20+1)/MAX(Pipeline!$F$20,1))) -> 9787.5 | AD13: =Pipeline!$Q$20*Pipeline!$D$20*MIN(1,MAX(0,(28-Pipeline!$E$20+1)/MAX(Pipeline!$F$20,1))) -> 9787.5 | AE13: =Pipeline!$Q$20*Pipeline!$D$20*MIN(1,MAX(0,(29-Pipeline!$E$20+1)/MAX(Pipeline!$F$20,1))) -> 9787.5 | AF13: =Pipeline!$Q$20*Pipeline!$D$20*MIN(1,MAX(0,(30-Pipeline!$E$20+1)/MAX(Pipeline!$F$20,1))) -> 9787.5 | AG13: =Pipeline!$Q$20*Pipeline!$D$20*MIN(1,MAX(0,(31-Pipeline!$E$20+1)/MAX(Pipeline!$F$20,1))) -> 9787.5 | AH13: =Pipeline!$Q$20*Pipeline!$D$20*MIN(1,MAX(0,(32-Pipeline!$E$20+1)/MAX(Pipeline!$F$20,1))) -> 9787.5 | AI13: =Pipeline!$Q$20*Pipeline!$D$20*MIN(1,MAX(0,(33-Pipeline!$E$20+1)/MAX(Pipeline!$F$20,1))) -> 9787.5 | AJ13: =Pipeline!$Q$20*Pipeline!$D$20*MIN(1,MAX(0,(34-Pipeline!$E$20+1)/MAX(Pipeline!$F$20,1))) -> 9787.5 | AK13: =Pipeline!$Q$20*Pipeline!$D$20*MIN(1,MAX(0,(35-Pipeline!$E$20+1)/MAX(Pipeline!$F$20,1))) -> 9787.5 | AL13: =Pipeline!$Q$20*Pipeline!$D$20*MIN(1,MAX(0,(36-Pipeline!$E$20+1)/MAX(Pipeline!$F$20,1))) -> 9787.5 | AM13: =Pipeline!$Q$20*Pipeline!$D$20*MIN(1,MAX(0,(37-Pipeline!$E$20+1)/MAX(Pipeline!$F$20,1))) -> 9787.5 | AN13: =Pipeline!$Q$20*Pipeline!$D$20*MIN(1,MAX(0,(38-Pipeline!$E$20+1)/MAX(Pipeline!$F$20,1))) -> 9787.5 | AO13: =Pipeline!$Q$20*Pipeline!$D$20*MIN(1,MAX(0,(39-Pipeline!$E$20+1)/MAX(Pipeline!$F$20,1))) -> 9787.5 | AP13: =Pipeline!$Q$20*Pipeline!$D$20*MIN(1,MAX(0,(40-Pipeline!$E$20+1)/MAX(Pipeline!$F$20,1))) -> 9787.5 | AQ13: =Pipeline!$Q$20*Pipeline!$D$20*MIN(1,MAX(0,(41-Pipeline!$E$20+1)/MAX(Pipeline!$F$20,1))) -> 9787.5 | AR13: =Pipeline!$Q$20*Pipeline!$D$20*MIN(1,MAX(0,(42-Pipeline!$E$20+1)/MAX(Pipeline!$F$20,1))) -> 9787.5 | AS13: =Pipeline!$Q$20*Pipeline!$D$20*MIN(1,MAX(0,(43-Pipeline!$E$20+1)/MAX(Pipeline!$F$20,1))) -> 9787.5 | AT13: =Pipeline!$Q$20*Pipeline!$D$20*MIN(1,MAX(0,(44-Pipeline!$E$20+1)/MAX(Pipeline!$F$20,1))) -> 9787.5 | AU13: =Pipeline!$Q$20*Pipeline!$D$20*MIN(1,MAX(0,(45-Pipeline!$E$20+1)/MAX(Pipeline!$F$20,1))) -> 9787.5 | AV13: =Pipeline!$Q$20*Pipeline!$D$20*MIN(1,MAX(0,(46-Pipeline!$E$20+1)/MAX(Pipeline!$F$20,1))) -> 9787.5 | AW13: =Pipeline!$Q$20*Pipeline!$D$20*MIN(1,MAX(0,(47-Pipeline!$E$20+1)/MAX(Pipeline!$F$20,1))) -> 9787.5 | AX13: =Pipeline!$Q$20*Pipeline!$D$20*MIN(1,MAX(0,(48-Pipeline!$E$20+1)/MAX(Pipeline!$F$20,1))) -> 9787.5 | AY13: =Pipeline!$Q$20*Pipeline!$D$20*MIN(1,MAX(0,(49-Pipeline!$E$20+1)/MAX(Pipeline!$F$20,1))) -> 9787.5 | AZ13: =Pipeline!$Q$20*Pipeline!$D$20*MIN(1,MAX(0,(50-Pipeline!$E$20+1)/MAX(Pipeline!$F$20,1))) -> 9787.5 | BA13: =Pipeline!$Q$20*Pipeline!$D$20*MIN(1,MAX(0,(51-Pipeline!$E$20+1)/MAX(Pipeline!$F$20,1))) -> 9787.5 | BB13: =Pipeline!$Q$20*Pipeline!$D$20*MIN(1,MAX(0,(52-Pipeline!$E$20+1)/MAX(Pipeline!$F$20,1))) -> 9787.5 | BC13: =Pipeline!$Q$20*Pipeline!$D$20*MIN(1,MAX(0,(53-Pipeline!$E$20+1)/MAX(Pipeline!$F$20,1))) -> 9787.5 | BD13: =Pipeline!$Q$20*Pipeline!$D$20*MIN(1,MAX(0,(54-Pipeline!$E$20+1)/MAX(Pipeline!$F$20,1))) -> 9787.5 | BE13: =Pipeline!$Q$20*Pipeline!$D$20*MIN(1,MAX(0,(55-Pipeline!$E$20+1)/MAX(Pipeline!$F$20,1))) -> 9787.5 | BF13: =Pipeline!$Q$20*Pipeline!$D$20*MIN(1,MAX(0,(56-Pipeline!$E$20+1)/MAX(Pipeline!$F$20,1))) -> 9787.5 | BG13: =Pipeline!$Q$20*Pipeline!$D$20*MIN(1,MAX(0,(57-Pipeline!$E$20+1)/MAX(Pipeline!$F$20,1))) -> 9787.5 | BH13: =Pipeline!$Q$20*Pipeline!$D$20*MIN(1,MAX(0,(58-Pipeline!$E$20+1)/MAX(Pipeline!$F$20,1))) -> 9787.5 | BI13: =Pipeline!$Q$20*Pipeline!$D$20*MIN(1,MAX(0,(59-Pipeline!$E$20+1)/MAX(Pipeline!$F$20,1))) -> 9787.5 | BJ13: =Pipeline!$Q$20*Pipeline!$D$20*MIN(1,MAX(0,(60-Pipeline!$E$20+1)/MAX(Pipeline!$F$20,1))) -> 9787.5 | BK13: =Pipeline!$Q$20*Pipeline!$D$20*MIN(1,MAX(0,(61-Pipeline!$E$20+1)/MAX(Pipeline!$F$20,1))) -> 9787.5 | BL13: =Pipeline!$Q$20*Pipeline!$D$20*MIN(1,MAX(0,(62-Pipeline!$E$20+1)/MAX(Pipeline!$F$20,1))) -> 9787.5 | BM13: =Pipeline!$Q$20*Pipeline!$D$20*MIN(1,MAX(0,(63-Pipeline!$E$20+1)/MAX(Pipeline!$F$20,1))) -> 9787.5 | BN13: =Pipeline!$Q$20*Pipeline!$D$20*MIN(1,MAX(0,(64-Pipeline!$E$20+1)/MAX(Pipeline!$F$20,1))) -> 9787.5 | BO13: =Pipeline!$Q$20*Pipeline!$D$20*MIN(1,MAX(0,(65-Pipeline!$E$20+1)/MAX(Pipeline!$F$20,1))) -> 9787.5 | BP13: =Pipeline!$Q$20*Pipeline!$D$20*MIN(1,MAX(0,(66-Pipeline!$E$20+1)/MAX(Pipeline!$F$20,1))) -> 9787.5 | BQ13: =Pipeline!$Q$20*Pipeline!$D$20*MIN(1,MAX(0,(67-Pipeline!$E$20+1)/MAX(Pipeline!$F$20,1))) -> 9787.5 | BR13: =Pipeline!$Q$20*Pipeline!$D$20*MIN(1,MAX(0,(68-Pipeline!$E$20+1)/MAX(Pipeline!$F$20,1))) -> 9787.5 | BS13: =Pipeline!$Q$20*Pipeline!$D$20*MIN(1,MAX(0,(69-Pipeline!$E$20+1)/MAX(Pipeline!$F$20,1))) -> 9787.5 | BT13: =Pipeline!$Q$20*Pipeline!$D$20*MIN(1,MAX(0,(70-Pipeline!$E$20+1)/MAX(Pipeline!$F$20,1))) -> 9787.5 | BU13: =Pipeline!$Q$20*Pipeline!$D$20*MIN(1,MAX(0,(71-Pipeline!$E$20+1)/MAX(Pipeline!$F$20,1))) -> 9787.5 | BV13: =Pipeline!$Q$20*Pipeline!$D$20*MIN(1,MAX(0,(72-Pipeline!$E$20+1)/MAX(Pipeline!$F$20,1))) -> 9787.5 | BW13: =Pipeline!$Q$20*Pipeline!$D$20*MIN(1,MAX(0,(73-Pipeline!$E$20+1)/MAX(Pipeline!$F$20,1))) -> 9787.5 | BX13: =Pipeline!$Q$20*Pipeline!$D$20*MIN(1,MAX(0,(74-Pipeline!$E$20+1)/MAX(Pipeline!$F$20,1))) -> 9787.5 | BY13: =Pipeline!$Q$20*Pipeline!$D$20*MIN(1,MAX(0,(75-Pipeline!$E$20+1)/MAX(Pipeline!$F$20,1))) -> 9787.5 | BZ13: =Pipeline!$Q$20*Pipeline!$D$20*MIN(1,MAX(0,(76-Pipeline!$E$20+1)/MAX(Pipeline!$F$20,1))) -> 9787.5 | CA13: =Pipeline!$Q$20*Pipeline!$D$20*MIN(1,MAX(0,(77-Pipeline!$E$20+1)/MAX(Pipeline!$F$20,1))) -> 9787.5 | CB13: =Pipeline!$Q$20*Pipeline!$D$20*MIN(1,MAX(0,(78-Pipeline!$E$20+1)/MAX(Pipeline!$F$20,1))) -> 9787.5 | CC13: =Pipeline!$Q$20*Pipeline!$D$20*MIN(1,MAX(0,(79-Pipeline!$E$20+1)/MAX(Pipeline!$F$20,1))) -> 9787.5 | CD13: =Pipeline!$Q$20*Pipeline!$D$20*MIN(1,MAX(0,(80-Pipeline!$E$20+1)/MAX(Pipeline!$F$20,1))) -> 9787.5 | CE13: =Pipeline!$Q$20*Pipeline!$D$20*MIN(1,MAX(0,(81-Pipeline!$E$20+1)/MAX(Pipeline!$F$20,1))) -> 9787.5 | CF13: =Pipeline!$Q$20*Pipeline!$D$20*MIN(1,MAX(0,(82-Pipeline!$E$20+1)/MAX(Pipeline!$F$20,1))) -> 9787.5 | CG13: =Pipeline!$Q$20*Pipeline!$D$20*MIN(1,MAX(0,(83-Pipeline!$E$20+1)/MAX(Pipeline!$F$20,1))) -> 9787.5 | CH13: =Pipeline!$Q$20*Pipeline!$D$20*MIN(1,MAX(0,(84-Pipeline!$E$20+1)/MAX(Pipeline!$F$20,1))) -> 9787.5
A14: · Primaflor (€/mes pond.) | C14: =Pipeline!$Q$21*Pipeline!$D$21*MIN(1,MAX(0,(1-Pipeline!$E$21+1)/MAX(Pipeline!$F$21,1))) -> 0 | D14: =Pipeline!$Q$21*Pipeline!$D$21*MIN(1,MAX(0,(2-Pipeline!$E$21+1)/MAX(Pipeline!$F$21,1))) -> 0 | E14: =Pipeline!$Q$21*Pipeline!$D$21*MIN(1,MAX(0,(3-Pipeline!$E$21+1)/MAX(Pipeline!$F$21,1))) -> 0 | F14: =Pipeline!$Q$21*Pipeline!$D$21*MIN(1,MAX(0,(4-Pipeline!$E$21+1)/MAX(Pipeline!$F$21,1))) -> 0 | G14: =Pipeline!$Q$21*Pipeline!$D$21*MIN(1,MAX(0,(5-Pipeline!$E$21+1)/MAX(Pipeline!$F$21,1))) -> 0 | H14: =Pipeline!$Q$21*Pipeline!$D$21*MIN(1,MAX(0,(6-Pipeline!$E$21+1)/MAX(Pipeline!$F$21,1))) -> 0 | I14: =Pipeline!$Q$21*Pipeline!$D$21*MIN(1,MAX(0,(7-Pipeline!$E$21+1)/MAX(Pipeline!$F$21,1))) -> 0 | J14: =Pipeline!$Q$21*Pipeline!$D$21*MIN(1,MAX(0,(8-Pipeline!$E$21+1)/MAX(Pipeline!$F$21,1))) -> 0 | K14: =Pipeline!$Q$21*Pipeline!$D$21*MIN(1,MAX(0,(9-Pipeline!$E$21+1)/MAX(Pipeline!$F$21,1))) -> 0 | L14: =Pipeline!$Q$21*Pipeline!$D$21*MIN(1,MAX(0,(10-Pipeline!$E$21+1)/MAX(Pipeline!$F$21,1))) -> 0 | M14: =Pipeline!$Q$21*Pipeline!$D$21*MIN(1,MAX(0,(11-Pipeline!$E$21+1)/MAX(Pipeline!$F$21,1))) -> 0 | N14: =Pipeline!$Q$21*Pipeline!$D$21*MIN(1,MAX(0,(12-Pipeline!$E$21+1)/MAX(Pipeline!$F$21,1))) -> 0 | O14: =Pipeline!$Q$21*Pipeline!$D$21*MIN(1,MAX(0,(13-Pipeline!$E$21+1)/MAX(Pipeline!$F$21,1))) -> 0 | P14: =Pipeline!$Q$21*Pipeline!$D$21*MIN(1,MAX(0,(14-Pipeline!$E$21+1)/MAX(Pipeline!$F$21,1))) -> 365.4 | Q14: =Pipeline!$Q$21*Pipeline!$D$21*MIN(1,MAX(0,(15-Pipeline!$E$21+1)/MAX(Pipeline!$F$21,1))) -> 730.8 | R14: =Pipeline!$Q$21*Pipeline!$D$21*MIN(1,MAX(0,(16-Pipeline!$E$21+1)/MAX(Pipeline!$F$21,1))) -> 1096.2 | S14: =Pipeline!$Q$21*Pipeline!$D$21*MIN(1,MAX(0,(17-Pipeline!$E$21+1)/MAX(Pipeline!$F$21,1))) -> 1461.6 | T14: =Pipeline!$Q$21*Pipeline!$D$21*MIN(1,MAX(0,(18-Pipeline!$E$21+1)/MAX(Pipeline!$F$21,1))) -> 1827 | U14: =Pipeline!$Q$21*Pipeline!$D$21*MIN(1,MAX(0,(19-Pipeline!$E$21+1)/MAX(Pipeline!$F$21,1))) -> 2192.4 | V14: =Pipeline!$Q$21*Pipeline!$D$21*MIN(1,MAX(0,(20-Pipeline!$E$21+1)/MAX(Pipeline!$F$21,1))) -> 2557.8 | W14: =Pipeline!$Q$21*Pipeline!$D$21*MIN(1,MAX(0,(21-Pipeline!$E$21+1)/MAX(Pipeline!$F$21,1))) -> 2923.2 | X14: =Pipeline!$Q$21*Pipeline!$D$21*MIN(1,MAX(0,(22-Pipeline!$E$21+1)/MAX(Pipeline!$F$21,1))) -> 3288.6 | Y14: =Pipeline!$Q$21*Pipeline!$D$21*MIN(1,MAX(0,(23-Pipeline!$E$21+1)/MAX(Pipeline!$F$21,1))) -> 3654 | Z14: =Pipeline!$Q$21*Pipeline!$D$21*MIN(1,MAX(0,(24-Pipeline!$E$21+1)/MAX(Pipeline!$F$21,1))) -> 3654 | AA14: =Pipeline!$Q$21*Pipeline!$D$21*MIN(1,MAX(0,(25-Pipeline!$E$21+1)/MAX(Pipeline!$F$21,1))) -> 3654 | AB14: =Pipeline!$Q$21*Pipeline!$D$21*MIN(1,MAX(0,(26-Pipeline!$E$21+1)/MAX(Pipeline!$F$21,1))) -> 3654 | AC14: =Pipeline!$Q$21*Pipeline!$D$21*MIN(1,MAX(0,(27-Pipeline!$E$21+1)/MAX(Pipeline!$F$21,1))) -> 3654 | AD14: =Pipeline!$Q$21*Pipeline!$D$21*MIN(1,MAX(0,(28-Pipeline!$E$21+1)/MAX(Pipeline!$F$21,1))) -> 3654 | AE14: =Pipeline!$Q$21*Pipeline!$D$21*MIN(1,MAX(0,(29-Pipeline!$E$21+1)/MAX(Pipeline!$F$21,1))) -> 3654 | AF14: =Pipeline!$Q$21*Pipeline!$D$21*MIN(1,MAX(0,(30-Pipeline!$E$21+1)/MAX(Pipeline!$F$21,1))) -> 3654 | AG14: =Pipeline!$Q$21*Pipeline!$D$21*MIN(1,MAX(0,(31-Pipeline!$E$21+1)/MAX(Pipeline!$F$21,1))) -> 3654 | AH14: =Pipeline!$Q$21*Pipeline!$D$21*MIN(1,MAX(0,(32-Pipeline!$E$21+1)/MAX(Pipeline!$F$21,1))) -> 3654 | AI14: =Pipeline!$Q$21*Pipeline!$D$21*MIN(1,MAX(0,(33-Pipeline!$E$21+1)/MAX(Pipeline!$F$21,1))) -> 3654 | AJ14: =Pipeline!$Q$21*Pipeline!$D$21*MIN(1,MAX(0,(34-Pipeline!$E$21+1)/MAX(Pipeline!$F$21,1))) -> 3654 | AK14: =Pipeline!$Q$21*Pipeline!$D$21*MIN(1,MAX(0,(35-Pipeline!$E$21+1)/MAX(Pipeline!$F$21,1))) -> 3654 | AL14: =Pipeline!$Q$21*Pipeline!$D$21*MIN(1,MAX(0,(36-Pipeline!$E$21+1)/MAX(Pipeline!$F$21,1))) -> 3654 | AM14: =Pipeline!$Q$21*Pipeline!$D$21*MIN(1,MAX(0,(37-Pipeline!$E$21+1)/MAX(Pipeline!$F$21,1))) -> 3654 | AN14: =Pipeline!$Q$21*Pipeline!$D$21*MIN(1,MAX(0,(38-Pipeline!$E$21+1)/MAX(Pipeline!$F$21,1))) -> 3654 | AO14: =Pipeline!$Q$21*Pipeline!$D$21*MIN(1,MAX(0,(39-Pipeline!$E$21+1)/MAX(Pipeline!$F$21,1))) -> 3654 | AP14: =Pipeline!$Q$21*Pipeline!$D$21*MIN(1,MAX(0,(40-Pipeline!$E$21+1)/MAX(Pipeline!$F$21,1))) -> 3654 | AQ14: =Pipeline!$Q$21*Pipeline!$D$21*MIN(1,MAX(0,(41-Pipeline!$E$21+1)/MAX(Pipeline!$F$21,1))) -> 3654 | AR14: =Pipeline!$Q$21*Pipeline!$D$21*MIN(1,MAX(0,(42-Pipeline!$E$21+1)/MAX(Pipeline!$F$21,1))) -> 3654 | AS14: =Pipeline!$Q$21*Pipeline!$D$21*MIN(1,MAX(0,(43-Pipeline!$E$21+1)/MAX(Pipeline!$F$21,1))) -> 3654 | AT14: =Pipeline!$Q$21*Pipeline!$D$21*MIN(1,MAX(0,(44-Pipeline!$E$21+1)/MAX(Pipeline!$F$21,1))) -> 3654 | AU14: =Pipeline!$Q$21*Pipeline!$D$21*MIN(1,MAX(0,(45-Pipeline!$E$21+1)/MAX(Pipeline!$F$21,1))) -> 3654 | AV14: =Pipeline!$Q$21*Pipeline!$D$21*MIN(1,MAX(0,(46-Pipeline!$E$21+1)/MAX(Pipeline!$F$21,1))) -> 3654 | AW14: =Pipeline!$Q$21*Pipeline!$D$21*MIN(1,MAX(0,(47-Pipeline!$E$21+1)/MAX(Pipeline!$F$21,1))) -> 3654 | AX14: =Pipeline!$Q$21*Pipeline!$D$21*MIN(1,MAX(0,(48-Pipeline!$E$21+1)/MAX(Pipeline!$F$21,1))) -> 3654 | AY14: =Pipeline!$Q$21*Pipeline!$D$21*MIN(1,MAX(0,(49-Pipeline!$E$21+1)/MAX(Pipeline!$F$21,1))) -> 3654 | AZ14: =Pipeline!$Q$21*Pipeline!$D$21*MIN(1,MAX(0,(50-Pipeline!$E$21+1)/MAX(Pipeline!$F$21,1))) -> 3654 | BA14: =Pipeline!$Q$21*Pipeline!$D$21*MIN(1,MAX(0,(51-Pipeline!$E$21+1)/MAX(Pipeline!$F$21,1))) -> 3654 | BB14: =Pipeline!$Q$21*Pipeline!$D$21*MIN(1,MAX(0,(52-Pipeline!$E$21+1)/MAX(Pipeline!$F$21,1))) -> 3654 | BC14: =Pipeline!$Q$21*Pipeline!$D$21*MIN(1,MAX(0,(53-Pipeline!$E$21+1)/MAX(Pipeline!$F$21,1))) -> 3654 | BD14: =Pipeline!$Q$21*Pipeline!$D$21*MIN(1,MAX(0,(54-Pipeline!$E$21+1)/MAX(Pipeline!$F$21,1))) -> 3654 | BE14: =Pipeline!$Q$21*Pipeline!$D$21*MIN(1,MAX(0,(55-Pipeline!$E$21+1)/MAX(Pipeline!$F$21,1))) -> 3654 | BF14: =Pipeline!$Q$21*Pipeline!$D$21*MIN(1,MAX(0,(56-Pipeline!$E$21+1)/MAX(Pipeline!$F$21,1))) -> 3654 | BG14: =Pipeline!$Q$21*Pipeline!$D$21*MIN(1,MAX(0,(57-Pipeline!$E$21+1)/MAX(Pipeline!$F$21,1))) -> 3654 | BH14: =Pipeline!$Q$21*Pipeline!$D$21*MIN(1,MAX(0,(58-Pipeline!$E$21+1)/MAX(Pipeline!$F$21,1))) -> 3654 | BI14: =Pipeline!$Q$21*Pipeline!$D$21*MIN(1,MAX(0,(59-Pipeline!$E$21+1)/MAX(Pipeline!$F$21,1))) -> 3654 | BJ14: =Pipeline!$Q$21*Pipeline!$D$21*MIN(1,MAX(0,(60-Pipeline!$E$21+1)/MAX(Pipeline!$F$21,1))) -> 3654 | BK14: =Pipeline!$Q$21*Pipeline!$D$21*MIN(1,MAX(0,(61-Pipeline!$E$21+1)/MAX(Pipeline!$F$21,1))) -> 3654 | BL14: =Pipeline!$Q$21*Pipeline!$D$21*MIN(1,MAX(0,(62-Pipeline!$E$21+1)/MAX(Pipeline!$F$21,1))) -> 3654 | BM14: =Pipeline!$Q$21*Pipeline!$D$21*MIN(1,MAX(0,(63-Pipeline!$E$21+1)/MAX(Pipeline!$F$21,1))) -> 3654 | BN14: =Pipeline!$Q$21*Pipeline!$D$21*MIN(1,MAX(0,(64-Pipeline!$E$21+1)/MAX(Pipeline!$F$21,1))) -> 3654 | BO14: =Pipeline!$Q$21*Pipeline!$D$21*MIN(1,MAX(0,(65-Pipeline!$E$21+1)/MAX(Pipeline!$F$21,1))) -> 3654 | BP14: =Pipeline!$Q$21*Pipeline!$D$21*MIN(1,MAX(0,(66-Pipeline!$E$21+1)/MAX(Pipeline!$F$21,1))) -> 3654 | BQ14: =Pipeline!$Q$21*Pipeline!$D$21*MIN(1,MAX(0,(67-Pipeline!$E$21+1)/MAX(Pipeline!$F$21,1))) -> 3654 | BR14: =Pipeline!$Q$21*Pipeline!$D$21*MIN(1,MAX(0,(68-Pipeline!$E$21+1)/MAX(Pipeline!$F$21,1))) -> 3654 | BS14: =Pipeline!$Q$21*Pipeline!$D$21*MIN(1,MAX(0,(69-Pipeline!$E$21+1)/MAX(Pipeline!$F$21,1))) -> 3654 | BT14: =Pipeline!$Q$21*Pipeline!$D$21*MIN(1,MAX(0,(70-Pipeline!$E$21+1)/MAX(Pipeline!$F$21,1))) -> 3654 | BU14: =Pipeline!$Q$21*Pipeline!$D$21*MIN(1,MAX(0,(71-Pipeline!$E$21+1)/MAX(Pipeline!$F$21,1))) -> 3654 | BV14: =Pipeline!$Q$21*Pipeline!$D$21*MIN(1,MAX(0,(72-Pipeline!$E$21+1)/MAX(Pipeline!$F$21,1))) -> 3654 | BW14: =Pipeline!$Q$21*Pipeline!$D$21*MIN(1,MAX(0,(73-Pipeline!$E$21+1)/MAX(Pipeline!$F$21,1))) -> 3654 | BX14: =Pipeline!$Q$21*Pipeline!$D$21*MIN(1,MAX(0,(74-Pipeline!$E$21+1)/MAX(Pipeline!$F$21,1))) -> 3654 | BY14: =Pipeline!$Q$21*Pipeline!$D$21*MIN(1,MAX(0,(75-Pipeline!$E$21+1)/MAX(Pipeline!$F$21,1))) -> 3654 | BZ14: =Pipeline!$Q$21*Pipeline!$D$21*MIN(1,MAX(0,(76-Pipeline!$E$21+1)/MAX(Pipeline!$F$21,1))) -> 3654 | CA14: =Pipeline!$Q$21*Pipeline!$D$21*MIN(1,MAX(0,(77-Pipeline!$E$21+1)/MAX(Pipeline!$F$21,1))) -> 3654 | CB14: =Pipeline!$Q$21*Pipeline!$D$21*MIN(1,MAX(0,(78-Pipeline!$E$21+1)/MAX(Pipeline!$F$21,1))) -> 3654 | CC14: =Pipeline!$Q$21*Pipeline!$D$21*MIN(1,MAX(0,(79-Pipeline!$E$21+1)/MAX(Pipeline!$F$21,1))) -> 3654 | CD14: =Pipeline!$Q$21*Pipeline!$D$21*MIN(1,MAX(0,(80-Pipeline!$E$21+1)/MAX(Pipeline!$F$21,1))) -> 3654 | CE14: =Pipeline!$Q$21*Pipeline!$D$21*MIN(1,MAX(0,(81-Pipeline!$E$21+1)/MAX(Pipeline!$F$21,1))) -> 3654 | CF14: =Pipeline!$Q$21*Pipeline!$D$21*MIN(1,MAX(0,(82-Pipeline!$E$21+1)/MAX(Pipeline!$F$21,1))) -> 3654 | CG14: =Pipeline!$Q$21*Pipeline!$D$21*MIN(1,MAX(0,(83-Pipeline!$E$21+1)/MAX(Pipeline!$F$21,1))) -> 3654 | CH14: =Pipeline!$Q$21*Pipeline!$D$21*MIN(1,MAX(0,(84-Pipeline!$E$21+1)/MAX(Pipeline!$F$21,1))) -> 3654
A15: · — hueco nueva cuenta — (€/mes pond.) | C15: =Pipeline!$Q$22*Pipeline!$D$22*MIN(1,MAX(0,(1-Pipeline!$E$22+1)/MAX(Pipeline!$F$22,1))) -> 0 | D15: =Pipeline!$Q$22*Pipeline!$D$22*MIN(1,MAX(0,(2-Pipeline!$E$22+1)/MAX(Pipeline!$F$22,1))) -> 0 | E15: =Pipeline!$Q$22*Pipeline!$D$22*MIN(1,MAX(0,(3-Pipeline!$E$22+1)/MAX(Pipeline!$F$22,1))) -> 0 | F15: =Pipeline!$Q$22*Pipeline!$D$22*MIN(1,MAX(0,(4-Pipeline!$E$22+1)/MAX(Pipeline!$F$22,1))) -> 0 | G15: =Pipeline!$Q$22*Pipeline!$D$22*MIN(1,MAX(0,(5-Pipeline!$E$22+1)/MAX(Pipeline!$F$22,1))) -> 0 | H15: =Pipeline!$Q$22*Pipeline!$D$22*MIN(1,MAX(0,(6-Pipeline!$E$22+1)/MAX(Pipeline!$F$22,1))) -> 0 | I15: =Pipeline!$Q$22*Pipeline!$D$22*MIN(1,MAX(0,(7-Pipeline!$E$22+1)/MAX(Pipeline!$F$22,1))) -> 0 | J15: =Pipeline!$Q$22*Pipeline!$D$22*MIN(1,MAX(0,(8-Pipeline!$E$22+1)/MAX(Pipeline!$F$22,1))) -> 0 | K15: =Pipeline!$Q$22*Pipeline!$D$22*MIN(1,MAX(0,(9-Pipeline!$E$22+1)/MAX(Pipeline!$F$22,1))) -> 0 | L15: =Pipeline!$Q$22*Pipeline!$D$22*MIN(1,MAX(0,(10-Pipeline!$E$22+1)/MAX(Pipeline!$F$22,1))) -> 0 | M15: =Pipeline!$Q$22*Pipeline!$D$22*MIN(1,MAX(0,(11-Pipeline!$E$22+1)/MAX(Pipeline!$F$22,1))) -> 0 | N15: =Pipeline!$Q$22*Pipeline!$D$22*MIN(1,MAX(0,(12-Pipeline!$E$22+1)/MAX(Pipeline!$F$22,1))) -> 0 | O15: =Pipeline!$Q$22*Pipeline!$D$22*MIN(1,MAX(0,(13-Pipeline!$E$22+1)/MAX(Pipeline!$F$22,1))) -> 0 | P15: =Pipeline!$Q$22*Pipeline!$D$22*MIN(1,MAX(0,(14-Pipeline!$E$22+1)/MAX(Pipeline!$F$22,1))) -> 0 | Q15: =Pipeline!$Q$22*Pipeline!$D$22*MIN(1,MAX(0,(15-Pipeline!$E$22+1)/MAX(Pipeline!$F$22,1))) -> 0 | R15: =Pipeline!$Q$22*Pipeline!$D$22*MIN(1,MAX(0,(16-Pipeline!$E$22+1)/MAX(Pipeline!$F$22,1))) -> 0 | S15: =Pipeline!$Q$22*Pipeline!$D$22*MIN(1,MAX(0,(17-Pipeline!$E$22+1)/MAX(Pipeline!$F$22,1))) -> 0 | T15: =Pipeline!$Q$22*Pipeline!$D$22*MIN(1,MAX(0,(18-Pipeline!$E$22+1)/MAX(Pipeline!$F$22,1))) -> 0 | U15: =Pipeline!$Q$22*Pipeline!$D$22*MIN(1,MAX(0,(19-Pipeline!$E$22+1)/MAX(Pipeline!$F$22,1))) -> 0 | V15: =Pipeline!$Q$22*Pipeline!$D$22*MIN(1,MAX(0,(20-Pipeline!$E$22+1)/MAX(Pipeline!$F$22,1))) -> 0 | W15: =Pipeline!$Q$22*Pipeline!$D$22*MIN(1,MAX(0,(21-Pipeline!$E$22+1)/MAX(Pipeline!$F$22,1))) -> 0 | X15: =Pipeline!$Q$22*Pipeline!$D$22*MIN(1,MAX(0,(22-Pipeline!$E$22+1)/MAX(Pipeline!$F$22,1))) -> 0 | Y15: =Pipeline!$Q$22*Pipeline!$D$22*MIN(1,MAX(0,(23-Pipeline!$E$22+1)/MAX(Pipeline!$F$22,1))) -> 0 | Z15: =Pipeline!$Q$22*Pipeline!$D$22*MIN(1,MAX(0,(24-Pipeline!$E$22+1)/MAX(Pipeline!$F$22,1))) -> 0 | AA15: =Pipeline!$Q$22*Pipeline!$D$22*MIN(1,MAX(0,(25-Pipeline!$E$22+1)/MAX(Pipeline!$F$22,1))) -> 0 | AB15: =Pipeline!$Q$22*Pipeline!$D$22*MIN(1,MAX(0,(26-Pipeline!$E$22+1)/MAX(Pipeline!$F$22,1))) -> 0 | AC15: =Pipeline!$Q$22*Pipeline!$D$22*MIN(1,MAX(0,(27-Pipeline!$E$22+1)/MAX(Pipeline!$F$22,1))) -> 0 | AD15: =Pipeline!$Q$22*Pipeline!$D$22*MIN(1,MAX(0,(28-Pipeline!$E$22+1)/MAX(Pipeline!$F$22,1))) -> 0 | AE15: =Pipeline!$Q$22*Pipeline!$D$22*MIN(1,MAX(0,(29-Pipeline!$E$22+1)/MAX(Pipeline!$F$22,1))) -> 0 | AF15: =Pipeline!$Q$22*Pipeline!$D$22*MIN(1,MAX(0,(30-Pipeline!$E$22+1)/MAX(Pipeline!$F$22,1))) -> 0 | AG15: =Pipeline!$Q$22*Pipeline!$D$22*MIN(1,MAX(0,(31-Pipeline!$E$22+1)/MAX(Pipeline!$F$22,1))) -> 0 | AH15: =Pipeline!$Q$22*Pipeline!$D$22*MIN(1,MAX(0,(32-Pipeline!$E$22+1)/MAX(Pipeline!$F$22,1))) -> 0 | AI15: =Pipeline!$Q$22*Pipeline!$D$22*MIN(1,MAX(0,(33-Pipeline!$E$22+1)/MAX(Pipeline!$F$22,1))) -> 0 | AJ15: =Pipeline!$Q$22*Pipeline!$D$22*MIN(1,MAX(0,(34-Pipeline!$E$22+1)/MAX(Pipeline!$F$22,1))) -> 0 | AK15: =Pipeline!$Q$22*Pipeline!$D$22*MIN(1,MAX(0,(35-Pipeline!$E$22+1)/MAX(Pipeline!$F$22,1))) -> 0 | AL15: =Pipeline!$Q$22*Pipeline!$D$22*MIN(1,MAX(0,(36-Pipeline!$E$22+1)/MAX(Pipeline!$F$22,1))) -> 0 | AM15: =Pipeline!$Q$22*Pipeline!$D$22*MIN(1,MAX(0,(37-Pipeline!$E$22+1)/MAX(Pipeline!$F$22,1))) -> 0 | AN15: =Pipeline!$Q$22*Pipeline!$D$22*MIN(1,MAX(0,(38-Pipeline!$E$22+1)/MAX(Pipeline!$F$22,1))) -> 0 | AO15: =Pipeline!$Q$22*Pipeline!$D$22*MIN(1,MAX(0,(39-Pipeline!$E$22+1)/MAX(Pipeline!$F$22,1))) -> 0 | AP15: =Pipeline!$Q$22*Pipeline!$D$22*MIN(1,MAX(0,(40-Pipeline!$E$22+1)/MAX(Pipeline!$F$22,1))) -> 0 | AQ15: =Pipeline!$Q$22*Pipeline!$D$22*MIN(1,MAX(0,(41-Pipeline!$E$22+1)/MAX(Pipeline!$F$22,1))) -> 0 | AR15: =Pipeline!$Q$22*Pipeline!$D$22*MIN(1,MAX(0,(42-Pipeline!$E$22+1)/MAX(Pipeline!$F$22,1))) -> 0 | AS15: =Pipeline!$Q$22*Pipeline!$D$22*MIN(1,MAX(0,(43-Pipeline!$E$22+1)/MAX(Pipeline!$F$22,1))) -> 0 | AT15: =Pipeline!$Q$22*Pipeline!$D$22*MIN(1,MAX(0,(44-Pipeline!$E$22+1)/MAX(Pipeline!$F$22,1))) -> 0 | AU15: =Pipeline!$Q$22*Pipeline!$D$22*MIN(1,MAX(0,(45-Pipeline!$E$22+1)/MAX(Pipeline!$F$22,1))) -> 0 | AV15: =Pipeline!$Q$22*Pipeline!$D$22*MIN(1,MAX(0,(46-Pipeline!$E$22+1)/MAX(Pipeline!$F$22,1))) -> 0 | AW15: =Pipeline!$Q$22*Pipeline!$D$22*MIN(1,MAX(0,(47-Pipeline!$E$22+1)/MAX(Pipeline!$F$22,1))) -> 0 | AX15: =Pipeline!$Q$22*Pipeline!$D$22*MIN(1,MAX(0,(48-Pipeline!$E$22+1)/MAX(Pipeline!$F$22,1))) -> 0 | AY15: =Pipeline!$Q$22*Pipeline!$D$22*MIN(1,MAX(0,(49-Pipeline!$E$22+1)/MAX(Pipeline!$F$22,1))) -> 0 | AZ15: =Pipeline!$Q$22*Pipeline!$D$22*MIN(1,MAX(0,(50-Pipeline!$E$22+1)/MAX(Pipeline!$F$22,1))) -> 0 | BA15: =Pipeline!$Q$22*Pipeline!$D$22*MIN(1,MAX(0,(51-Pipeline!$E$22+1)/MAX(Pipeline!$F$22,1))) -> 0 | BB15: =Pipeline!$Q$22*Pipeline!$D$22*MIN(1,MAX(0,(52-Pipeline!$E$22+1)/MAX(Pipeline!$F$22,1))) -> 0 | BC15: =Pipeline!$Q$22*Pipeline!$D$22*MIN(1,MAX(0,(53-Pipeline!$E$22+1)/MAX(Pipeline!$F$22,1))) -> 0 | BD15: =Pipeline!$Q$22*Pipeline!$D$22*MIN(1,MAX(0,(54-Pipeline!$E$22+1)/MAX(Pipeline!$F$22,1))) -> 0 | BE15: =Pipeline!$Q$22*Pipeline!$D$22*MIN(1,MAX(0,(55-Pipeline!$E$22+1)/MAX(Pipeline!$F$22,1))) -> 0 | BF15: =Pipeline!$Q$22*Pipeline!$D$22*MIN(1,MAX(0,(56-Pipeline!$E$22+1)/MAX(Pipeline!$F$22,1))) -> 0 | BG15: =Pipeline!$Q$22*Pipeline!$D$22*MIN(1,MAX(0,(57-Pipeline!$E$22+1)/MAX(Pipeline!$F$22,1))) -> 0 | BH15: =Pipeline!$Q$22*Pipeline!$D$22*MIN(1,MAX(0,(58-Pipeline!$E$22+1)/MAX(Pipeline!$F$22,1))) -> 0 | BI15: =Pipeline!$Q$22*Pipeline!$D$22*MIN(1,MAX(0,(59-Pipeline!$E$22+1)/MAX(Pipeline!$F$22,1))) -> 0 | BJ15: =Pipeline!$Q$22*Pipeline!$D$22*MIN(1,MAX(0,(60-Pipeline!$E$22+1)/MAX(Pipeline!$F$22,1))) -> 0 | BK15: =Pipeline!$Q$22*Pipeline!$D$22*MIN(1,MAX(0,(61-Pipeline!$E$22+1)/MAX(Pipeline!$F$22,1))) -> 0 | BL15: =Pipeline!$Q$22*Pipeline!$D$22*MIN(1,MAX(0,(62-Pipeline!$E$22+1)/MAX(Pipeline!$F$22,1))) -> 0 | BM15: =Pipeline!$Q$22*Pipeline!$D$22*MIN(1,MAX(0,(63-Pipeline!$E$22+1)/MAX(Pipeline!$F$22,1))) -> 0 | BN15: =Pipeline!$Q$22*Pipeline!$D$22*MIN(1,MAX(0,(64-Pipeline!$E$22+1)/MAX(Pipeline!$F$22,1))) -> 0 | BO15: =Pipeline!$Q$22*Pipeline!$D$22*MIN(1,MAX(0,(65-Pipeline!$E$22+1)/MAX(Pipeline!$F$22,1))) -> 0 | BP15: =Pipeline!$Q$22*Pipeline!$D$22*MIN(1,MAX(0,(66-Pipeline!$E$22+1)/MAX(Pipeline!$F$22,1))) -> 0 | BQ15: =Pipeline!$Q$22*Pipeline!$D$22*MIN(1,MAX(0,(67-Pipeline!$E$22+1)/MAX(Pipeline!$F$22,1))) -> 0 | BR15: =Pipeline!$Q$22*Pipeline!$D$22*MIN(1,MAX(0,(68-Pipeline!$E$22+1)/MAX(Pipeline!$F$22,1))) -> 0 | BS15: =Pipeline!$Q$22*Pipeline!$D$22*MIN(1,MAX(0,(69-Pipeline!$E$22+1)/MAX(Pipeline!$F$22,1))) -> 0 | BT15: =Pipeline!$Q$22*Pipeline!$D$22*MIN(1,MAX(0,(70-Pipeline!$E$22+1)/MAX(Pipeline!$F$22,1))) -> 0 | BU15: =Pipeline!$Q$22*Pipeline!$D$22*MIN(1,MAX(0,(71-Pipeline!$E$22+1)/MAX(Pipeline!$F$22,1))) -> 0 | BV15: =Pipeline!$Q$22*Pipeline!$D$22*MIN(1,MAX(0,(72-Pipeline!$E$22+1)/MAX(Pipeline!$F$22,1))) -> 0 | BW15: =Pipeline!$Q$22*Pipeline!$D$22*MIN(1,MAX(0,(73-Pipeline!$E$22+1)/MAX(Pipeline!$F$22,1))) -> 0 | BX15: =Pipeline!$Q$22*Pipeline!$D$22*MIN(1,MAX(0,(74-Pipeline!$E$22+1)/MAX(Pipeline!$F$22,1))) -> 0 | BY15: =Pipeline!$Q$22*Pipeline!$D$22*MIN(1,MAX(0,(75-Pipeline!$E$22+1)/MAX(Pipeline!$F$22,1))) -> 0 | BZ15: =Pipeline!$Q$22*Pipeline!$D$22*MIN(1,MAX(0,(76-Pipeline!$E$22+1)/MAX(Pipeline!$F$22,1))) -> 0 | CA15: =Pipeline!$Q$22*Pipeline!$D$22*MIN(1,MAX(0,(77-Pipeline!$E$22+1)/MAX(Pipeline!$F$22,1))) -> 0 | CB15: =Pipeline!$Q$22*Pipeline!$D$22*MIN(1,MAX(0,(78-Pipeline!$E$22+1)/MAX(Pipeline!$F$22,1))) -> 0 | CC15: =Pipeline!$Q$22*Pipeline!$D$22*MIN(1,MAX(0,(79-Pipeline!$E$22+1)/MAX(Pipeline!$F$22,1))) -> 0 | CD15: =Pipeline!$Q$22*Pipeline!$D$22*MIN(1,MAX(0,(80-Pipeline!$E$22+1)/MAX(Pipeline!$F$22,1))) -> 0 | CE15: =Pipeline!$Q$22*Pipeline!$D$22*MIN(1,MAX(0,(81-Pipeline!$E$22+1)/MAX(Pipeline!$F$22,1))) -> 0 | CF15: =Pipeline!$Q$22*Pipeline!$D$22*MIN(1,MAX(0,(82-Pipeline!$E$22+1)/MAX(Pipeline!$F$22,1))) -> 0 | CG15: =Pipeline!$Q$22*Pipeline!$D$22*MIN(1,MAX(0,(83-Pipeline!$E$22+1)/MAX(Pipeline!$F$22,1))) -> 0 | CH15: =Pipeline!$Q$22*Pipeline!$D$22*MIN(1,MAX(0,(84-Pipeline!$E$22+1)/MAX(Pipeline!$F$22,1))) -> 0
A16: DEMANDA IDENTIFICADA — ingresos a tarifa mayorista (€/mes) | C16: =SUM(C9:C15) -> 1033.125 | D16: =SUM(D9:D15) -> 2144.55 | E16: =SUM(E9:E15) -> 4457.6625 | F16: =SUM(F9:F15) -> 5737.65 | G16: =SUM(G9:G15) -> 6939.3375 | H16: =SUM(H9:H15) -> 8858.775 | I16: =SUM(I9:I15) -> 10778.212 | J16: =SUM(J9:J15) -> 12697.65 | ... CH16: =SUM(CH9:CH15) -> 32131.275
